Workbook

Sheet Pokemon
A1: key | B1: en | C1: ja | D1: fr | E1: de | F1: es | G1: it | H1: ko | I1: zh_HK | J1: zh | K1: es_149
A2: =CONCATENATE("NAME_PkMn_", UPPER(B2)) | B2: Bulbasaur | C2: フシギダネ | D2: Bulbizarre | E2: Bisasam | F2: =B2 | G2: =B2 | H2: 이상해씨 | I2: =IFERROR(__xludf.DUMMYFUNCTION("GOOGLETRANSLATE(J2,""zh_HANS"",""zh_HANT"")"),"妙蛙種子") | J2: 妙蛙种子 | K2: =F2
A3: =CONCATENATE("NAME_PkMn_", UPPER(B3)) | B3: Ivysaur | C3: フシギソウ | D3: Herbizarre | E3: Bisaknosp | F3: =B3 | G3: =B3 | H3: 이상해풀 | I3: =J3 | J3: 妙蛙草 | K3: =F3
A4: =CONCATENATE("NAME_PkMn_", UPPER(B4)) | B4: Venusaur | C4: フシギバナ | D4: Florizarre | E4: Bisaflor | F4: =B4 | G4: =B4 | H4: 이상해꽃 | I4: =J4 | J4: 妙蛙花 | K4: =F4
A5: =CONCATENATE("NAME_PkMn_", UPPER(B5)) | B5: Charmander | C5: ヒトカゲ | D5: Salamèche | E5: Glumanda | F5: =B5 | G5: =B5 | H5: 파이리 | I5: =IFERROR(__xludf.DUMMYFUNCTION("GOOGLETRANSLATE(J5,""zh_HANS"",""zh_HANT"")"),"小火龍") | J5: 小火龙 | K5: =F5
A6: =CONCATENATE("NAME_PkMn_", UPPER(B6)) | B6: Charmeleon | C6: リザード | D6: Reptincel | E6: Glutexo | F6: =B6 | G6: =B6 | H6: 리자드 | I6: =IFERROR(__xludf.DUMMYFUNCTION("GOOGLETRANSLATE(J6,""zh_HANS"",""zh_HANT"")"),"火恐龍") | J6: 火恐龙 | K6: =F6
A7: =CONCATENATE("NAME_PkMn_", UPPER(B7)) | B7: Charizard | C7: リザードン | D7: Dracaufeu | E7: Glurak | F7: =B7 | G7: =B7 | H7: 리자몽 | I7: =IFERROR(__xludf.DUMMYFUNCTION("GOOGLETRANSLATE(J7,""zh_HANS"",""zh_HANT"")"),"噴火龍") | J7: 喷火龙 | K7: =F7
A8: =CONCATENATE("NAME_PkMn_", UPPER(B8)) | B8: Squirtle | C8: ゼニガメ | D8: Carapuce | E8: Schiggy | F8: =B8 | G8: =B8 | H8: 꼬부기 | I8: =IFERROR(__xludf.DUMMYFUNCTION("GOOGLETRANSLATE(J8,""zh_HANS"",""zh_HANT"")"),"傑尼龜") | J8: 杰尼龟 | K8: =F8
A9: =CONCATENATE("NAME_PkMn_", UPPER(B9)) | B9: Wartortle | C9: カメール | D9: Carabaffe | E9: Schillok | F9: =B9 | G9: =B9 | H9: 어니부기 | I9: =IFERROR(__xludf.DUMMYFUNCTION("GOOGLETRANSLATE(J9,""zh_HANS"",""zh_HANT"")"),"卡咪龜") | J9: 卡咪龟 | K9: =F9
A10: =CONCATENATE("NAME_PkMn_", UPPER(B10)) | B10: Blastoise | C10: カメックス | D10: Tortank | E10: Turtok | F10: =B10 | G10: =B10 | H10: 거북왕 | I10: =IFERROR(__xludf.DUMMYFUNCTION("GOOGLETRANSLATE(J10,""zh_HANS"",""zh_HANT"")"),"水箭龜") | J10: 水箭龟 | K10: =F10
A11: =CONCATENATE("NAME_PkMn_", UPPER(B11)) | B11: Caterpie | C11: キャタピー | D11: Chenipan | E11: Raupy | F11: =B11 | G11: =B11 | H11: 캐터피 | I11: =IFERROR(__xludf.DUMMYFUNCTION("GOOGLETRANSLATE(J11,""zh_HANS"",""zh_HANT"")"),"綠毛蟲") | J11: 绿毛虫 | K11: =F11
A12: =CONCATENATE("NAME_PkMn_", UPPER(B12)) | B12: Metapod | C12: トランセル | D12: Chrysacier | E12: Safcon | F12: =B12 | G12: =B12 | H12: 단데기 | I12: 鐵甲蛹 | J12: =IFERROR(__xludf.DUMMYFUNCTION("GOOGLETRANSLATE(I12,""zh_HANT"",""zh_HANS"")"),"铁甲蛹") | K12: =F12
A13: =CONCATENATE("NAME_PkMn_", UPPER(B13)) | B13: Butterfree | C13: バタフリー | D13: Papilusion | E13: Smettbo | F13: =B13 | G13: =B13 | H13: 버터플 | I13: 巴大蝶 | J13: =I13 | K13: =F13
A14: =CONCATENATE("NAME_PkMn_", UPPER(B14)) | B14: Weedle | C14: ビードル | D14: Aspicot | E14: Hornliu | F14: =B14 | G14: =B14 | H14: 뿔충이 | I14: 獨角蟲 | J14: =IFERROR(__xludf.DUMMYFUNCTION("GOOGLETRANSLATE(I14,""zh_HANT"",""zh_HANS"")"),"独角虫") | K14: =F14
A15: =CONCATENATE("NAME_PkMn_", UPPER(B15)) | B15: Kakuna | C15: コクーン | D15: Coconfort | E15: Kokuna | F15: =B15 | G15: =B15 | H15: 딱충이 | I15: 獨角蟲 | J15: =IFERROR(__xludf.DUMMYFUNCTION("GOOGLETRANSLATE(I15,""zh_HANT"",""zh_HANS"")"),"独角虫") | K15: =F15
A16: =CONCATENATE("NAME_PkMn_", UPPER(B16)) | B16: Beedrill | C16: スピアー | D16: Dardargnan | E16: Bibor | F16: =B16 | G16: =B16 | H16: 독침붕 | I16: =J16 | J16: 大针蜂 | K16: =F16
A17: =CONCATENATE("NAME_PkMn_", UPPER(B17)) | B17: Pidgey | C17: ポッポ | D17: Roucool | E17: Taubsi | F17: =B17 | G17: =B17 | H17: 구구 | I17: 波波 | J17: =I17 | K17: =F17
A18: =CONCATENATE("NAME_PkMn_", UPPER(B18)) | B18: Pidgeotto | C18: ピジョン | D18: Roucoups | E18: Tauboga | F18: =B18 | G18: =B18 | H18: 피죤 | I18: 比比鳥 | J18: =IFERROR(__xludf.DUMMYFUNCTION("GOOGLETRANSLATE(I18,""zh_HANT"",""zh_HANS"")"),"比比鸟") | K18: =F18
A19: =CONCATENATE("NAME_PkMn_", UPPER(B19)) | B19: Pidgeot | C19: ピジョット | D19: Roucarnage | E19: Tauboss | F19: =B19 | G19: =B19 | H19: 피죤투 | I19: =IFERROR(__xludf.DUMMYFUNCTION("GOOGLETRANSLATE(J19,""zh_HANS"",""zh_HANT"")"),"大比鳥") | J19: 大比鸟 | K19: =F19
A20: =CONCATENATE("NAME_PkMn_", UPPER(B20)) | B20: Rattata | C20: コラッタ | D20: =B20 | E20: Rattfratz | F20: =B20 | G20: =B20 | H20: 꼬렛 | I20: 小拉達 | J20: =IFERROR(__xludf.DUMMYFUNCTION("GOOGLETRANSLATE(I20,""zh_HANT"",""zh_HANS"")"),"小拉达") | K20: =F20
A21: =CONCATENATE("NAME_PkMn_", UPPER(B21)) | B21: Raticate | C21: ラッタ | D21: Rattatac | E21: Rattikarl | F21: =B21 | G21: =B21 | H21: 레트라 | I21: 拉達 | J21: =IFERROR(__xludf.DUMMYFUNCTION("GOOGLETRANSLATE(I21,""zh_HANT"",""zh_HANS"")"),"拉达") | K21: =F21
A22: =CONCATENATE("NAME_PkMn_", UPPER(B22)) | B22: Spearow | C22: オニスズメ | D22: Piafabec | E22: Habitak | F22: =B22 | G22: =B22 | H22: 깨비참 | I22: 烈雀 | J22: =I22 | K22: =F22
A23: =CONCATENATE("NAME_PkMn_", UPPER(B23)) | B23: Fearow | C23: オニドリル | D23: Rapasdepic | E23: Ibitak | F23: =B23 | G23: =B23 | H23: 깨비드릴조 | I23: 大嘴雀 | J23: =I23 | K23: =F23
A24: =CONCATENATE("NAME_PkMn_", UPPER(B24)) | B24: Ekans | C24: アーボ | D24: Abo | E24: Rettan | F24: =B24 | G24: =B24 | H24: 아보 | I24: 阿柏蛇 | J24: =I24 | K24: =F24
A25: =CONCATENATE("NAME_PkMn_", UPPER(B25)) | B25: Arbok | C25: アーボック | D25: =B25 | E25: =B25 | F25: =B25 | G25: =B25 | H25: 아보크 | I25: 阿柏怪 | J25: =I25 | K25: =F25
A26: =CONCATENATE("NAME_PkMn_", UPPER(B26)) | B26: Pikachu | C26: ピカチュウ | D26: =B26 | E26: =B26 | F26: =B26 | G26: =B26 | H26: 피카츄 | I26: =J26 | J26: 皮卡丘 | K26: =F26
A27: =CONCATENATE("NAME_PkMn_", UPPER(B27)) | B27: Raichu | C27: ライチュウ | D27: =B27 | E27: =B27 | F27: =B27 | G27: =B27 | H27: 라이츄 | I27: 雷丘 | J27: =I27 | K27: =F27
A28: =CONCATENATE("NAME_PkMn_", UPPER(B28)) | B28: Sandshrew | C28: サンド | D28: Sabelette | E28: Sandan | F28: =B28 | G28: =B28 | H28: 모래두지 | I28: 穿山鼠 | J28: =I28 | K28: =F28
A29: =CONCATENATE("NAME_PkMn_", UPPER(B29)) | B29: Sandslash | C29: サンドパン | D29: Sablaireau | E29: Sandamer | F29: =B29 | G29: =B29 | H29: 고지 | I29: 穿山王 | J29: =I29 | K29: =F29
A30: NAME_PkMn_NIDORAN-F | B30: =CONCATENATE("Nidoran", CHAR(9792)) | C30: ニドラン♀ | D30: =B30 | E30: Nidoran-W | F30: =B30 | G30: =B30 | H30: 니드런♀ | I30: 尼多蘭 | J30: =IFERROR(__xludf.DUMMYFUNCTION("GOOGLETRANSLATE(I30,""zh_HANT"",""zh_HANS"")"),"尼多兰") | K30: =F30
A31: =CONCATENATE("NAME_PkMn_", UPPER(B31)) | B31: Nidorina | C31: ニドリーナ | D31: =B31 | E31: =B31 | F31: =B31 | G31: =B31 | H31: 니드리나 | I31: 尼多娜 | J31: =I31 | K31: =F31
A32: =CONCATENATE("NAME_PkMn_", UPPER(B32)) | B32: Nidoqueen | C32: ニドクイン | D32: =B32 | E32: =B32 | F32: =B32 | G32: =B32 | H32: 니드퀸 | I32: 尼多后 | J32: =I32 | K32: =F32
A33: NAME_PkMn_NIDORAN-M | B33: =CONCATENATE("Nidoran", CHAR(9794)) | C33: ニドラン♂ | D33: =B33 | E33: Nidoran-M | F33: =B33 | G33: =B33 | H33: 니드런♂ | I33: 尼多朗 | J33: =I33 | K33: =F33
A34: =CONCATENATE("NAME_PkMn_", UPPER(B34)) | B34: Nidorino | C34: ニドリーノ | D34: =B34 | E34: =B34 | F34: =B34 | G34: =B34 | H34: 니드리노 | I34: 尼多力諾 | J34: =IFERROR(__xludf.DUMMYFUNCTION("GOOGLETRANSLATE(I34,""zh_HANT"",""zh_HANS"")"),"尼多力诺") | K34: =F34
A35: =CONCATENATE("NAME_PkMn_", UPPER(B35)) | B35: Nidoking | C35: ニドキング | D35: =B35 | E35: =B35 | F35: =B35 | G35: =B35 | H35: 니드킹 | I35: 尼多王 | J35: =I35 | K35: =F35
A36: =CONCATENATE("NAME_PkMn_", UPPER(B36)) | B36: Clefairy | C36: ピッピ | D36: Mélofée | E36: Piepi | F36: =B36 | G36: =B36 | H36: 삐삐 | I36: 皮皮 | J36: =I36 | K36: =F36
A37: =CONCATENATE("NAME_PkMn_", UPPER(B37)) | B37: Clefable | C37: ピクシー | D37: Mélodelfe | E37: Pixi | F37: =B37 | G37: =B37 | H37: 픽시 | I37: 皮可西 | J37: =I37 | K37: =F37
A38: =CONCATENATE("NAME_PkMn_", UPPER(B38)) | B38: Vulpix | C38: ロコン | D38: Goupix | E38: =B38 | F38: =B38 | G38: =B38 | H38: 식스테일 | I38: 六尾 | J38: =I38 | K38: =F38
A39: =CONCATENATE("NAME_PkMn_", UPPER(B39)) | B39: Ninetales | C39: キュウコン | D39: Feunard | E39: Vulnona | F39: =B39 | G39: =B39 | H39: 나인테일 | I39: 九尾 | J39: =I39 | K39: =F39
A40: =CONCATENATE("NAME_PkMn_", UPPER(B40)) | B40: Jigglypuff | C40: プリン | D40: Rondoudou | E40: Pummeluff | F40: =B40 | G40: =B40 | H40: 푸린 | I40: 胖丁 | J40: =I40 | K40: =F40
A41: =CONCATENATE("NAME_PkMn_", UPPER(B41)) | B41: Wigglytuff | C41: プクリン | D41: Grodoudou | E41: Knuddeluff | F41: =B41 | G41: =B41 | H41: 푸크린 | I41: 胖可丁 | J41: =I41 | K41: =F41
A42: =CONCATENATE("NAME_PkMn_", UPPER(B42)) | B42: Zubat | C42: ズバット | D42: Nosferapti | E42: =B42 | F42: =B42 | G42: =B42 | H42: 주뱃 | I42: 超音蝠 | J42: =I42 | K42: =F42
A43: =CONCATENATE("NAME_PkMn_", UPPER(B43)) | B43: Golbat | C43: ゴルバット | D43: Nosferalto | E43: =B43 | F43: =B43 | G43: =B43 | H43: 골뱃 | I43: 大嘴蝠 | J43: =I43 | K43: =F43
A44: =CONCATENATE("NAME_PkMn_", UPPER(B44)) | B44: Oddish | C44: ナゾノクサ | D44: Mystherbe | E44: Myrapla | F44: =B44 | G44: =B44 | H44: 뚜벅쵸 | I44: 走路草 | J44: =I44 | K44: =F44
A45: =CONCATENATE("NAME_PkMn_", UPPER(B45)) | B45: Gloom | C45: クサイハナ | D45: Ortide | E45: Duflor | F45: =B45 | G45: =B45 | H45: 냄새꼬 | I45: 臭臭花 | J45: =I45 | K45: =F45
A46: =CONCATENATE("NAME_PkMn_", UPPER(B46)) | B46: Vileplume | C46: ラフレシア | D46: Rafflesia | E46: Giflor | F46: =B46 | G46: =B46 | H46: 라플레시아 | I46: 霸王花 | J46: =I46 | K46: =F46
A47: =CONCATENATE("NAME_PkMn_", UPPER(B47)) | B47: Paras | C47: パラス | D47: =B47 | E47: =B47 | F47: =B47 | G47: =B47 | H47: 파라스 | I47: 派拉斯 | J47: =I47 | K47: =F47
A48: =CONCATENATE("NAME_PkMn_", UPPER(B48)) | B48: Parasect | C48: パラセクト | D48: =B48 | E48: Parasek | F48: =B48 | G48: =B48 | H48: 파라섹트 | I48: 派拉斯特 | J48: =I48 | K48: =F48
A49: =CONCATENATE("NAME_PkMn_", UPPER(B49)) | B49: Venonat | C49: コンパン | D49: Mimitoss | E49: Bluzuk | F49: =B49 | G49: =B49 | H49: 콘팡 | I49: 毛球 | J49: =I49 | K49: =F49
A50: =CONCATENATE("NAME_PkMn_", UPPER(B50)) | B50: Venomoth | C50: モルフォン | D50: Aéromite | E50: Omot | F50: =B50 | G50: =B50 | H50: 도나리 | I50: 摩魯蛾 | J50: =IFERROR(__xludf.DUMMYFUNCTION("GOOGLETRANSLATE(I50,""zh_HANT"",""zh_HANS"")"),"摩鲁蛾") | K50: =F50
A51: =CONCATENATE("NAME_PkMn_", UPPER(B51)) | B51: Diglett | C51: ヂィグダ | D51: Taupiqueur | E51: Digda | F51: =B51 | G51: =B51 | H51: 디그다 | I51: 地鼠 | J51: =I51 | K51: =F51
A52: =CONCATENATE("NAME_PkMn_", UPPER(B52)) | B52: Dugtrio | C52: ダグトリオ | D52: Triopikeur | E52: Digdri | F52: =B52 | G52: =B52 | H52: 닥트리오 | I52: 三地鼠 | J52: =I52 | K52: =F52
A53: =CONCATENATE("NAME_PkMn_", UPPER(B53)) | B53: Meowth | C53: ニャース | D53: Miaouss | E53: Mauzi | F53: =B53 | G53: =B53 | H53: 나옹 | I53: 喵喵 | J53: =I53 | K53: =F53
A54: =CONCATENATE("NAME_PkMn_", UPPER(B54)) | B54: Persian | C54: ペルシアン | D54: =B54 | E54: Snobilikat | F54: =B54 | G54: =B54 | H54: 페르시온 | I54: 貓老大 | J54: =I54 | K54: =F54
A55: =CONCATENATE("NAME_PkMn_", UPPER(B55)) | B55: Psyduck | C55: コダック | D55: Psykokwak | E55: Enton | F55: =B55 | G55: =B55 | H55: 고라파덕 | I55: 可達鴨 | J55: =IFERROR(__xludf.DUMMYFUNCTION("GOOGLETRANSLATE(I55,""zh_HANT"",""zh_HANS"")"),"可达鸭") | K55: =F55
A56: =CONCATENATE("NAME_PkMn_", UPPER(B56)) | B56: Golduck | C56: ゴルダック | D56: Akwakwak | E56: Entoron | F56: =B56 | G56: =B56 | H56: 골덕 | I56: 哥達鴨 | J56: =IFERROR(__xludf.DUMMYFUNCTION("GOOGLETRANSLATE(I56,""zh_HANT"",""zh_HANS"")"),"哥达鸭") | K56: =F56
A57: =CONCATENATE("NAME_PkMn_", UPPER(B57)) | B57: Mankey | C57: マンキー | D57: Férosinge | E57: Mankey | F57: =B57 | G57: =B57 | H57: 망키 | I57: 猴怪 | J57: =I57 | K57: =F57
A58: =CONCATENATE("NAME_PkMn_", UPPER(B58)) | B58: Primeape | C58: オコリザル | D58: Colosinge | E58: Rasaff | F58: =B58 | G58: =B58 | H58: 성원숭 | I58: 火爆猴 | J58: =IFERROR(__xludf.DUMMYFUNCTION("GOOGLETRANSLATE(I58,""zh_HANT"",""zh_HANS"")"),"火爆猴") | K58: =F58
A59: =CONCATENATE("NAME_PkMn_", UPPER(B59)) | B59: Growlithe | C59: ガーヂィ | D59: Caninos | E59: Fuakno | F59: =B59 | G59: =B59 | H59: 가디 | I59: 卡蒂狗 | J59: =I59 | K59: =F59
A60: =CONCATENATE("NAME_PkMn_", UPPER(B60)) | B60: Arcanine | C60: ウインヂィ | D60: Arcanin | E60: Arkani | F60: =B60 | G60: =B60 | H60: 윈디 | I60: 風速狗 | J60: =IFERROR(__xludf.DUMMYFUNCTION("GOOGLETRANSLATE(I60,""zh_HANT"",""zh_HANS"")"),"风速狗") | K60: =F60
A61: =CONCATENATE("NAME_PkMn_", UPPER(B61)) | B61: Poliwag | C61: ニョロモ | D61: Ptitard | E61: Quapsel | F61: =B61 | G61: =B61 | H61: 발챙이 | I61: 蚊香蝌蚪 | J61: =I61 | K61: =F61
A62: =CONCATENATE("NAME_PkMn_", UPPER(B62)) | B62: Poliwhirl | C62: ニョロゾ | D62: Têtarte | E62: Quaputzi | F62: =B62 | G62: =B62 | H62: 슈륙챙이 | I62: 蚊香君 | J62: =I62 | K62: =F62
A63: =CONCATENATE("NAME_PkMn_", UPPER(B63)) | B63: Poliwrath | C63: ニョロボン | D63: Tartard | E63: Quappo | F63: =B63 | G63: =B63 | H63: 강챙이 | I63: 蚊香泳士 | J63: =I63 | K63: =F63
A64: =CONCATENATE("NAME_PkMn_", UPPER(B64)) | B64: Abra | C64: ケーシィ | D64: =B64 | E64: =B64 | F64: =B64 | G64: =B64 | H64: 캐이시 | I64: 凱西 | J64: =IFERROR(__xludf.DUMMYFUNCTION("GOOGLETRANSLATE(I64,""zh_HANT"",""zh_HANS"")"),"凯西") | K64: =F64
A65: =CONCATENATE("NAME_PkMn_", UPPER(B65)) | B65: Kadabra | C65: ユンゲラー | D65: =B65 | E65: =B65 | F65: =B65 | G65: =B65 | H65: 윤겔라 | I65: 勇基拉 | J65: =I65 | K65: =F65
A66: =CONCATENATE("NAME_PkMn_", UPPER(B66)) | B66: Alakazam | C66: フーヂィン | D66: =B66 | E66: Simsala | F66: =B66 | G66: =B66 | H66: 후디 | I66: =J66 | J66: 胡地 | K66: =F66
A67: =CONCATENATE("NAME_PkMn_", UPPER(B67)) | B67: Machop | C67: ワンリキー | D67: Machoc | E67: Machollo | F67: =B67 | G67: =B67 | H67: 알통몬 | I67: 腕力 | J67: =I67 | K67: =F67
A68: =CONCATENATE("NAME_PkMn_", UPPER(B68)) | B68: Machoke | C68: ゴーリキー | D68: Machopeur | E68: Maschock | F68: =B68 | G68: =B68 | H68: 근육몬 | I68: 豪力 | J68: =I68 | K68: =F68
A69: =CONCATENATE("NAME_PkMn_", UPPER(B69)) | B69: Machamp | C69: カイリキー | D69: Mackogneur | E69: Machomei | F69: =B69 | G69: =B69 | H69: 괴력몬 | I69: 怪力 | J69: =I69 | K69: =F69
A70: =CONCATENATE("NAME_PkMn_", UPPER(B70)) | B70: Bellsprout | C70: マダツボミ | D70: Chétiflor | E70: Knofensa | F70: =B70 | G70: =B70 | H70: 모다피 | I70: 喇叭芽 | J70: =I70 | K70: =F70
A71: =CONCATENATE("NAME_PkMn_", UPPER(B71)) | B71: Weepinbell | C71: ウツドン | D71: Boustiflor | E71: Ultrigaria | F71: =B71 | G71: =B71 | H71: 우츠동 | I71: 口呆花 | J71: =I71 | K71: =F71
A72: =CONCATENATE("NAME_PkMn_", UPPER(B72)) | B72: Victreebel | C72: ウツボット | D72: Empiflor | E72: Sarzenia | F72: =B72 | G72: =B72 | H72: 우츠보트 | I72: 大食花 | J72: =I72 | K72: =F72
A73: =CONCATENATE("NAME_PkMn_", UPPER(B73)) | B73: Tentacool | C73: メノクラゲ | D73: =B73 | E73: Tentacha | F73: =B73 | G73: =B73 | H73: 왕눈해 | I73: 瑪瑙水母 | J73: =IFERROR(__xludf.DUMMYFUNCTION("GOOGLETRANSLATE(I73,""zh_HANT"",""zh_HANS"")"),"玛瑙水母") | K73: =F73
A74: =CONCATENATE("NAME_PkMn_", UPPER(B74)) | B74: Tentacruel | C74: ドククラゲ | D74: =B74 | E74: Tentoxa | F74: =B74 | G74: =B74 | H74: 독파리 | I74: 毒刺水母 | J74: =I74 | K74: =F74
A75: =CONCATENATE("NAME_PkMn_", UPPER(B75)) | B75: Geodude | C75: イシツブテ | D75: Racaillou | E75: Kleinstein | F75: =B75 | G75: =B75 | H75: 꼬마돌 | I75: 小拳石 | J75: =I75 | K75: =F75
A76: =CONCATENATE("NAME_PkMn_", UPPER(B76)) | B76: Graveler | C76: ゴローン | D76: Gravalanch | E76: Georok | F76: =B76 | G76: =B76 | H76: 데구리 | I76: 隆隆石 | J76: =I76 | K76: =F76
A77: =CONCATENATE("NAME_PkMn_", UPPER(B77)) | B77: Golem | C77: ゴローニャ | D77: Grolem | E77: Geowaz | F77: =B77 | G77: =B77 | H77: 딱구리 | I77: 隆隆岩 | J77: =I77 | K77: =F77
A78: =CONCATENATE("NAME_PkMn_", UPPER(B78)) | B78: Ponyta | C78: ポニータ | D78: =B78 | E78: Ponyta | F78: =B78 | G78: =B78 | H78: 포니타 | I78: 小火馬 | J78: =IFERROR(__xludf.DUMMYFUNCTION("GOOGLETRANSLATE(I78,""zh_HANT"",""zh_HANS"")"),"小火马") | K78: =F78
A79: =CONCATENATE("NAME_PkMn_", UPPER(B79)) | B79: Rapidash | C79: ギャロップ | D79: Galopa | E79: Gallopa | F79: =B79 | G79: =B79 | H79: 날쌩마 | I79: 烈焰馬 | J79: =IFERROR(__xludf.DUMMYFUNCTION("GOOGLETRANSLATE(I79,""zh_HANT"",""zh_HANS"")"),"烈焰马") | K79: =F79
A80: =CONCATENATE("NAME_PkMn_", UPPER(B80)) | B80: Slowpoke | C80: ヤドン | D80: Ramoloss | E80: Flegmon | F80: =B80 | G80: =B80 | H80: 야돈 | I80: 呆呆獸 | J80: =IFERROR(__xludf.DUMMYFUNCTION("GOOGLETRANSLATE(I80,""zh_HANT"",""zh_HANS"")"),"呆呆兽") | K80: =F80
A81: =CONCATENATE("NAME_PkMn_", UPPER(B81)) | B81: Slowbro | C81: ヤドラン | D81: Flagadoss | E81: Lahmus | F81: =B81 | G81: =B81 | H81: 야도란 | I81: =IFERROR(__xludf.DUMMYFUNCTION("GOOGLETRANSLATE(J81,""zh_HANS"",""zh_HANT"")"),"呆殼獸") | J81: 呆壳兽 | K81: =F81
A82: =CONCATENATE("NAME_PkMn_", UPPER(B82)) | B82: Magnemite | C82: コイル | D82: Magnéti | E82: Magnetilo | F82: =B82 | G82: =B82 | H82: 코일 | I82: 小磁怪 | J82: =I82 | K82: =F82
A83: =CONCATENATE("NAME_PkMn_", UPPER(B83)) | B83: Magneton | C83: レアコイル | D83: Magnéton | E83: =B83 | F83: =B83 | G83: =B83 | H83: 레어코일 | I83: 三合一磁怪 | J83: =IFERROR(__xludf.DUMMYFUNCTION("GOOGLETRANSLATE(I83,""zh_HANT"",""zh_HANS"")"),"三合一磁怪") | K83: =F83
A84: NAME_PkMn_FARFETCHD | B84: Farfetch'd | C84: カモネギ | D84: Canarticho | E84: Porenta | F84: =B84 | G84: =B84 | H84: 파오리 | I84: 大蔥鴨 | J84: =IFERROR(__xludf.DUMMYFUNCTION("GOOGLETRANSLATE(I84,""zh_HANT"",""zh_HANS"")"),"大葱鸭") | K84: =F84
A85: =CONCATENATE("NAME_PkMn_", UPPER(B85)) | B85: Doduo | C85: ドードー | D85: =B85 | E85: Dodu | F85: =B85 | G85: =B85 | H85: 두두 | I85: 嘟嘟 | J85: =I85 | K85: =F85
A86: =CONCATENATE("NAME_PkMn_", UPPER(B86)) | B86: Dodrio | C86: ドードリオ | D86: =B86 | E86: Dodri | F86: =B86 | G86: =B86 | H86: 두트리오 | I86: 嘟嘟利 | J86: =I86 | K86: =F86
A87: =CONCATENATE("NAME_PkMn_", UPPER(B87)) | B87: Seel | C87: パウワウ | D87: Otaria | E87: Jurob | F87: =B87 | G87: =B87 | H87: 쥬쥬 | I87: 小海獅 | J87: =IFERROR(__xludf.DUMMYFUNCTION("GOOGLETRANSLATE(I87,""zh_HANT"",""zh_HANS"")"),"小海狮") | K87: =F87
A88: =CONCATENATE("NAME_PkMn_", UPPER(B88)) | B88: Dewgong | C88: ジュゴン | D88: Lamantine | E88: Jugong | F88: =B88 | G88: =B88 | H88: 쥬레곤 | I88: 白海獅 | J88: =IFERROR(__xludf.DUMMYFUNCTION("GOOGLETRANSLATE(I88,""zh_HANT"",""zh_HANS"")"),"白海狮") | K88: =F88
A89: =CONCATENATE("NAME_PkMn_", UPPER(B89)) | B89: Grimer | C89: ベトベター | D89: Tadmorv | E89: Sleima | F89: =B89 | G89: =B89 | H89: 질퍽이 | I89: 臭泥 | J89: =I89 | K89: =F89
A90: =CONCATENATE("NAME_PkMn_", UPPER(B90)) | B90: Muk | C90: ベトベトン | D90: Grotadmorv | E90: Sleimok | F90: =B90 | G90: =B90 | H90: 질뻐기 | I90: 臭臭泥 | J90: =I90 | K90: =F90
A91: =CONCATENATE("NAME_PkMn_", UPPER(B91)) | B91: Shellder | C91: シェルダー | D91: Kokiyas | E91: Muschas | F91: =B91 | G91: =B91 | H91: 셀러 | I91: 大舌貝 | J91: =IFERROR(__xludf.DUMMYFUNCTION("GOOGLETRANSLATE(I91,""zh_HANT"",""zh_HANS"")"),"大舌贝") | K91: =F91
A92: =CONCATENATE("NAME_PkMn_", UPPER(B92)) | B92: Cloyster | C92: パルシェン | D92: Crustabri | E92: Austos | F92: =B92 | G92: =B92 | H92: 파르셀 | I92: 刺甲貝 | J92: =IFERROR(__xludf.DUMMYFUNCTION("GOOGLETRANSLATE(I92,""zh_HANT"",""zh_HANS"")"),"刺甲贝") | K92: =F92
A93: =CONCATENATE("NAME_PkMn_", UPPER(B93)) | B93: Gastly | C93: ゴース | D93: Fantominus | E93: Nebulak | F93: =B93 | G93: =B93 | H93: 고오스 | I93: 鬼斯 | J93: =I93 | K93: =F93
A94: =CONCATENATE("NAME_PkMn_", UPPER(B94)) | B94: Haunter | C94: ゴースト | D94: Spectrum | E94: Apollo | F94: =B94 | G94: =B94 | H94: 고우스트 | I94: 鬼斯通 | J94: =I94 | K94: =F94
A95: =CONCATENATE("NAME_PkMn_", UPPER(B95)) | B95: Gengar | C95: ゲンガー | D95: Ectoplasma | E95: =B95 | F95: =B95 | G95: =B95 | H95: 팬텀 | I95: =J95 | J95: 耿鬼 | K95: =F95
A96: =CONCATENATE("NAME_PkMn_", UPPER(B96)) | B96: Onix | C96: イワーク | D96: =B96 | E96: =B96 | F96: =B96 | G96: =B96 | H96: 롱스톤 | I96: 大岩蛇 | J96: =I96 | K96: =F96
A97: =CONCATENATE("NAME_PkMn_", UPPER(B97)) | B97: Drowzee | C97: スリープ | D97: Soporifik | E97: Traumato | F97: =B97 | G97: =B97 | H97: 슬리프 | I97: 催眠貘 | J97: =I97 | K97: =F97
A98: =CONCATENATE("NAME_PkMn_", UPPER(B98)) | B98: Hypno | C98: スリーパー | D98: Hypnomade | E98: =B98 | F98: =B98 | G98: =B98 | H98: 슬리퍼 | I98: 引夢貘人 | J98: =IFERROR(__xludf.DUMMYFUNCTION("GOOGLETRANSLATE(I98,""zh_HANT"",""zh_HANS"")"),"引梦貘人") | K98: =F98
A99: =CONCATENATE("NAME_PkMn_", UPPER(B99)) | B99: Krabby | C99: クラブ | D99: =B99 | E99: =B99 | F99: =B99 | G99: =B99 | H99: 크랩 | I99: 大鉗蟹 | J99: =IFERROR(__xludf.DUMMYFUNCTION("GOOGLETRANSLATE(I99,""zh_HANT"",""zh_HANS"")"),"大钳蟹") | K99: =F99
A100: =CONCATENATE("NAME_PkMn_", UPPER(B100)) | B100: Kingler | C100: キングラー | D100: Krabboss | E100: =B100 | F100: =B100 | G100: =B100 | H100: 킹크랩 | I100: 巨鉗蟹 | J100: =IFERROR(__xludf.DUMMYFUNCTION("GOOGLETRANSLATE(I100,""zh_HANT"",""zh_HANS"")"),"巨钳蟹") | K100: =F100
...

Sheet Forms
A1: =Pokemon!A1 | B1: =Pokemon!B1 | C1: =Pokemon!C1 | D1: =Pokemon!D1 | E1: =Pokemon!E1 | F1: =Pokemon!F1 | G1: =Pokemon!G1 | H1: =Pokemon!H1 | ... K1: =Pokemon!K1
A2: =CONCATENATE("NAME_FORM_", SUBSTITUTE(UPPER(B2), " ", "")) | B2: Male | C2: オス | D2: Mâle | E2: Männlich | F2: Macho | G2: Maschio | H2: 수컷 | I2: 雄性 | J2: =I2 | K2: =F2
A3: =CONCATENATE("NAME_FORM_", SUBSTITUTE(UPPER(B3), " ", "")) | B3: Female | C3: メス | D3: Femelle | E3: Weiblich | F3: Hembra | G3: Femmina | H3: 암컷 | I3: 雌性 | J3: =I3 | K3: =F3
A4: =CONCATENATE("NAME_FORM_", SUBSTITUTE(UPPER(B4), " ", "")) | B4: Shiny | C4: ひかる | D4: Chromatique | E4: Schillerndes | F4: Variocolor | G4: Cromatico | H4: 빛나는 | I4: 發光 | J4: =IFERROR(__xludf.DUMMYFUNCTION("GOOGLETRANSLATE(I4,""zh_HANT"",""zh_HANS"")"),"发光") | K4: =F4
A5: =CONCATENATE("NAME_FORM_", SUBSTITUTE(UPPER(B5), " ", "")) | B5: Normal Form | C5: ポワルンのすがた | D5: Forme Normale | E5: Normalform | F5: =CONCATENATE("Forma ",Types!F2) | G5: Forma Castform | H5: 캐스퐁의 모습 | I5: 飄浮泡泡的樣子 | J5: =IFERROR(__xludf.DUMMYFUNCTION("GOOGLETRANSLATE(I5,""zh_HANT"",""zh_HANS"")"),"飘浮泡泡的样子") | K5: =F5
A6: =CONCATENATE("NAME_FORM_", SUBSTITUTE(UPPER(B6), " ", "")) | B6: Sunny Form | C6: たいようのすがた | D6: Forme Solaire | E6: Sonnenform | F6: Forma Sol | G6: Forma Sole | H6: 태양의 모습 | I6: 太陽的樣子 | J6: =IFERROR(__xludf.DUMMYFUNCTION("GOOGLETRANSLATE(I6,""zh_HANT"",""zh_HANS"")"),"太阳的样子") | K6: =F6
A7: =CONCATENATE("NAME_FORM_", SUBSTITUTE(UPPER(B7), " ", "")) | B7: Rainy Form | C7: あまみずのすがた | D7: Forme Eau de Pluie | E7: Regenform | F7: Forma Lluvia | G7: Forma Pioggia | H7: 빗방울의 모습 | I7: 雨水的樣子 | J7: =IFERROR(__xludf.DUMMYFUNCTION("GOOGLETRANSLATE(I7,""zh_HANT"",""zh_HANS"")"),"雨水的样子") | K7: =F7
A8: =CONCATENATE("NAME_FORM_", SUBSTITUTE(UPPER(B8), " ", "")) | B8: Snowy Form | C8: ゆきぐものすがた | D8: Forme Blizzard | E8: Schneeform | F8: Forma Nieve | G8: Forma Nuvola di Neve | H8: 설운의 모습 | I8: 雪雲的樣子 | J8: =IFERROR(__xludf.DUMMYFUNCTION("GOOGLETRANSLATE(I8,""zh_HANT"",""zh_HANS"")"),"雪云的样子") | K8: =F8
A9: =CONCATENATE("NAME_FORM_", SUBSTITUTE(UPPER(B9), " ", "")) | B9: =CONCATENATE(B5, "e") | C9: ノーマルフォルム | D9: =D5 | E9: =E5 | F9: =F5 | G9: Forma Normale | H9: 노말폼 | I9: 普通形態 | J9: =IFERROR(__xludf.DUMMYFUNCTION("GOOGLETRANSLATE(I9,""zh_HANT"",""zh_HANS"")"),"普通形态") | K9: =F9
A10: =CONCATENATE("NAME_FORM_", SUBSTITUTE(UPPER(B10), " ", "")) | B10: Attack Forme | C10: アタックフォルム | D10: Forme Attaque | E10: Angriffsform | F10: Forma Ataque | G10: Forma Attacco | H10: 어택폼 | I10: 攻擊形態 | J10: =IFERROR(__xludf.DUMMYFUNCTION("GOOGLETRANSLATE(I10,""zh_HANT"",""zh_HANS"")"),"攻击形态") | K10: =F10
A11: =CONCATENATE("NAME_FORM_", SUBSTITUTE(UPPER(B11), " ", "")) | B11: Defence Forme | C11: ヂィフェンスフォルム | D11: Forme Défense | E11: Verteidigungsform | F11: Forma Defensa | G11: Forma Difesa | H11: 디펜스폼 | I11: 防禦形態 | J11: =IFERROR(__xludf.DUMMYFUNCTION("GOOGLETRANSLATE(I11,""zh_HANT"",""zh_HANS"")"),"防御形态") | K11: =F11
A12: =CONCATENATE("NAME_FORM_", SUBSTITUTE(UPPER(B12), " ", "")) | B12: Speed Forme | C12: スピードフォルム | D12: Forme Vitesse | E12: Initiativeform | F12: Forma Velocidad | G12: Forma Velocità | H12: 스피드폼 | I12: 速度形態 | J12: =IFERROR(__xludf.DUMMYFUNCTION("GOOGLETRANSLATE(I12,""zh_HANT"",""zh_HANS"")"),"速度形态") | K12: =F12
A13: =CONCATENATE("NAME_FORM_", SUBSTITUTE(UPPER(B13), " ", "")) | B13: Plant Cloak | C13: くさきのミノ | D13: Cape Plante | E13: Pflanzenumhang | F13: Tronco Planta | G13: Manto Pianta | H13: 초목도롱 | I13: 草木蓑衣 | J13: =I13 | K13: =F13
A14: =CONCATENATE("NAME_FORM_", SUBSTITUTE(UPPER(B14), " ", "")) | B14: Sandy Cloak | C14: すなちのミノ | D14: Cape Sable | E14: Sandumhang | F14: Tronco Arena | G14: Manto Sabbia | H14: 모래땅도롱 | I14: 砂土蓑衣 | J14: =I14 | K14: =F14
A15: =CONCATENATE("NAME_FORM_", SUBSTITUTE(UPPER(B15), " ", "")) | B15: Trash Cloak | C15: ゴミのミノ | D15: Cape Déchet | E15: Lumpenumhang | F15: Tronco Basura | G15: Manto Scarti | H15: 슈레도롱 | I15: 垃圾蓑衣 | J15: =I15 | K15: =F15
A16: =CONCATENATE("NAME_FORM_", SUBSTITUTE(UPPER(B16), " ", "")) | B16: Overcast Form | C16: ネガフォルム | D16: Temps Couvert | E16: Wolkenform | F16: Forma Encapotado | G16: Forma Nuvola | H16: 네거폼 | I16: 陰天形態 | J16: =IFERROR(__xludf.DUMMYFUNCTION("GOOGLETRANSLATE(I16,""zh_HANT"",""zh_HANS"")"),"阴天形态") | K16: =F16
A17: =CONCATENATE("NAME_FORM_", SUBSTITUTE(UPPER(B17), " ", "")) | B17: Sunshine Form | C17: ポシフォルム | D17: Temps Ensoleillé | E17: =E6 | F17: Forma Soleado | G17: Forma Splendore | H17: 포지폼 | I17: 晴天形態 | J17: =IFERROR(__xludf.DUMMYFUNCTION("GOOGLETRANSLATE(I17,""zh_HANT"",""zh_HANS"")"),"晴天形态") | K17: =F17
A18: =CONCATENATE("NAME_FORM_", SUBSTITUTE(UPPER(B18), " ", "")) | B18: West Sea | C18: にしのうみ | D18: Mer Occident | E18: Westliches Meer | F18: Mar Oest | G18: Mare Ovest | H18: 서쪽바다 | I18: 西海 | J18: =I18 | K18: =F18
A19: =CONCATENATE("NAME_FORM_", SUBSTITUTE(UPPER(B19), " ", "")) | B19: East Sea | C19: ひがしのうみ | D19: Mer Orient | E19: Östliches Meer | F19: Mar Est | G19: Mare Est | H19: 동쪽바다 | I19: 東海 | J19: =I19 | K19: =F19
A20: =CONCATENATE("NAME_FORM_", SUBSTITUTE(UPPER(B20), " ", "")) | B20: Heat Rotom | C20: =CONCATENATE("ヒート", Pokemon!C480) | D20: Motisma Chaleur | E20: Hitze-Rotom | F20: Rotom Claor | G20: =CONCATENATE(F20, "e") | H20: 히트로토무 | I20: 加熱洛托姆 | J20: =IFERROR(__xludf.DUMMYFUNCTION("GOOGLETRANSLATE(I20,""zh_HANT"",""zh_HANS"")"),"加热洛托姆") | K20: =F20
A21: =CONCATENATE("NAME_FORM_", SUBSTITUTE(UPPER(B21), " ", "")) | B21: Wash Rotom | C21: =CONCATENATE("ウォッシュ", Pokemon!C480) | D21: Motisma Lavage | E21: Wasch-Rotom | F21: Rotom Lavado | G21: Rotom Lavaggio | H21: 워시로토무 | I21: 清洗洛托姆 | J21: =I21 | K21: =F21
A22: =CONCATENATE("NAME_FORM_", SUBSTITUTE(UPPER(B22), " ", "")) | B22: Frost Rotom | C22: =CONCATENATE("フロスト", Pokemon!C480) | D22: Motisma Froid | E22: Frost-Rotom | F22: Rotom Frio | G22: Rotom Gelo | H22: 프로스트로토무 | I22: 結冰洛托姆 | J22: =IFERROR(__xludf.DUMMYFUNCTION("GOOGLETRANSLATE(I22,""zh_HANT"",""zh_HANS"")"),"结冰洛托姆") | K22: =F22
A23: =CONCATENATE("NAME_FORM_", SUBSTITUTE(UPPER(B23), " ", "")) | B23: Fan Rotom | C23: =CONCATENATE("スピン", Pokemon!C480) | D23: Motisma Hélice | E23: Wirbel-Rotom | F23: Rotom Ventilador | G23: Rotom Vortice | H23: 스핀로토무 | I23: 旋轉洛托姆 | J23: =IFERROR(__xludf.DUMMYFUNCTION("GOOGLETRANSLATE(I23,""zh_HANT"",""zh_HANS"")"),"旋转洛托姆") | K23: =F23
A24: =CONCATENATE("NAME_FORM_", SUBSTITUTE(UPPER(B24), " ", "")) | B24: Mow Rotom | C24: =CONCATENATE("カット", Pokemon!C480) | D24: Motisma Tonte | E24: Schneid-Rotom | F24: Rotom Corte | G24: Rotom Taglio | H24: 커트로토무 | I24: 切割洛托姆 | J24: =I24 | K24: =F24
A25: =CONCATENATE("NAME_FORM_", SUBSTITUTE(UPPER(B25), " ", "")) | B25: Altered Forme | C25: アナザーフォルム | D25: Forme Alternative | E25: Wandelform | F25: Forma Modificada | G25: Forma Alterata | H25: 어나더폼 | I25: 別種形態 | J25: =IFERROR(__xludf.DUMMYFUNCTION("GOOGLETRANSLATE(I25,""zh_HANT"",""zh_HANS"")"),"别种形态") | K25: =F25
A26: =CONCATENATE("NAME_FORM_", SUBSTITUTE(UPPER(B26), " ", "")) | B26: Origin Forme | C26: オリジンフォルム | D26: Forme Originelle | E26: Urform | F26: Forma Origen | G26: Forma Origine | H26: 오리진폼 | I26: 起源形態 | J26: =IFERROR(__xludf.DUMMYFUNCTION("GOOGLETRANSLATE(I26,""zh_HANT"",""zh_HANS"")"),"起源形态") | K26: =F26
A27: =CONCATENATE("NAME_FORM_", SUBSTITUTE(UPPER(B27), " ", "")) | B27: Land Forme | C27: ランドフォルム | D27: Forme Terrestre | E27: Landform | F27: Forma Tierra | G27: Forma Terra | H27: 랜드폼 | I27: 陸上形態 | J27: =IFERROR(__xludf.DUMMYFUNCTION("GOOGLETRANSLATE(I27,""zh_HANT"",""zh_HANS"")"),"陆上形态") | K27: =F27
A28: =CONCATENATE("NAME_FORM_", SUBSTITUTE(UPPER(B28), " ", "")) | B28: Sky Forme | C28: スカイフォルム | D28: Forme Céleste | E28: Zenitform | F28: =G28 | G28: Forma Cielo | H28: 스카이폼 | I28: 天空形態 | J28: =IFERROR(__xludf.DUMMYFUNCTION("GOOGLETRANSLATE(I28,""zh_HANT"",""zh_HANS"")"),"天空形态") | K28: =F28
A29: NAME_FORM_NORMALTYPE | B29: =CONCATENATE(Types!B2,"-type") | C29: =CONCATENATE(Types!C2,"タイプ") | D29: Type Normal | E29: =CONCATENATE("Typen ",Types!E2) | F29: =CONCATENATE("Tipo ",Types!F2) | G29: =CONCATENATE("Tipo ",Types!G2) | H29: =CONCATENATE(Types!H2,"타입") | I29: =IFERROR(__xludf.DUMMYFUNCTION("GOOGLETRANSLATE(J29,""zh_HANS"",""zh_HANT"")"),"一般屬性") | J29: =CONCATENATE(Types!J2,"属性") | K29: =F29
A30: NAME_FORM_FIGHTINGTYPE | B30: =CONCATENATE(Types!B3,"-type") | C30: =CONCATENATE(Types!C3,"タイプ") | D30: Type Combat | E30: =CONCATENATE("Typen ",Types!E3) | F30: =CONCATENATE("Tipo ",Types!F3) | G30: =CONCATENATE("Tipo ",Types!G3) | H30: =CONCATENATE(Types!H3,"타입") | I30: =IFERROR(__xludf.DUMMYFUNCTION("GOOGLETRANSLATE(J30,""zh_HANS"",""zh_HANT"")"),"格鬥屬性") | J30: =CONCATENATE(Types!J3,"属性") | K30: =F30
A31: NAME_FORM_FLYINGTYPE | B31: =CONCATENATE(Types!B4,"-type") | C31: =CONCATENATE(Types!C4,"タイプ") | D31: Type Vol | E31: =CONCATENATE("Typen ",Types!E4) | F31: =CONCATENATE("Tipo ",Types!F4) | G31: =CONCATENATE("Tipo ",Types!G4) | H31: =CONCATENATE(Types!H4,"타입") | I31: =IFERROR(__xludf.DUMMYFUNCTION("GOOGLETRANSLATE(J31,""zh_HANS"",""zh_HANT"")"),"飛行屬性") | J31: =CONCATENATE(Types!J4,"属性") | K31: =F31
A32: NAME_FORM_POISONTYPE | B32: =CONCATENATE(Types!B5,"-type") | C32: =CONCATENATE(Types!C5,"タイプ") | D32: Type Poison | E32: =CONCATENATE("Typen ",Types!E5) | F32: =CONCATENATE("Tipo ",Types!F5) | G32: =CONCATENATE("Tipo ",Types!G5) | H32: =CONCATENATE(Types!H5,"타입") | I32: =IFERROR(__xludf.DUMMYFUNCTION("GOOGLETRANSLATE(J32,""zh_HANS"",""zh_HANT"")"),"毒屬性") | J32: =CONCATENATE(Types!J5,"属性") | K32: =F32
A33: NAME_FORM_GROUNDTYPE | B33: =CONCATENATE(Types!B6,"-type") | C33: =CONCATENATE(Types!C6,"タイプ") | D33: Type Sol | E33: =CONCATENATE("Typen ",Types!E6) | F33: =CONCATENATE("Tipo ",Types!F6) | G33: =CONCATENATE("Tipo ",Types!G6) | H33: =CONCATENATE(Types!H6,"타입") | I33: =IFERROR(__xludf.DUMMYFUNCTION("GOOGLETRANSLATE(J33,""zh_HANS"",""zh_HANT"")"),"地面屬性") | J33: =CONCATENATE(Types!J6,"属性") | K33: =F33
A34: NAME_FORM_ROCKTYPE | B34: =CONCATENATE(Types!B7,"-type") | C34: =CONCATENATE(Types!C7,"タイプ") | D34: Type Roche | E34: =CONCATENATE("Typen ",Types!E7) | F34: =CONCATENATE("Tipo ",Types!F7) | G34: =CONCATENATE("Tipo ",Types!G7) | H34: =CONCATENATE(Types!H7,"타입") | I34: =IFERROR(__xludf.DUMMYFUNCTION("GOOGLETRANSLATE(J34,""zh_HANS"",""zh_HANT"")"),"岩石屬性") | J34: =CONCATENATE(Types!J7,"属性") | K34: =F34
A35: NAME_FORM_BUGTYPE | B35: =CONCATENATE(Types!B8,"-type") | C35: =CONCATENATE(Types!C8,"タイプ") | D35: Type Insecte | E35: =CONCATENATE("Typen ",Types!E8) | F35: =CONCATENATE("Tipo ",Types!F8) | G35: =CONCATENATE("Tipo ",Types!G8) | H35: =CONCATENATE(Types!H8,"타입") | I35: =IFERROR(__xludf.DUMMYFUNCTION("GOOGLETRANSLATE(J35,""zh_HANS"",""zh_HANT"")"),"蟲屬性") | J35: =CONCATENATE(Types!J8,"属性") | K35: =F35
A36: NAME_FORM_GHOSTTYPE | B36: =CONCATENATE(Types!B9,"-type") | C36: =CONCATENATE(Types!C9,"タイプ") | D36: Type Spectre | E36: =CONCATENATE("Typen ",Types!E9) | F36: =CONCATENATE("Tipo ",Types!F9) | G36: =CONCATENATE("Tipo ",Types!G9) | H36: =CONCATENATE(Types!H9,"타입") | I36: =IFERROR(__xludf.DUMMYFUNCTION("GOOGLETRANSLATE(J36,""zh_HANS"",""zh_HANT"")"),"幽靈屬性") | J36: =CONCATENATE(Types!J9,"属性") | K36: =F36
A37: NAME_FORM_STEELTYPE | B37: =CONCATENATE(Types!B10,"-type") | C37: =CONCATENATE(Types!C10,"タイプ") | D37: Type Acier | E37: =CONCATENATE("Typen ",Types!E10) | F37: =CONCATENATE("Tipo ",Types!F10) | G37: =CONCATENATE("Tipo ",Types!G10) | H37: =CONCATENATE(Types!H10,"타입") | I37: =IFERROR(__xludf.DUMMYFUNCTION("GOOGLETRANSLATE(J37,""zh_HANS"",""zh_HANT"")"),"鋼屬性") | J37: =CONCATENATE(Types!J10,"属性") | K37: =F37
A38: NAME_FORM_FIRETYPE | B38: =CONCATENATE(Types!B11,"-type") | C38: =CONCATENATE(Types!C11,"タイプ") | D38: Type Feu | E38: =CONCATENATE("Typen ",Types!E11) | F38: =CONCATENATE("Tipo ",Types!F11) | G38: =CONCATENATE("Tipo ",Types!G11) | H38: =CONCATENATE(Types!H11,"타입") | I38: =IFERROR(__xludf.DUMMYFUNCTION("GOOGLETRANSLATE(J38,""zh_HANS"",""zh_HANT"")"),"火屬性") | J38: =CONCATENATE(Types!J11,"属性") | K38: =F38
A39: NAME_FORM_WATERTYPE | B39: =CONCATENATE(Types!B12,"-type") | C39: =CONCATENATE(Types!C12,"タイプ") | D39: Type Eau | E39: =CONCATENATE("Typen ",Types!E12) | F39: =CONCATENATE("Tipo ",Types!F12) | G39: =CONCATENATE("Tipo ",Types!G12) | H39: =CONCATENATE(Types!H12,"타입") | I39: =IFERROR(__xludf.DUMMYFUNCTION("GOOGLETRANSLATE(J39,""zh_HANS"",""zh_HANT"")"),"水屬性") | J39: =CONCATENATE(Types!J12,"属性") | K39: =F39
A40: NAME_FORM_GRASSTYPE | B40: =CONCATENATE(Types!B13,"-type") | C40: =CONCATENATE(Types!C13,"タイプ") | D40: Type Plante | E40: =CONCATENATE("Typen ",Types!E13) | F40: =CONCATENATE("Tipo ",Types!F13) | G40: =CONCATENATE("Tipo ",Types!G13) | H40: =CONCATENATE(Types!H13,"타입") | I40: =IFERROR(__xludf.DUMMYFUNCTION("GOOGLETRANSLATE(J40,""zh_HANS"",""zh_HANT"")"),"草屬性") | J40: =CONCATENATE(Types!J13,"属性") | K40: =F40
A41: NAME_FORM_ELECTRICTYPE | B41: =CONCATENATE(Types!B14,"-type") | C41: =CONCATENATE(Types!C14,"タイプ") | D41: Type Électrik | E41: =CONCATENATE("Typen ",Types!E14) | F41: =CONCATENATE("Tipo ",Types!F14) | G41: =CONCATENATE("Tipo ",Types!G14) | H41: =CONCATENATE(Types!H14,"타입") | I41: =IFERROR(__xludf.DUMMYFUNCTION("GOOGLETRANSLATE(J41,""zh_HANS"",""zh_HANT"")"),"電屬性") | J41: =CONCATENATE(Types!J14,"属性") | K41: =F41
A42: NAME_FORM_PSYCHICTYPE | B42: =CONCATENATE(Types!B15,"-type") | C42: =CONCATENATE(Types!C15,"タイプ") | D42: Type Psy | E42: =CONCATENATE("Typen ",Types!E15) | F42: =CONCATENATE("Tipo ",Types!F15) | G42: =CONCATENATE("Tipo ",Types!G15) | H42: =CONCATENATE(Types!H15,"타입") | I42: =IFERROR(__xludf.DUMMYFUNCTION("GOOGLETRANSLATE(J42,""zh_HANS"",""zh_HANT"")"),"超能力屬性") | J42: =CONCATENATE(Types!J15,"属性") | K42: =F42
A43: NAME_FORM_ICETYPE | B43: =CONCATENATE(Types!B16,"-type") | C43: =CONCATENATE(Types!C16,"タイプ") | D43: Type Glace | E43: =CONCATENATE("Typen ",Types!E16) | F43: =CONCATENATE("Tipo ",Types!F16) | G43: =CONCATENATE("Tipo ",Types!G16) | H43: =CONCATENATE(Types!H16,"타입") | I43: =IFERROR(__xludf.DUMMYFUNCTION("GOOGLETRANSLATE(J43,""zh_HANS"",""zh_HANT"")"),"冰屬性") | J43: =CONCATENATE(Types!J16,"属性") | K43: =F43
A44: NAME_FORM_DRAGONTYPE | B44: =CONCATENATE(Types!B17,"-type") | C44: =CONCATENATE(Types!C17,"タイプ") | D44: Type Dragon | E44: =CONCATENATE("Typen ",Types!E17) | F44: =CONCATENATE("Tipo ",Types!F17) | G44: =CONCATENATE("Tipo ",Types!G17) | H44: =CONCATENATE(Types!H17,"타입") | I44: =IFERROR(__xludf.DUMMYFUNCTION("GOOGLETRANSLATE(J44,""zh_HANS"",""zh_HANT"")"),"龍屬性") | J44: =CONCATENATE(Types!J17,"属性") | K44: =F44
A45: NAME_FORM_DARKTYPE | B45: =CONCATENATE(Types!B18,"-type") | C45: =CONCATENATE(Types!C18,"タイプ") | D45: Type Ténèbres | E45: =CONCATENATE("Typen ",Types!E18) | F45: =CONCATENATE("Tipo ",Types!F18) | G45: =CONCATENATE("Tipo ",Types!G18) | H45: =CONCATENATE(Types!H18,"타입") | I45: =IFERROR(__xludf.DUMMYFUNCTION("GOOGLETRANSLATE(J45,""zh_HANS"",""zh_HANT"")"),"惡屬性") | J45: =CONCATENATE(Types!J18,"属性") | K45: =F45
A46: NAME_FORM_FAIRYTYPE | B46: =CONCATENATE(Types!B19,"-type") | C46: =CONCATENATE(Types!C19,"タイプ") | D46: Type Fée | E46: =CONCATENATE("Typen ",Types!E19) | F46: =CONCATENATE("Tipo ",Types!F19) | G46: =CONCATENATE("Tipo ",Types!G19) | H46: =CONCATENATE(Types!H19,"타입") | I46: =IFERROR(__xludf.DUMMYFUNCTION("GOOGLETRANSLATE(J46,""zh_HANS"",""zh_HANT"")"),"妖精屬性") | J46: =CONCATENATE(Types!J19,"属性") | K46: =F46
A47: =CONCATENATE("NAME_FORM_", SUBSTITUTE(UPPER(B47), " ", "")) | B47: Red-Striped Form | C47: あかすじのすがた | D47: Motif Rouge | E47: Rotlinige Form | F47: Forma Raya Roja | G47: Forma Linearossa | H47: 적색근의 모습 | I47: 紅條紋的樣子 | J47: =IFERROR(__xludf.DUMMYFUNCTION("GOOGLETRANSLATE(I47,""zh_HANT"",""zh_HANS"")"),"红条纹的样子") | K47: =F47
A48: =CONCATENATE("NAME_FORM_", SUBSTITUTE(UPPER(B48), " ", "")) | B48: Blue-Striped Form | C48: あおすじのすがた | D48: Motif Bleu | E48: Blaulinige Form | F48: Forma Raya Azul | G48: Forma Lineablu | H48: 청색근의 모습 | I48: 藍條紋的樣子 | J48: =IFERROR(__xludf.DUMMYFUNCTION("GOOGLETRANSLATE(I48,""zh_HANT"",""zh_HANS"")"),"蓝条纹的样子") | K48: =F48
A49: =CONCATENATE("NAME_FORM_", SUBSTITUTE(UPPER(B49), " ", "")) | B49: Standard Mode | C49: ノーマルモード | D49: Mode Normal | E49: Normalmodus | F49: Modo Normal | G49: Stato Normale | H49: 노말모드 | I49: 普通模式 | J49: =I49 | K49: =F49
A50: =CONCATENATE("NAME_FORM_", SUBSTITUTE(UPPER(B50), " ", "")) | B50: =Abilities!B162 | C50: =Abilities!C162 | D50: =Abilities!D162 | E50: =Abilities!E162 | F50: =Abilities!F162 | G50: =Abilities!G162 | H50: =Abilities!H162 | I50: =Abilities!I162 | J50: =Abilities!J162 | K50: =F50
A51: =CONCATENATE("NAME_FORM_", SUBSTITUTE(UPPER(B51), " ", "")) | B51: Spring Form | C51: はるのすがた | D51: Forme Printemps | E51: Frühlingsform | F51: =G51 | G51: Forma Primavera | H51: 봄의 모습 | I51: 春天的樣子 | J51: =IFERROR(__xludf.DUMMYFUNCTION("GOOGLETRANSLATE(I51,""zh_HANT"",""zh_HANS"")"),"春天的样子") | K51: =F51
A52: =CONCATENATE("NAME_FORM_", SUBSTITUTE(UPPER(B52), " ", "")) | B52: Summer Form | C52: なつのすがた | D52: Forme Été | E52: Sommerform | F52: Forma Verano | G52: Forma Estate | H52: 여름의 모습 | I52: 夏天的樣子 | J52: =IFERROR(__xludf.DUMMYFUNCTION("GOOGLETRANSLATE(I52,""zh_HANT"",""zh_HANS"")"),"夏天的样子") | K52: =F52
A53: =CONCATENATE("NAME_FORM_", SUBSTITUTE(UPPER(B53), " ", "")) | B53: Autumn Form | C53: あきのすがた | D53: Forme Automne | E53: Herbstform | F53: Forma Otoño | G53: Forma Autunno | H53: 가을의 모습 | I53: 秋天的樣子 | J53: =IFERROR(__xludf.DUMMYFUNCTION("GOOGLETRANSLATE(I53,""zh_HANT"",""zh_HANS"")"),"秋天的样子") | K53: =F53
A54: =CONCATENATE("NAME_FORM_", SUBSTITUTE(UPPER(B54), " ", "")) | B54: Winter Form | C54: ふゆのすがた | D54: Forme Hiver | E54: Winterform | F54: Forma Invierno | G54: Forma Inverno | H54: 겨울의 모습 | I54: 冬天的樣子 | J54: =IFERROR(__xludf.DUMMYFUNCTION("GOOGLETRANSLATE(I54,""zh_HANT"",""zh_HANS"")"),"冬天的样子") | K54: =F54
A55: =CONCATENATE("NAME_FORM_", SUBSTITUTE(UPPER(B55), " ", "")) | B55: Incarnate Forme | C55: けしんフォルム | D55: Forme Avatar | E55: Inkarnationsform | F55: Forma Avatar | G55: Forma Incarnazione | H55: 화신폼 | I55: 化身形態 | J55: =IFERROR(__xludf.DUMMYFUNCTION("GOOGLETRANSLATE(I55,""zh_HANT"",""zh_HANS"")"),"化身形态") | K55: =F55
A56: =CONCATENATE("NAME_FORM_", SUBSTITUTE(UPPER(B56), " ", "")) | B56: Therian Forme | C56: れいじゅうフォルム | D56: Forme Totémique | E56: Tiergeistform | F56: Forma Tótem | G56: Forma Totem | H56: 영물폼 | I56: 靈獸形態 | J56: =IFERROR(__xludf.DUMMYFUNCTION("GOOGLETRANSLATE(I56,""zh_HANT"",""zh_HANS"")"),"灵兽形态") | K56: =F56
A57: =CONCATENATE("NAME_FORM_", SUBSTITUTE(UPPER(B57), " ", "")) | B57: Black Kyurem | C57: ブラックキュレム | D57: Kyurem Noir | E57: Schwarzes Kyurem | F57: Kyurem Negro | G57: Kyurem Nero | H57: 블랙 큐레무 | I57: 闇黑酋雷姆 | J57: =IFERROR(__xludf.DUMMYFUNCTION("GOOGLETRANSLATE(I57,""zh_HANT"",""zh_HANS"")"),"暗黑酋雷姆") | K57: =F57
A58: =CONCATENATE("NAME_FORM_", SUBSTITUTE(UPPER(B58), " ", "")) | B58: White Kyurem | C58: ホワイトキュレム | D58: Kyurem Blanc | E58: Weißes Kyurem | F58: Kyurem Blanco | G58: Kyurem Bianco | H58: 화이트 큐레무 | I58: 焰白酋雷姆 | J58: =I58 | K58: =F58
A59: =CONCATENATE("NAME_FORM_", SUBSTITUTE(UPPER(B59), " ", "")) | B59: Ordinary Form | C59: いつものすがた | D59: Aspect Normal | E59: Standardform | F59: Forma Habitual | G59: Forma Normale | H59: 평상시 모습 | I59: 平常的樣子 | J59: =IFERROR(__xludf.DUMMYFUNCTION("GOOGLETRANSLATE(I59,""zh_HANT"",""zh_HANS"")"),"平常的样子") | K59: =F59
A60: =CONCATENATE("NAME_FORM_", SUBSTITUTE(UPPER(B60), " ", "")) | B60: Resolute Form | C60: かくごのすがた | D60: Aspect Décidé | E60: Resolutform | F60: Forma Brío | G60: Forma Risoluta | H60: 각오의 모습 | I60: 覺悟的樣子 | J60: =IFERROR(__xludf.DUMMYFUNCTION("GOOGLETRANSLATE(I60,""zh_HANT"",""zh_HANS"")"),"觉悟的样子") | K60: =F60
A61: =CONCATENATE("NAME_FORM_", SUBSTITUTE(UPPER(B61), " ", "")) | B61: Aria Forme | C61: ボイスフォルム | D61: Forme Chant | E61: Gesangsform | F61: Forma Lírica | G61: Forma Canto | H61: 보이스폼 | I61: 歌聲形態 | J61: =IFERROR(__xludf.DUMMYFUNCTION("GOOGLETRANSLATE(I61,""zh_HANT"",""zh_HANS"")"),"歌声形态") | K61: =F61
A62: =CONCATENATE("NAME_FORM_", SUBSTITUTE(UPPER(B62), " ", "")) | B62: Pirouette Forme | C62: ステップフォルム | D62: Forme Danse | E62: Tanzform | F62: =G62 | G62: Forma Danza | H62: 스텝폼 | I62: 舞步形態 | J62: =IFERROR(__xludf.DUMMYFUNCTION("GOOGLETRANSLATE(I62,""zh_HANT"",""zh_HANS"")"),"舞步形态") | K62: =F62
A63: =CONCATENATE("NAME_FORM_", SUBSTITUTE(UPPER(B63), " ", "")) | B63: Ash Greninja | C63: サトシゲッコウガ | D63: Sachanobi | E63: Ash-Quajutsu | F63: Greninja Ash | G63: Greninja Forma Ash | H63: =CONCATENATE("지우",Pokemon!H659) | I63: =CONCATENATE("小智版",Pokemon!I659) | J63: =CONCATENATE("小智版",Pokemon!J659) | K63: =F63
A64: =CONCATENATE("NAME_FORM_", SUBSTITUTE(UPPER(B64), " ", "")) | B64: Archipelago Pattern | C64: ぐんとうもよう | D64: Motif Archipel | E64: Archipelmuster | F64: Motivo Isleño | G64: Motivo Arcipelago | H64: 군도의 모양 | I64: 群島花紋 | J64: =IFERROR(__xludf.DUMMYFUNCTION("GOOGLETRANSLATE(I64,""zh_HANT"",""zh_HANS"")"),"群岛花纹") | K64: =F64
A65: =CONCATENATE("NAME_FORM_", SUBSTITUTE(UPPER(B65), " ", "")) | B65: Continental Pattern | C65: たいりくのもよう | D65: Motif Continent | E65: Kontinentalmuster | F65: Motivo Continental | G65: =CONCATENATE(F65, "e") | H65: 대륙의 모양 | I65: 大陸花紋 | J65: =IFERROR(__xludf.DUMMYFUNCTION("GOOGLETRANSLATE(I65,""zh_HANT"",""zh_HANS"")"),"大陆花纹") | K65: =F65
A66: =CONCATENATE("NAME_FORM_", SUBSTITUTE(UPPER(B66), " ", "")) | B66: Elegant Pattern | C66: みやびなもよう | D66: Motif Monarchie | E66: Prunkmuster | F66: Motivo Oriental | G66: Motivo Eleganza | H66: 우아한 모양 | I66: 高雅花紋 | J66: =IFERROR(__xludf.DUMMYFUNCTION("GOOGLETRANSLATE(I66,""zh_HANT"",""zh_HANS"")"),"高雅花纹") | K66: =F66
A67: =CONCATENATE("NAME_FORM_", SUBSTITUTE(UPPER(B67), " ", "")) | B67: Garden Pattern | C67: ていえんのもよう | D67: Motif Verdure | E67: Ziergartenmuster | F67: Motivo Vergel | G67: Motivo Prato | H67: 정원의 모양 | I67: 庭園花紋 | J67: =IFERROR(__xludf.DUMMYFUNCTION("GOOGLETRANSLATE(I67,""zh_HANT"",""zh_HANS"")"),"庭园花纹") | K67: =F67
A68: =CONCATENATE("NAME_FORM_", SUBSTITUTE(UPPER(B68), " ", "")) | B68: High Plains Pattern | C68: こうやのもよう | D68: Motif Sécheresse | E68: Dürremuster | F68: Motivo Estepa | G68: Motivo Deserto | H68: 황야의 모양 | I68: 荒野花紋 | J68: =IFERROR(__xludf.DUMMYFUNCTION("GOOGLETRANSLATE(I68,""zh_HANT"",""zh_HANS"")"),"荒野花纹") | K68: =F68
A69: =CONCATENATE("NAME_FORM_", SUBSTITUTE(UPPER(B69), " ", "")) | B69: Icy Snow Pattern | C69: ひょうせつのもよう | D69: Motif Blizzard | E69: Frostmuster | F69: Motivo Polar | G69: Motivo Nevi Perenni | H69: 빙설의 모양 | I69: 冰雪花紋 | J69: =IFERROR(__xludf.DUMMYFUNCTION("GOOGLETRANSLATE(I69,""zh_HANT"",""zh_HANS"")"),"冰雪花纹") | K69: =F69
A70: =CONCATENATE("NAME_FORM_", SUBSTITUTE(UPPER(B70), " ", "")) | B70: Jungle Pattern | C70: ジャンガルのもよう | D70: Motif Jungle | E70: Dschungelmuster | F70: Motivo Jungla | G70: Motivo Giungla | H70: 정글의 모양 | I70: 熱帶雨林花紋 | J70: =IFERROR(__xludf.DUMMYFUNCTION("GOOGLETRANSLATE(I70,""zh_HANT"",""zh_HANS"")"),"热带雨林花纹") | K70: =F70
A71: =CONCATENATE("NAME_FORM_", SUBSTITUTE(UPPER(B71), " ", "")) | B71: Marine Pattern | C71: マリンのもよう | D71: Motif Rivage | E71: Aquamarinmuster | F71: =G71 | G71: Motivo Marino | H71: 마린의 모양 | I71: 大海花紋 | J71: =IFERROR(__xludf.DUMMYFUNCTION("GOOGLETRANSLATE(I71,""zh_HANT"",""zh_HANS"")"),"大海花纹") | K71: =F71
A72: =CONCATENATE("NAME_FORM_", SUBSTITUTE(UPPER(B72), " ", "")) | B72: Meadow Pattern | C72: はなぞののもよう | D72: Motif Floraison | E72: Blumenmeermuster | F72: Motivo Floral | G72: Motivo Giardinfiore | H72: 화원의 모양 | I72: 花園花紋 | J72: =IFERROR(__xludf.DUMMYFUNCTION("GOOGLETRANSLATE(I72,""zh_HANT"",""zh_HANS"")"),"花园花纹") | K72: =F72
A73: =CONCATENATE("NAME_FORM_", SUBSTITUTE(UPPER(B73), " ", "")) | B73: Modern Pattern | C73: モダンなもよう | D73: Motif Métropole | E73: Innovationmuster | F73: Motivo Moderno | G73: Motivo Trendy | H73: 모던한 모양 | I73: 摩登花紋 | J73: =IFERROR(__xludf.DUMMYFUNCTION("GOOGLETRANSLATE(I73,""zh_HANT"",""zh_HANS"")"),"摩登花纹") | K73: =F73
A74: =CONCATENATE("NAME_FORM_", SUBSTITUTE(UPPER(B74), " ", "")) | B74: Monsoon Pattern | C74: スコールのもよう | D74: Motif Cyclone | E74: Monsunmuster | F74: Motivo Monzón | G74: Motivo Pluviale | H74: 스콜의 모양 | I74: 驟雨花紋 | J74: =IFERROR(__xludf.DUMMYFUNCTION("GOOGLETRANSLATE(I74,""zh_HANT"",""zh_HANS"")"),"骤雨花纹") | K74: =F74
A75: =CONCATENATE("NAME_FORM_", SUBSTITUTE(UPPER(B75), " ", "")) | B75: Ocean Pattern | C75: オーシャンのもよう | D75: Motif Soleil Levant | E75: Ozeanmuster | F75: Motivo Océano | G75: Motivo Oceanico | H75: 오션의 모양 | I75: 大洋花紋 | J75: =IFERROR(__xludf.DUMMYFUNCTION("GOOGLETRANSLATE(I75,""zh_HANT"",""zh_HANS"")"),"大洋花纹") | K75: =F75
A76: =CONCATENATE("NAME_FORM_", SUBSTITUTE(UPPER(B76), " ", "")) | B76: Polar Pattern | C76: ゆきぐにのもよう | D76: Motif Banquise | E76: Schneefeldmuster | F76: Motivo Taiga | G76: Motivo Nordico | H76: 설국의 모양 | I76: 雪國花紋 | J76: =IFERROR(__xludf.DUMMYFUNCTION("GOOGLETRANSLATE(I76,""zh_HANT"",""zh_HANS"")"),"雪国花纹") | K76: =F76
A77: =CONCATENATE("NAME_FORM_", SUBSTITUTE(UPPER(B77), " ", "")) | B77: River Pattern | C77: だいがのもよう | D77: Motif Delta | E77: Flussdeltamuster | F77: Motivo Oasis | G77: Motivo Fluviale | H77: 대하의 모양 | I77: 大河花紋 | J77: =IFERROR(__xludf.DUMMYFUNCTION("GOOGLETRANSLATE(I77,""zh_HANT"",""zh_HANS"")"),"大河花纹") | K77: =F77
A78: =CONCATENATE("NAME_FORM_", SUBSTITUTE(UPPER(B78), " ", "")) | B78: Sandstorm Pattern | C78: さじんのもよう | D78: Motif Sable | E78: Sandmuster | F78: Motivo Desierto | G78: Motivo Sabbia | H78: 사진의 모양 | I78: 沙塵花紋 | J78: =IFERROR(__xludf.DUMMYFUNCTION("GOOGLETRANSLATE(I78,""zh_HANT"",""zh_HANS"")"),"沙尘花纹") | K78: =F78
A79: =CONCATENATE("NAME_FORM_", SUBSTITUTE(UPPER(B79), " ", "")) | B79: Savanna Pattern | C79: サバンナのもよう | D79: Motif Mangrove | E79: Savannenmuster | F79: Motivo Pantano | G79: Motivo Savana | H79: 사바나의 모양 | I79: 熱帶草原花紋 | J79: =IFERROR(__xludf.DUMMYFUNCTION("GOOGLETRANSLATE(I79,""zh_HANT"",""zh_HANS"")"),"热带草原花纹") | K79: =F79
A80: =CONCATENATE("NAME_FORM_", SUBSTITUTE(UPPER(B80), " ", "")) | B80: Sun Pattern | C80: たいようのもよう | D80: Motif Zénith | E80: Sonnenmuster | F80: Motivo Solar | G80: Motivo Solare | H80: 태양의 모양 | I80: 太陽花紋 | J80: =IFERROR(__xludf.DUMMYFUNCTION("GOOGLETRANSLATE(I80,""zh_HANT"",""zh_HANS"")"),"太阳花纹") | K80: =F80
A81: =CONCATENATE("NAME_FORM_", SUBSTITUTE(UPPER(B81), " ", "")) | B81: Tundra Pattern | C81: せつげんのもよう | D81: Motif Glace | E81: Flockenmuster | F81: Motivo Tundra | G81: Motivo Manto di Neve | H81: 설원의 모양 | I81: 雪原花紋 | J81: =IFERROR(__xludf.DUMMYFUNCTION("GOOGLETRANSLATE(I81,""zh_HANT"",""zh_HANS"")"),"雪原花纹") | K81: =F81
A82: NAME_FORM_POKEBALLPATTERN | B82: Poké Ball Pattern | C82: ファンシーなもよう | D82: Motif Poké Ball | E82: =CONCATENATE(Items!E111,"-Muster") | F82: =G82 | G82: Motivo Poké Ball | H82: 볼의 모양 | I82: 球球花紋 | J82: =IFERROR(__xludf.DUMMYFUNCTION("GOOGLETRANSLATE(I82,""zh_HANT"",""zh_HANS"")"),"球球花纹") | K82: =F82
A83: =CONCATENATE("NAME_FORM_", SUBSTITUTE(UPPER(B83), " ", "")) | B83: Fancy Pattern | C83: ボールのもよう | D83: Motif Fantaisie | E83: Fantasiemuster | F83: Motivo Fantasía | G83: Motivo Sbarazzino | H83: 팬시한 모양 | I83: 幻彩花紋 | J83: =IFERROR(__xludf.DUMMYFUNCTION("GOOGLETRANSLATE(I83,""zh_HANT"",""zh_HANS"")"),"幻彩花纹") | K83: =F83
A84: =CONCATENATE("NAME_FORM_", SUBSTITUTE(UPPER(B84), " ", "")) | B84: Red Flower | C84: あかりはな | D84: Fleur Rouge | E84: Rotblütler | F84: Flor Roja | G84: Fiore Rosso | H84: 빨간 꽃 | I84: 紅花 | J84: =IFERROR(__xludf.DUMMYFUNCTION("GOOGLETRANSLATE(I84,""zh_HANT"",""zh_HANS"")"),"红花") | K84: =F84
A85: =CONCATENATE("NAME_FORM_", SUBSTITUTE(UPPER(B85), " ", "")) | B85: Yellow Flower | C85: きりろのはな | D85: Fleur Jaune | E85: Gelbblütler | F85: Flor Amarilla | G85: Fiore Giallo | H85: 노란 꽃 | I85: 黃花 | J85: =IFERROR(__xludf.DUMMYFUNCTION("GOOGLETRANSLATE(I85,""zh_HANT"",""zh_HANS"")"),"黄花") | K85: =F85
A86: =CONCATENATE("NAME_FORM_", SUBSTITUTE(UPPER(B86), " ", "")) | B86: Orange Flower | C86: オレンジいろのはな | D86: Fleur Orange | E86: Orangeblütler | F86: Flor Naranja | G86: Fiore Arancione | H86: 오렌지색 꽃 | I86: 橙花 | J86: =I86 | K86: =F86
A87: =CONCATENATE("NAME_FORM_", SUBSTITUTE(UPPER(B87), " ", "")) | B87: Blue Flower | C87: あおりはな | D87: Fleur Bleue | E87: Blaublütler | F87: Flor Azul | G87: Fiore Blu | H87: 파란 꽃 | I87: 藍花 | J87: =IFERROR(__xludf.DUMMYFUNCTION("GOOGLETRANSLATE(I87,""zh_HANT"",""zh_HANS"")"),"蓝花") | K87: =F87
A88: =CONCATENATE("NAME_FORM_", SUBSTITUTE(UPPER(B88), " ", "")) | B88: White Flower | C88: しろりはな | D88: Fleur Blanche | E88: Weißblütler | F88: Flor Blanca | G88: Fiore Bianco | H88: 하얀 꽃 | I88: 白花 | J88: =I88 | K88: =F88
A89: =CONCATENATE("NAME_FORM_", SUBSTITUTE(UPPER(B89), " ", "")) | B89: Eternal Flower | C89: えいえんのはな | D89: Fleur Éternelle | E89: Ewigblütler | F89: Flor Eterna | G89: Fiore Eterno | H89: 영원의 꽃 | I89: 永恆之花 | J89: =IFERROR(__xludf.DUMMYFUNCTION("GOOGLETRANSLATE(I89,""zh_HANT"",""zh_HANS"")"),"永恒之花") | K89: =F89
A90: =CONCATENATE("NAME_FORM_", SUBSTITUTE(UPPER(B90), " ", "")) | B90: Natural Form | C90: やせいのすがた | D90: Forme Sauvage | E90: Zottelform | F90: Forma Salvaje | G90: Forma Selvatica | H90: 야생의 모습 | I90: 野生的樣子 | J90: =IFERROR(__xludf.DUMMYFUNCTION("GOOGLETRANSLATE(I90,""zh_HANT"",""zh_HANS"")"),"野生的样子") | K90: =F90
A91: =CONCATENATE("NAME_FORM_", SUBSTITUTE(UPPER(B91), " ", "")) | B91: Heart Trim | C91: ハートカット | D91: Coupe Cœur | E91: Herzchenschnitt | F91: Corte Corazón | G91: Taglio Cuore | H91: 하트컷 | I91: 心形造型 | J91: =I91 | K91: =F91
A92: =CONCATENATE("NAME_FORM_", SUBSTITUTE(UPPER(B92), " ", "")) | B92: Star Trim | C92: スターカット | D92: Coupe Cœur | E92: Sternchenschnitt | F92: Corte Estrella | G92: Taglio Stella | H92: 스타컷 | I92: 星形造型 | J92: =I92 | K92: =F92
A93: =CONCATENATE("NAME_FORM_", SUBSTITUTE(UPPER(B93), " ", "")) | B93: Diamond Trim | C93: ダイヤカット | D93: Coupe Diamant | E93: Diamantenschnitt | F93: Corte Rondo | G93: Taglio Diamonte | H93: 다이아컷 | I93: 菱形造型 | J93: =I93 | K93: =F93
A94: =CONCATENATE("NAME_FORM_", SUBSTITUTE(UPPER(B94), " ", "")) | B94: Debutante Trim | C94: レヂィカット | D94: Coupe Demoiselle | E94: Fräuleinschnitt | F94: Corte Señorita | G94: Taglio Signorina | H94: 레이디컷 | I94: 淑女造型 | J94: =I94 | K94: =F94
A95: =CONCATENATE("NAME_FORM_", SUBSTITUTE(UPPER(B95), " ", "")) | B95: Matron Trim | C95: マダムカット | D95: Coupe Madame | E95: Damenschnitt | F95: Corte Dama | G95: Taglio Gentildonna | H95: 마담컷 | I95: 貴婦造型 | J95: =IFERROR(__xludf.DUMMYFUNCTION("GOOGLETRANSLATE(I95,""zh_HANT"",""zh_HANS"")"),"贵妇造型") | K95: =F95
A96: =CONCATENATE("NAME_FORM_", SUBSTITUTE(UPPER(B96), " ", "")) | B96: Dandy Trim | C96: ジェントルカット | D96: Coupe Monsieur | E96: Kavaliersschnitt | F96: Corte Caballero | G96: Taglio Gentiluomo | H96: 젠틀컷 | I96: 紳士造型 | J96: =IFERROR(__xludf.DUMMYFUNCTION("GOOGLETRANSLATE(I96,""zh_HANT"",""zh_HANS"")"),"绅士造型") | K96: =F96
A97: =CONCATENATE("NAME_FORM_", SUBSTITUTE(UPPER(B97), " ", "")) | B97: La Reine Trim | C97: クイーンカット | D97: Coupe Reine | E97: Königinnenschnitt | F97: Corte Aristocrático | G97: Taglio Regina | H97: 퀸컷 | I97: 女王造型 | J97: =I97 | K97: =F97
A98: =CONCATENATE("NAME_FORM_", SUBSTITUTE(UPPER(B98), " ", "")) | B98: Kabuki Trim | C98: カブキカット | D98: Coupe Kabuki | E98: Kabuki-Schnitt | F98: Corte Kabuki | G98: Taglio Kabuki | H98: 가부키컷 | I98: 歌舞伎造型 | J98: =I98 | K98: =F98
A99: =CONCATENATE("NAME_FORM_", SUBSTITUTE(UPPER(B99), " ", "")) | B99: Pharaoh Trim | C99: キングドムカット | D99: Coupe Pharaon | E99: Herrscherschnitt | F99: Corte Faraónico | G99: Taglio Faraone | H99: 킹덤컷 | I99: 國王造型 | J99: =IFERROR(__xludf.DUMMYFUNCTION("GOOGLETRANSLATE(I99,""zh_HANT"",""zh_HANS"")"),"国王造型") | K99: =F99
A100: =CONCATENATE("NAME_FORM_", SUBSTITUTE(UPPER(B100), " ", "")) | B100: Shield Forme | C100: シールドフォルム | D100: Forme Parade | E100: Schildform | F100: Forma Escudo | G100: Forma Scudo | H100: 실드폼 | I100: 盾牌形態 | J100: =IFERROR(__xludf.DUMMYFUNCTION("GOOGLETRANSLATE(I100,""zh_HANT"",""zh_HANS"")"),"盾牌形态") | K100: =F100
...

Sheet Categories
A1: =Pokemon!A1 | B1: =Pokemon!B1 | C1: =Pokemon!C1 | D1: =Pokemon!D1 | E1: =Pokemon!E1 | F1: =Pokemon!F1 | G1: =Pokemon!G1 | H1: =Pokemon!H1 | ... K1: =Pokemon!K1
A2: =CONCATENATE("CATEGORY_",UPPER(Pokemon!B2)) | B2: Seed | C2: たね | D2: Graine | E2: Samen | F2: Semilla | G2: Seme | H2: 씨앗 | I2: 種子 | J2: =IFERROR(__xludf.DUMMYFUNCTION("GOOGLETRANSLATE(I2, ""zh_HANT"",""zh_HANS"")"),"种子") | K2: =F2
A3: =CONCATENATE("CATEGORY_",UPPER(Pokemon!B3)) | B3: =B2 | C3: =C2 | D3: =D2 | E3: =E2 | F3: =F2 | G3: =G2 | H3: =H2 | I3: =I2 | J3: =J2 | K3: =F3
A4: =CONCATENATE("CATEGORY_",UPPER(Pokemon!B4)) | B4: =B2 | C4: =C2 | D4: =D2 | E4: =E2 | F4: =F2 | G4: =G2 | H4: =H2 | I4: =I2 | J4: =J2 | K4: =F4
A5: =CONCATENATE("CATEGORY_",UPPER(Pokemon!B5)) | B5: Lizard | C5: とかげ | D5: Lézard | E5: Echse | F5: Lagartija | G5: Lucertola | H5: 도롱뇽 | I5: 蜥蜴 | J5: =I5 | K5: =F5
A6: =CONCATENATE("CATEGORY_",UPPER(Pokemon!B6)) | B6: Flame | C6: かえん | D6: Flamme | E6: =D6 | F6: Llama | G6: Fiamma | H6: 화염 | I6: 火焰 | J6: =I6 | K6: =F6
A7: =CONCATENATE("CATEGORY_",UPPER(Pokemon!B7)) | B7: =B6 | C7: =C6 | D7: =D6 | E7: =E6 | F7: =F6 | G7: =G6 | H7: =H6 | I7: =I6 | J7: =J6 | K7: =F7
A8: =CONCATENATE("CATEGORY_",UPPER(Pokemon!B8)) | B8: Tiny Turtle | C8: かめのこ | D8: Minitortue | E8: Minikröte | F8: Tortuguita | G8: Tartaghina | H8: 꼬마거북 | I8: 小龜 | J8: =IFERROR(__xludf.DUMMYFUNCTION("GOOGLETRANSLATE(I8, ""zh_HANT"",""zh_HANS"")"),"小龟") | K8: =F8
A9: =CONCATENATE("CATEGORY_",UPPER(Pokemon!B9)) | B9: Turtle | C9: かめ | D9: Tortue | E9: Kröte | F9: Tortuga | G9: Tartaruga | H9: 거북 | I9: =IFERROR(__xludf.DUMMYFUNCTION("GOOGLETRANSLATE(J9,""zh_HANS"",""zh_HANT"")"),"龜") | J9: 龟 | K9: =F9
A10: =CONCATENATE("CATEGORY_",UPPER(Pokemon!B10)) | B10: Shellfish | C10: こうら | D10: Carapace | E10: Schaltier | F10: Marisco | G10: Crostaceo | H10: 껍질 | I10: 甲殼 | J10: =IFERROR(__xludf.DUMMYFUNCTION("GOOGLETRANSLATE(I10, ""zh_HANT"",""zh_HANS"")"),"甲壳") | K10: =F10
A11: =CONCATENATE("CATEGORY_",UPPER(Pokemon!B11)) | B11: Worm | C11: いもむし | D11: Ver | E11: Wurm | F11: Gusano | G11: Baco | H11: 애벌레 | I11: 蟲寶寶 | J11: =IFERROR(__xludf.DUMMYFUNCTION("GOOGLETRANSLATE(I11, ""zh_HANT"",""zh_HANS"")"),"虫宝宝") | K11: =F11
A12: =CONCATENATE("CATEGORY_",UPPER(Pokemon!B12)) | B12: Cocoon | C12: さなぎ | D12: Cocon | E12: Kokon | F12: Capullo | G12: Bozzolo | H12: 번데기 | I12: 蛹 | J12: =I12 | K12: =F12
A13: =CONCATENATE("CATEGORY_",UPPER(Pokemon!B13)) | B13: Butterfly | C13: ちょうちょ | D13: Papillon | E13: Falter | F13: Mariposa | G13: Farfalla | H13: 나비 | I13: 蝴蝶 | J13: =I13 | K13: =F13
A14: =CONCATENATE("CATEGORY_",UPPER(Pokemon!B14)) | B14: Hairy Bug | C14: えむし | D14: Insectopic | E14: Raupe | F14: Oruga | G14: Millepiedi | H14: 송충이 | I14: 毛毛蟲 | J14: =IFERROR(__xludf.DUMMYFUNCTION("GOOGLETRANSLATE(I14, ""zh_HANT"",""zh_HANS"")"),"毛毛虫") | K14: =F14
A15: =CONCATENATE("CATEGORY_",UPPER(Pokemon!B15)) | B15: =B12 | C15: =C12 | D15: =D12 | E15: =E12 | F15: =F12 | G15: =G12 | H15: =H12 | I15: =I12 | J15: =J12 | K15: =F15
A16: =CONCATENATE("CATEGORY_",UPPER(Pokemon!B16)) | B16: Poison Bee | C16: どくばち | D16: Guêpoison | E16: Giftbiene | F16: Abeja Ven. | G16: Velenape | H16: 독벌 | I16: 毒蜂 | J16: =I16 | K16: =F16
A17: =CONCATENATE("CATEGORY_",UPPER(Pokemon!B17)) | B17: Tiny Bird | C17: ことり | D17: Minoiseau | E17: Kleinvogel | F17: Pajarito | G17: Uccellino | H17: 아기새 | I17: 小鳥 | J17: =IFERROR(__xludf.DUMMYFUNCTION("GOOGLETRANSLATE(I17, ""zh_HANT"",""zh_HANS"")"),"小鸟") | K17: =F17
A18: =CONCATENATE("CATEGORY_",UPPER(Pokemon!B18)) | B18: Bird | C18: とり | D18: Oiseau | E18: Vogel | F18: Pájaro | G18: Uccello | H18: 새 | I18: 鳥 | J18: =IFERROR(__xludf.DUMMYFUNCTION("GOOGLETRANSLATE(I18, ""zh_HANT"",""zh_HANS"")"),"鸟") | K18: =F18
A19: =CONCATENATE("CATEGORY_",UPPER(Pokemon!B19)) | B19: =B18 | C19: =C18 | D19: =D18 | E19: =E18 | F19: =F18 | G19: =G18 | H19: =H18 | I19: =I18 | J19: =IFERROR(__xludf.DUMMYFUNCTION("GOOGLETRANSLATE(I19, ""zh_HANT"",""zh_HANS"")"),"鸟") | K19: =F19
A20: =CONCATENATE("CATEGORY_",UPPER(Pokemon!B20)) | B20: Mouse | C20: ねずみ | D20: Souris | E20: Maus | F20: Ratón | G20: Topo | H20: 쥐 | I20: 鼠 | J20: =I20 | K20: =F20
A21: =CONCATENATE("CATEGORY_",UPPER(Pokemon!B21)) | B21: =B20 | C21: =C20 | D21: =D20 | E21: =E20 | F21: =F20 | G21: =G20 | H21: =H20 | I21: =I20 | J21: =J20 | K21: =F21
A22: =CONCATENATE("CATEGORY_",UPPER(Pokemon!B22)) | B22: =B17 | C22: =C17 | D22: =D17 | E22: =E17 | F22: =F17 | G22: =G17 | H22: =H17 | I22: =I17 | J22: =J17 | K22: =F22
A23: =CONCATENATE("CATEGORY_",UPPER(Pokemon!B23)) | B23: Beak | C23: くちばし | D23: Bec-Oiseau | E23: Pickvogel | F23: Pico | G23: Becco | H23: 부리 | I23: 鳥嘴 | J23: =IFERROR(__xludf.DUMMYFUNCTION("GOOGLETRANSLATE(I23, ""zh_HANT"",""zh_HANS"")"),"鸟嘴") | K23: =F23
A24: =CONCATENATE("CATEGORY_",UPPER(Pokemon!B24)) | B24: Snake | C24: へび | D24: Serpent | E24: Schlange | F24: Serpiente | G24: Serpente | H24: 뱀 | I24: 蛇 | J24: =I24 | K24: =F24
A25: =CONCATENATE("CATEGORY_",UPPER(Pokemon!B25)) | B25: Cobra | C25: コブラ | D25: Cobra | E25: Kobra | F25: =B25 | G25: =B25 | H25: 코브라 | I25: 眼鏡蛇 | J25: =IFERROR(__xludf.DUMMYFUNCTION("GOOGLETRANSLATE(I25, ""zh_HANT"",""zh_HANS"")"),"眼镜蛇") | K25: =F25
A26: =CONCATENATE("CATEGORY_",UPPER(Pokemon!B26)) | B26: =B20 | C26: =C20 | D26: =D20 | E26: =E20 | F26: =F20 | G26: =G20 | H26: =H20 | I26: =I20 | J26: =J20 | K26: =F26
A27: =CONCATENATE("CATEGORY_",UPPER(Pokemon!B27)) | B27: =B20 | C27: =C20 | D27: =D20 | E27: =E20 | F27: =F20 | G27: =G20 | H27: =H20 | I27: =I20 | J27: =J20 | K27: =F27
A28: =CONCATENATE("CATEGORY_",UPPER(Pokemon!B28)) | B28: =B20 | C28: =C20 | D28: =D20 | E28: =E20 | F28: =F20 | G28: =G20 | H28: =H20 | I28: =I20 | J28: =J20 | K28: =F28
A29: =CONCATENATE("CATEGORY_",UPPER(Pokemon!B29)) | B29: =B20 | C29: =C20 | D29: =D20 | E29: =E20 | F29: =F20 | G29: =G20 | H29: =H20 | I29: =I20 | J29: =J20 | K29: =F29
A30: CATEGORY_NIDORAN-F | B30: Poison Pin | C30: どくばり | D30: Vénépic | E30: Giftdorn | F30: Pin Veneno | G30: Velenago | H30: 독침 | I30: 毒針 | J30: =IFERROR(__xludf.DUMMYFUNCTION("GOOGLETRANSLATE(I30, ""zh_HANT"",""zh_HANS"")"),"毒针") | K30: =F30
A31: =CONCATENATE("CATEGORY_",UPPER(Pokemon!B31)) | B31: =B30 | C31: =C30 | D31: =D30 | E31: =E30 | F31: =F30 | G31: =G30 | H31: =H30 | I31: =I30 | J31: =J30 | K31: =F31
A32: =CONCATENATE("CATEGORY_",UPPER(Pokemon!B32)) | B32: Drill | C32: ドリル | D32: Perceur | E32: Bohrer | F32: Taladro | G32: Trapano | H32: 드릴 | I32: 鑽錐 | J32: =IFERROR(__xludf.DUMMYFUNCTION("GOOGLETRANSLATE(I32, ""zh_HANT"",""zh_HANS"")"),"钻锥") | K32: =F32
A33: CATEGORY_NIDORAN-M | B33: =B30 | C33: =C30 | D33: =D30 | E33: =E30 | F33: =F30 | G33: =G30 | H33: =H30 | I33: =I30 | J33: =J30 | K33: =F33
A34: =CONCATENATE("CATEGORY_",UPPER(Pokemon!B34)) | B34: =B30 | C34: =C30 | D34: =D30 | E34: =E30 | F34: =F30 | G34: =G30 | H34: =H30 | I34: =I30 | J34: =J30 | K34: =F34
A35: =CONCATENATE("CATEGORY_",UPPER(Pokemon!B35)) | B35: =B32 | C35: =C32 | D35: =D32 | E35: =E32 | F35: =F32 | G35: =G32 | H35: =H32 | I35: =I32 | J35: =J32 | K35: =F35
A36: =CONCATENATE("CATEGORY_",UPPER(Pokemon!B36)) | B36: =Types!B19 | C36: ようせい | D36: =Types!D19 | E36: =Types!E19 | F36: =Types!F19 | G36: Fata | H36: 요정 | I36: =Types!I19 | J36: =Types!J19 | K36: =F36
A37: =CONCATENATE("CATEGORY_",UPPER(Pokemon!B37)) | B37: =B36 | C37: =C36 | D37: =D36 | E37: =E36 | F37: =F36 | G37: =G36 | H37: =H36 | I37: =I36 | J37: =J36 | K37: =F37
A38: =CONCATENATE("CATEGORY_",UPPER(Pokemon!B38)) | B38: Fox | C38: きつね | D38: Renard | E38: Fuchs | F38: Zorro | G38: Volpe | H38: 여우 | I38: 狐狸 | J38: =I38 | K38: =F38
A39: =CONCATENATE("CATEGORY_",UPPER(Pokemon!B39)) | B39: =B38 | C39: =C38 | D39: =D38 | E39: =E38 | F39: =F38 | G39: =G38 | H39: =H38 | I39: =I38 | J39: =J38 | K39: =F39
A40: =CONCATENATE("CATEGORY_",UPPER(Pokemon!B40)) | B40: Balloon | C40: ふうせん | D40: Bouboule | E40: Ballon | F40: Globo | G40: Pallone | H40: 풍선 | I40: 氣球 | J40: =IFERROR(__xludf.DUMMYFUNCTION("GOOGLETRANSLATE(I40, ""zh_HANT"",""zh_HANS"")"),"气球") | K40: =F40
A41: =CONCATENATE("CATEGORY_",UPPER(Pokemon!B41)) | B41: =B40 | C41: =C40 | D41: =D40 | E41: =E40 | F41: =F40 | G41: =G40 | H41: =H40 | I41: =I40 | J41: =J40 | K41: =F41
A42: =CONCATENATE("CATEGORY_",UPPER(Pokemon!B42)) | B42: Bat | C42: こうもり | D42: Chovsouris | E42: Fledermaus | F42: Murciélago | G42: Pipistrello | H42: 박쥐 | I42: =J42 | J42: 蝙蝠 | K42: =F42
A43: =CONCATENATE("CATEGORY_",UPPER(Pokemon!B43)) | B43: =B42 | C43: =C42 | D43: =D42 | E43: =E42 | F43: =F42 | G43: =G42 | H43: =H42 | I43: =I42 | J43: =J42 | K43: =F43
A44: =CONCATENATE("CATEGORY_",UPPER(Pokemon!B44)) | B44: Weed | C44: ぎっそう | D44: Racine | E44: Unkraut | F44: Hierbajo | G44: Malerba | H44: 잡초 | I44: 雜草 | J44: =IFERROR(__xludf.DUMMYFUNCTION("GOOGLETRANSLATE(I44, ""zh_HANT"",""zh_HANS"")"),"杂草") | K44: =F44
A45: =CONCATENATE("CATEGORY_",UPPER(Pokemon!B45)) | B45: =B44 | C45: =C44 | D45: =D44 | E45: =E44 | F45: =F44 | G45: =G44 | H45: =H44 | I45: =I44 | J45: =J44 | K45: =F45
A46: =CONCATENATE("CATEGORY_",UPPER(Pokemon!B46)) | B46: Flower | C46: フラワー | D46: Fleur | E46: Blume | F46: Flor | G46: Fiore | H46: 꽃 | I46: 花 | J46: =I46 | K46: =F46
A47: =CONCATENATE("CATEGORY_",UPPER(Pokemon!B47)) | B47: Mushroom | C47: きのこ | D47: Champignon | E47: Pilz | F47: Hongo | G47: Fungo | H47: 버섯 | I47: 蘑菇 | J47: =I47 | K47: =F47
A48: =CONCATENATE("CATEGORY_",UPPER(Pokemon!B48)) | B48: =B47 | C48: =C47 | D48: =D47 | E48: =E47 | F48: =F47 | G48: =G47 | H48: =H47 | I48: =I47 | J48: =J47 | K48: =F48
A49: =CONCATENATE("CATEGORY_",UPPER(Pokemon!B49)) | B49: Insect | C49: こんちゅう | D49: Vermine | E49: Insekt | F49: Insecto | G49: Insetto | H49: 곤충 | I49: 昆蟲 | J49: =IFERROR(__xludf.DUMMYFUNCTION("GOOGLETRANSLATE(I49, ""zh_HANT"",""zh_HANS"")"),"昆虫") | K49: =F49
A50: =CONCATENATE("CATEGORY_",UPPER(Pokemon!B50)) | B50: Poison Moth | C50: どくが | D50: Papipoison | E50: Giftmotte | F50: Polilla Ven. | G50: Velentarma | H50: 독나방 | I50: 毒蛾 | J50: =I50 | K50: =F50
A51: =CONCATENATE("CATEGORY_",UPPER(Pokemon!B51)) | B51: Mole | C51: もぐら | D51: Taupe | E51: Maulwurf | F51: Topo | G51: Talpa | H51: 두더지 | I51: 鼴鼠 | J51: =IFERROR(__xludf.DUMMYFUNCTION("GOOGLETRANSLATE(I51, ""zh_HANT"",""zh_HANS"")"),"鼹鼠") | K51: =F51
A52: =CONCATENATE("CATEGORY_",UPPER(Pokemon!B52)) | B52: =B51 | C52: =C51 | D52: =D51 | E52: =E51 | F52: =F51 | G52: =G51 | H52: =H51 | I52: =I51 | J52: =J51 | K52: =F52
A53: =CONCATENATE("CATEGORY_",UPPER(Pokemon!B53)) | B53: Scratch Cat | C53: ばけねこ | D53: Chadégout | E53: Katze | F53: Gato Araña | G53: Graffimiao | H53: 요괴고양이 | I53: 妖怪貓 | J53: =IFERROR(__xludf.DUMMYFUNCTION("GOOGLETRANSLATE(I53, ""zh_HANT"",""zh_HANS"")"),"妖怪猫") | K53: =F53
A54: =CONCATENATE("CATEGORY_",UPPER(Pokemon!B54)) | B54: Classy Cat | C54: シャムネコ | D54: Chadeville | E54: Rassekatze | F54: Gato Fino | G54: Nobilgatto | H54: 샴고양이 | I54: 暹羅貓 | J54: =IFERROR(__xludf.DUMMYFUNCTION("GOOGLETRANSLATE(I54, ""zh_HANT"",""zh_HANS"")"),"暹罗猫") | K54: =F54
A55: =CONCATENATE("CATEGORY_",UPPER(Pokemon!B55)) | B55: Duck | C55: あひる | D55: Canard | E55: Ente | F55: Pato | G55: Papero | H55: 오리 | I55: 鴨 | J55: =IFERROR(__xludf.DUMMYFUNCTION("GOOGLETRANSLATE(I55, ""zh_HANT"",""zh_HANS"")"),"鸭") | K55: =F55
A56: =CONCATENATE("CATEGORY_",UPPER(Pokemon!B56)) | B56: =B55 | C56: =C55 | D56: =D55 | E56: =E55 | F56: =F55 | G56: =G55 | H56: =H55 | I56: =I55 | J56: =J55 | K56: =F56
A57: =CONCATENATE("CATEGORY_",UPPER(Pokemon!B57)) | B57: Pig Monkey | C57: ぶたざる | D57: Porsinge | E57: Schwein / Affe | F57: Mono Cerdo | G57: Suinpanzé | H57: 돈숭이 | I57: 豬猴 | J57: =IFERROR(__xludf.DUMMYFUNCTION("GOOGLETRANSLATE(I57, ""zh_HANT"",""zh_HANS"")"),"猪猴") | K57: =F57
A58: =CONCATENATE("CATEGORY_",UPPER(Pokemon!B58)) | B58: =B57 | C58: =C57 | D58: =D57 | E58: =E57 | F58: =F57 | G58: =G57 | H58: =H57 | I58: =I57 | J58: =J57 | K58: =F58
A59: =CONCATENATE("CATEGORY_",UPPER(Pokemon!B59)) | B59: Puppy | C59: こいぬ | D59: Chiot | E59: Welpen | F59: Perrito | G59: Cagnolino | H59: 강아지 | I59: 小狗 | J59: =I59 | K59: =F59
A60: =CONCATENATE(A59,"-H") | B60: =B173 | C60: =C173 | D60: =D173 | E60: =E173 | F60: =F173 | G60: =G173 | H60: =H173 | I60: =I173 | J60: =J173 | K60: =F60
A61: =CONCATENATE("CATEGORY_",UPPER(Pokemon!B60)) | B61: Legendary | C61: でんせつ | D61: Légendaire | E61: Legendär | F61: Legendario | G61: Leggenda | H61: 전설 | I61: 傳說 | J61: =IFERROR(__xludf.DUMMYFUNCTION("GOOGLETRANSLATE(I61, ""zh_HANT"",""zh_HANS"")"),"传说") | K61: =F61
A62: =CONCATENATE("CATEGORY_",UPPER(Pokemon!B61)) | B62: Tadpole | C62: おたま | D62: Têtard | E62: Kaulquappe | F62: Renacuajo | G62: Girino | H62: 올챙이 | I62: 蝌蚪 | J62: =I62 | K62: =F62
A63: =CONCATENATE("CATEGORY_",UPPER(Pokemon!B62)) | B63: =B62 | C63: =C62 | D63: =D62 | E63: =E62 | F63: =F62 | G63: =G62 | H63: =H62 | I63: =I62 | J63: =J62 | K63: =F63
A64: =CONCATENATE("CATEGORY_",UPPER(Pokemon!B63)) | B64: =B62 | C64: =C62 | D64: =D62 | E64: =E62 | F64: =F62 | G64: =G62 | H64: =H62 | I64: =I62 | J64: =J62 | K64: =F64
A65: =CONCATENATE("CATEGORY_",UPPER(Pokemon!B64)) | B65: Psi | C65: ねんりき | D65: Psy | E65: =B65 | F65: =B65 | G65: Psico | H65: 초능력 | I65: 念力 | J65: =I65 | K65: =F65
A66: =CONCATENATE("CATEGORY_",UPPER(Pokemon!B65)) | B66: =B65 | C66: =C65 | D66: =D65 | E66: =E65 | F66: =F65 | G66: =G65 | H66: =H65 | I66: =I65 | J66: =J65 | K66: =F66
A67: =CONCATENATE("CATEGORY_",UPPER(Pokemon!B66)) | B67: =B65 | C67: =C65 | D67: =D65 | E67: =E65 | F67: =F65 | G67: =G65 | H67: =H65 | I67: =I65 | J67: =J65 | K67: =F67
A68: =CONCATENATE("CATEGORY_",UPPER(Pokemon!B67)) | B68: Superpower | C68: かいりき | D68: Colosse | E68: Kraftprotz | F68: Superpoder | G68: Megaforza | H68: 괴력 | I68: 怪力 | J68: =I68 | K68: =F68
A69: =CONCATENATE("CATEGORY_",UPPER(Pokemon!B68)) | B69: =B68 | C69: =C68 | D69: =D68 | E69: =E68 | F69: =F68 | G69: =G68 | H69: =H68 | I69: =I68 | J69: =J68 | K69: =F69
A70: =CONCATENATE("CATEGORY_",UPPER(Pokemon!B69)) | B70: =B68 | C70: =C68 | D70: =D68 | E70: =E68 | F70: =F68 | G70: =G68 | H70: =H68 | I70: =I68 | J70: =J68 | K70: =F70
A71: =CONCATENATE("CATEGORY_",UPPER(Pokemon!B70)) | B71: =B46 | C71: =C46 | D71: =D46 | E71: =E46 | F71: =F46 | G71: =G46 | H71: =H46 | I71: =I46 | J71: =J46 | K71: =F71
A72: =CONCATENATE("CATEGORY_",UPPER(Pokemon!B71)) | B72: Flycatcher | C72: ハエトリ | D72: Carnivore | E72: Fliegentot | F72: Matamoscas | G72: Moschivoro | H72: 파리잡이 | I72: 捕蠅 | J72: =IFERROR(__xludf.DUMMYFUNCTION("GOOGLETRANSLATE(I72, ""zh_HANT"",""zh_HANS"")"),"捕蝇") | K72: =F72
A73: =CONCATENATE("CATEGORY_",UPPER(Pokemon!B72)) | B73: =B72 | C73: =C72 | D73: =D72 | E73: =E72 | F73: =F72 | G73: =G72 | H73: =H72 | I73: =I72 | J73: =J72 | K73: =F73
A74: =CONCATENATE("CATEGORY_",UPPER(Pokemon!B73)) | B74: Jellyfish | C74: くらげ | D74: Mollusque | E74: Qualle | F74: Medusa | G74: =F74 | H74: 해파리 | I74: 水母 | J74: =I74 | K74: =F74
A75: =CONCATENATE("CATEGORY_",UPPER(Pokemon!B74)) | B75: =B74 | C75: =C74 | D75: =D74 | E75: =E74 | F75: =F74 | G75: =G74 | H75: =H74 | I75: =I74 | J75: =J74 | K75: =F75
A76: =CONCATENATE("CATEGORY_",UPPER(Pokemon!B75)) | B76: =Types!B7 | C76: がんせき | D76: =Types!D7 | E76: =Types!E7 | F76: =Types!F7 | G76: =Types!G7 | H76: 암석 | I76: =Types!I7 | J76: =Types!J7 | K76: =F76
A77: =CONCATENATE("CATEGORY_",UPPER(Pokemon!B76)) | B77: =B76 | C77: =C76 | D77: =D76 | E77: =E76 | F77: =F76 | G77: =G76 | H77: =H76 | I77: =I76 | J77: =J76 | K77: =F77
A78: =CONCATENATE("CATEGORY_",UPPER(Pokemon!B77)) | B78: Megaton | C78: メガトン | D78: Titanesque | E78: Urgestein | F78: Megatón | G78: Megatone | H78: 메가톤 | I78: 重量級 | J78: =IFERROR(__xludf.DUMMYFUNCTION("GOOGLETRANSLATE(I78, ""zh_HANT"",""zh_HANS"")"),"重量级") | K78: =F78
A79: =CONCATENATE("CATEGORY_",UPPER(Pokemon!B78)) | B79: Fire Horse | C79: ひのうま | D79: Cheval Feu | E79: Feuerpferd | F79: Caballo F. | G79: Cavalfuoco | H79: 불의말 | I79: 火馬 | J79: =IFERROR(__xludf.DUMMYFUNCTION("GOOGLETRANSLATE(I79, ""zh_HANT"",""zh_HANS"")"),"火马") | K79: =F79
A80: =CONCATENATE(A79,"-G") | B80: Unique Horn | C80: いっかく | D80: Monocorne | E80: Einhorn | F80: Unicorne | G80: Singolcorno | H80: 일각 | I80: =J80 | J80: 一角 | K80: =F80
A81: =CONCATENATE("CATEGORY_",UPPER(Pokemon!B79)) | B81: =B79 | C81: =C79 | D81: =D79 | E81: =E79 | F81: =F79 | G81: =G79 | H81: =H79 | I81: =I79 | J81: =J79 | K81: =F81
A82: =CONCATENATE(A81,"-G") | B82: =B80 | C82: =C80 | D82: =D80 | E82: =E80 | F82: =F80 | G82: =G80 | H82: =H80 | I82: =I80 | J82: =J80 | K82: =F82
A83: =CONCATENATE("CATEGORY_",UPPER(Pokemon!B80)) | B83: Dopey | C83: まぬけ | D83: Crétin | E83: Schnarcher | F83: Atontado | G83: Ronfone | H83: 얼간이 | I83: 憨憨 | J83: =I83 | K83: =F83
A84: =CONCATENATE("CATEGORY_",UPPER(Pokemon!B81)) | B84: Hermit Crab | C84: やどかり | D84: Symbiose | E84: =D84 | F84: Ermitaño | G84: Paguro | H84: 기생 | I84: 寄居蟹 | J84: =I84 | K84: =F84
A85: =CONCATENATE("CATEGORY_",UPPER(Pokemon!B82)) | B85: =Items!B306 | C85: =Items!C306 | D85: Magnétique | E85: =Items!E306 | F85: =Items!F306 | G85: =Items!G306 | H85: 자석 | I85: 磁鐵 | J85: =IFERROR(__xludf.DUMMYFUNCTION("GOOGLETRANSLATE(I85, ""zh_HANT"",""zh_HANS"")"),"磁铁") | K85: =F85
A86: =CONCATENATE("CATEGORY_",UPPER(Pokemon!B83)) | B86: =B85 | C86: =C85 | D86: =D85 | E86: =E85 | F86: =F85 | G86: =G85 | H86: =H85 | I86: =I85 | J86: =J85 | K86: =F86
A87: =CONCATENATE("CATEGORY_",UPPER(Pokemon!B84)) | B87: Wild Duck | C87: かるがも | D87: Canard Fou | E87: Wildente | F87: Pato Salvaje | G87: Salvanatra | H87: 천둥오리 | I87: 黃嘴鴨 | J87: =IFERROR(__xludf.DUMMYFUNCTION("GOOGLETRANSLATE(I87, ""zh_HANT"",""zh_HANS"")"),"黄嘴鸭") | K87: =F87
A88: =CONCATENATE("CATEGORY_",UPPER(Pokemon!B85)) | B88: Twin Bird | C88: ふたごどり | D88: Duoiseau | E88: Duovogel | F88: Ave Gemela | G88: Biucello | H88: 쌍둥이새 | I88: 兩頭鳥 | J88: =IFERROR(__xludf.DUMMYFUNCTION("GOOGLETRANSLATE(I88, ""zh_HANT"",""zh_HANS"")"),"两头鸟") | K88: =F88
A89: =CONCATENATE("CATEGORY_",UPPER(Pokemon!B86)) | B89: Triple Bird | C89: みつごどり | D89: Trioiseau | E89: Trivogel | F89: Ave Triple | G89: Triucello | H89: 세쌍둥이새 | I89: 三頭鳥 | J89: =IFERROR(__xludf.DUMMYFUNCTION("GOOGLETRANSLATE(I89, ""zh_HANT"",""zh_HANS"")"),"三头鸟") | K89: =F89
A90: =CONCATENATE("CATEGORY_",UPPER(Pokemon!B87)) | B90: Sea Lion | C90: あしか | D90: Otarie | E90: Seehund | F90: León Marino | G90: Otaria | H90: 강치 | I90: 海獅 | J90: =IFERROR(__xludf.DUMMYFUNCTION("GOOGLETRANSLATE(I90, ""zh_HANT"",""zh_HANS"")"),"海狮") | K90: =F90
A91: =CONCATENATE("CATEGORY_",UPPER(Pokemon!B88)) | B91: =B90 | C91: =C90 | D91: =D90 | E91: =E90 | F91: =F90 | G91: =G90 | H91: =H90 | I91: =I90 | J91: =J90 | K91: =F91
A92: =CONCATENATE("CATEGORY_",UPPER(Pokemon!B89)) | B92: =Moves!B125 | C92: ヘドロ | D92: Dégueu | E92: Schlamm | F92: Lodo | G92: Melma | H92: 진흙 | I92: 污泥 | J92: =I92 | K92: =F92
A93: =CONCATENATE("CATEGORY_",UPPER(Pokemon!B90)) | B93: =B92 | C93: =C92 | D93: =D92 | E93: =E92 | F93: =F92 | G93: =G92 | H93: =H92 | I93: =I92 | J93: =J92 | K93: =F93
A94: =CONCATENATE("CATEGORY_",UPPER(Pokemon!B91)) | B94: Bivalve | C94: ２まいがい | D94: Bivalve | E94: Muschel | F94: Bivalvo | G94: =B94 | H94: 두조개 | I94: 雙殼貝 | J94: =IFERROR(__xludf.DUMMYFUNCTION("GOOGLETRANSLATE(I94, ""zh_HANT"",""zh_HANS"")"),"双壳贝") | K94: =F94
A95: =CONCATENATE("CATEGORY_",UPPER(Pokemon!B92)) | B95: =B94 | C95: =C94 | D95: =D94 | E95: =E94 | F95: =F94 | G95: =G94 | H95: =H94 | I95: =I94 | J95: =J94 | K95: =F95
A96: =CONCATENATE("CATEGORY_",UPPER(Pokemon!B93)) | B96: Gas | C96: ガスじょう | D96: Gaz | E96: =B96 | F96: =B96 | G96: =B96 | H96: 가스 | I96: 氣體狀 | J96: =IFERROR(__xludf.DUMMYFUNCTION("GOOGLETRANSLATE(I96, ""zh_HANT"",""zh_HANS"")"),"气体状") | K96: =F96
A97: =CONCATENATE("CATEGORY_",UPPER(Pokemon!B94)) | B97: =B96 | C97: =C96 | D97: =D96 | E97: =E96 | F97: =F96 | G97: =G96 | H97: =H96 | I97: =I96 | J97: =J96 | K97: =F97
A98: =CONCATENATE("CATEGORY_",UPPER(Pokemon!B95)) | B98: Shadow | C98: シャドー | D98: Ombre | E98: Schatten | F98: Sombra | G98: Ombra | H98: 그림자 | I98: 影子 | J98: =I98 | K98: =F98
A99: =CONCATENATE("CATEGORY_",UPPER(Pokemon!B96)) | B99: Rock Snake | C99: いわへび | D99: Serpenroc | E99: Felsnatter | F99: Serp. Roca | G99: Serpesasso | H99: 돌뱀 | I99: 岩蛇 | J99: =I99 | K99: =F99
A100: =CONCATENATE("CATEGORY_",UPPER(Pokemon!B97)) | B100: =Moves!B96 | C100: さいみん | D100: =Moves!D96 | E100: =Moves!E96 | F100: =Moves!F96 | G100: =Moves!G96 | H100: 최면 | I100: 催眠 | J100: =I100 | K100: =F100
...

Sheet Types
A1: =Pokemon!A1 | B1: =Pokemon!B1 | C1: =Pokemon!C1 | D1: =Pokemon!D1 | E1: =Pokemon!E1 | F1: =Pokemon!F1 | G1: =Pokemon!G1 | H1: =Pokemon!H1 | ... K1: =Pokemon!K1
A2: =CONCATENATE("NAME_TYPE_", UPPER(B2)) | B2: Normal | C2: ノーマル | D2: =B2 | E2: =B2 | F2: =B2 | G2: Normale | H2: 노말 | I2: =J2 | J2: 一般 | K2: =F2
A3: =CONCATENATE("NAME_TYPE_", UPPER(B3)) | B3: Fighting | C3: かくとう | D3: Combat | E3: Kampf | F3: Lucha | G3: Lotta | H3: 격투 | I3: =IFERROR(__xludf.DUMMYFUNCTION("GOOGLETRANSLATE(J3,""zh_HANS"",""zh_HANT"")"),"格鬥") | J3: 格斗 | K3: =F3
A4: =CONCATENATE("NAME_TYPE_", UPPER(B4)) | B4: Flying | C4: ひこう | D4: Vol | E4: Flug | F4: Volador | G4: Volante | H4: 비행 | I4: =IFERROR(__xludf.DUMMYFUNCTION("GOOGLETRANSLATE(J4,""zh_HANS"",""zh_HANT"")"),"飛行") | J4: 飞行 | K4: =F4
A5: =CONCATENATE("NAME_TYPE_", UPPER(B5)) | B5: Poison | C5: どく | D5: =B5 | E5: Gift | F5: Veneno | G5: Veleno | H5: 독 | I5: =J5 | J5: 毒 | K5: =F5
A6: =CONCATENATE("NAME_TYPE_", UPPER(B6)) | B6: Ground | C6: じめん | D6: Sol | E6: Boden | F6: Tierra | G6: Terra | H6: 땅 | I6: =J6 | J6: 地面 | K6: =F6
A7: =CONCATENATE("NAME_TYPE_", UPPER(B7)) | B7: Rock | C7: いわ | D7: Roche | E7: Gestein | F7: Roca | G7: Roccia | H7: 바위 | I7: =J7 | J7: 岩石 | K7: =F7
A8: =CONCATENATE("NAME_TYPE_", UPPER(B8)) | B8: Bug | C8: むし | D8: Insecte | E8: Käfer | F8: Bicho | G8: Coleottero | H8: 벌레 | I8: =IFERROR(__xludf.DUMMYFUNCTION("GOOGLETRANSLATE(J8,""zh_HANS"",""zh_HANT"")"),"蟲") | J8: 虫 | K8: =F8
A9: =CONCATENATE("NAME_TYPE_", UPPER(B9)) | B9: Ghost | C9: ゴースト | D9: Spectre | E9: Geist | F9: Fantasma | G9: Spettro | H9: 고스트 | I9: =IFERROR(__xludf.DUMMYFUNCTION("GOOGLETRANSLATE(J9,""zh_HANS"",""zh_HANT"")"),"幽靈") | J9: 幽灵 | K9: =F9
A10: =CONCATENATE("NAME_TYPE_", UPPER(B10)) | B10: Steel | C10: はがね | D10: Acier | E10: Stahl | F10: Acero | G10: Acciaio | H10: 강철 | I10: =IFERROR(__xludf.DUMMYFUNCTION("GOOGLETRANSLATE(J10,""zh_HANS"",""zh_HANT"")"),"鋼") | J10: 钢 | K10: =F10
A11: =CONCATENATE("NAME_TYPE_", UPPER(B11)) | B11: Fire | C11: ほのお | D11: Feu | E11: Feuer | F11: Fuego | G11: Fuoco | H11: 불꽃 | I11: 火 | J11: =I11 | K11: =F11
A12: =CONCATENATE("NAME_TYPE_", UPPER(B12)) | B12: Water | C12: みず | D12: Eau | E12: Wasser | F12: Agua | G12: Acqua | H12: 물 | I12: 水 | J12: =I12 | K12: =F12
A13: =CONCATENATE("NAME_TYPE_", UPPER(B13)) | B13: Grass | C13: くさ | D13: Plante | E13: Pflanze | F13: Planta | G13: Erba | H13: 풀 | I13: 草 | J13: =I13 | K13: =F13
A14: =CONCATENATE("NAME_TYPE_", UPPER(B14)) | B14: Electric | C14: でんき | D14: Électrik | E14: Elektro | F14: Eléctrico | G14: Elettro | H14: 전기 | I14: =IFERROR(__xludf.DUMMYFUNCTION("GOOGLETRANSLATE(J14,""zh_HANS"",""zh_HANT"")"),"電") | J14: 电 | K14: =F14
A15: =CONCATENATE("NAME_TYPE_", UPPER(B15)) | B15: Psychic | C15: エスパー | D15: Psy | E15: Psyscho | F15: Psíquico | G15: Psico | H15: 에스퍼 | I15: =J15 | J15: 超能力 | K15: =F15
A16: =CONCATENATE("NAME_TYPE_", UPPER(B16)) | B16: Ice | C16: こおり | D16: Glace | E16: Eis | F16: Hielo | G16: Ghiaccio | H16: 얼음 | I16: =J16 | J16: 冰 | K16: =F16
A17: =CONCATENATE("NAME_TYPE_", UPPER(B17)) | B17: Dragon | C17: ドラゴン | D17: =B17 | E17: Drache | F17: Dragón | G17: Drago | H17: 드개곤 | I17: =IFERROR(__xludf.DUMMYFUNCTION("GOOGLETRANSLATE(J17,""zh_HANS"",""zh_HANT"")"),"龍") | J17: 龙 | K17: =F17
A18: =CONCATENATE("NAME_TYPE_", UPPER(B18)) | B18: Dark | C18: あく | D18: Ténèbres | E18: Unlicht | F18: Siniestro | G18: Buio | H18: 악 | I18: =IFERROR(__xludf.DUMMYFUNCTION("GOOGLETRANSLATE(J18,""zh_HANS"",""zh_HANT"")"),"惡") | J18: 恶 | K18: =F18
A19: =CONCATENATE("NAME_TYPE_", UPPER(B19)) | B19: Fairy | C19: フェアリ | D19: Fée | E19: Fee | F19: Hada | G19: Folletto | H19: 페어리 | I19: =J19 | J19: 妖精 | K19: =F19
A20: =CONCATENATE("NAME_TYPE_", UPPER(B20)) | B20: Stellar | C20: ステラ | D20: Stellaire | E20: =B20 | F20: Astral | G20: =CONCATENATE(F20,"e") | H20: 스텔라 | I20: 星晶 | J20: =I20 | K20: =F20

Sheet Moves
A1: =Pokemon!A1 | B1: =Pokemon!B1 | C1: =Pokemon!C1 | D1: =Pokemon!D1 | E1: =Pokemon!E1 | F1: =Pokemon!F1 | G1: =Pokemon!G1 | H1: =Pokemon!H1 | ... K1: =Pokemon!K1
A2: =CONCATENATE("NAME_MOVE_", SUBSTITUTE(UPPER(B2), " ", "")) | B2: Pound | C2: はたく | D2: Écras'Face | E2: Klaps | F2: Destructor | G2: Botta | H2: 막치기 | I2: 拍擊 | J2: =IFERROR(__xludf.DUMMYFUNCTION("GOOGLETRANSLATE(I2,""zh_HANT"",""zh_HANS"")"),"拍击") | K2: =F2
A3: =CONCATENATE("NAME_MOVE_", SUBSTITUTE(UPPER(B3), " ", "")) | B3: Karate Chop | C3: からてチョップ | D3: Poing Karaté | E3: Karateschlag | F3: Golpe Kárate | G3: Colpo Karate | H3: 태권당수 | I3: 空手劈 | J3: =I3 | K3: =F3
A4: =CONCATENATE("NAME_MOVE_", SUBSTITUTE(UPPER(B4), " ", "")) | B4: Double Slap | C4: おうふくビンタ | D4: Torgnoles | E4: Duplexhieb | F4: Doble Bofetón | G4: Doppiasberla | H4: 연속뺨치기 | I4: 連環巴掌 | J4: =IFERROR(__xludf.DUMMYFUNCTION("GOOGLETRANSLATE(I4,""zh_HANT"",""zh_HANS"")"),"连环巴掌") | K4: =F4
A5: =CONCATENATE("NAME_MOVE_", SUBSTITUTE(UPPER(B5), " ", "")) | B5: Comet Punch | C5: れんぞくパンチ | D5: Poing Comète | E5: Kometenhieb | F5: Puño Cometa | G5: Cometapugno | H5: 연속펀치 | I5: 連續拳 | J5: =IFERROR(__xludf.DUMMYFUNCTION("GOOGLETRANSLATE(I5,""zh_HANT"",""zh_HANS"")"),"连续拳") | K5: =F5
A6: =CONCATENATE("NAME_MOVE_", SUBSTITUTE(UPPER(B6), " ", "")) | B6: Mega Punch | C6: メガトンパンチ | D6: Ultimapoing | E6: Megahieb | F6: Megapuño | G6: Megapugno | H6: 메가톤펀치 | I6: 百萬噸重拳 | J6: =IFERROR(__xludf.DUMMYFUNCTION("GOOGLETRANSLATE(I6,""zh_HANT"",""zh_HANS"")"),"百万吨重拳") | K6: =F6
A7: =CONCATENATE("NAME_MOVE_", SUBSTITUTE(UPPER(B7), " ", "")) | B7: Pay Day | C7: ネコにこばん | D7: Jackpot | E7: Zahltag | F7: Día de Pago | G7: Giornopaga | H7: 고양이돈받기 | I7: 聚寶功 | J7: =IFERROR(__xludf.DUMMYFUNCTION("GOOGLETRANSLATE(I7,""zh_HANT"",""zh_HANS"")"),"聚宝功") | K7: =F7
A8: =CONCATENATE("NAME_MOVE_", SUBSTITUTE(UPPER(B8), " ", "")) | B8: Fire Punch | C8: ほのおのパンチ | D8: Poing Feu | E8: Feuerschlag | F8: Puño Fuego | G8: Fuocopugno | H8: 불꽃펀치 | I8: 火焰拳 | J8: =I8 | K8: =F8
A9: =CONCATENATE("NAME_MOVE_", SUBSTITUTE(UPPER(B9), " ", "")) | B9: Ice Punch | C9: らいとうパンチ | D9: Poing Glace | E9: Eishieb | F9: Puño Hielo | G9: Gelopugno | H9: 냉동펀치 | I9: 冰凍拳 | J9: =IFERROR(__xludf.DUMMYFUNCTION("GOOGLETRANSLATE(I9,""zh_HANT"",""zh_HANS"")"),"冰冻拳") | K9: =F9
A10: =CONCATENATE("NAME_MOVE_", SUBSTITUTE(UPPER(B10), " ", "")) | B10: Thunder Punch | C10: かみなりパンチ | D10: Poing Éclair | E10: Donnerschlag | F10: Puño Trueno | G10: Tuonopugno | H10: 번개펀치 | I10: 雷電拳 | J10: =IFERROR(__xludf.DUMMYFUNCTION("GOOGLETRANSLATE(I10,""zh_HANT"",""zh_HANS"")"),"雷电拳") | K10: =F10
A11: =CONCATENATE("NAME_MOVE_", SUBSTITUTE(UPPER(B11), " ", "")) | B11: Scratch | C11: ひっかく | D11: Griffe | E11: Kratzer | F11: Arañazo | G11: Graffio | H11: 할퀴기 | I11: 抓 | J11: =I11 | K11: =F11
A12: =CONCATENATE("NAME_MOVE_", SUBSTITUTE(UPPER(B12), " ", "")) | B12: Vise Grip | C12: はさむ | D12: Force Poigne | E12: Klammer | F12: Agarre | G12: Presa | H12: 찝기 | I12: 夾住 | J12: =IFERROR(__xludf.DUMMYFUNCTION("GOOGLETRANSLATE(I12,""zh_HANT"",""zh_HANS"")"),"夹住") | K12: =F12
A13: =CONCATENATE("NAME_MOVE_", SUBSTITUTE(UPPER(B13), " ", "")) | B13: Guillotine | C13: はさみギロチン | D13: =B13 | E13: =B13 | F13: Guillotina | G13: Ghigliottina | H13: 가위자르기 | I13: 斷頭鉗 | J13: 极落钳 | K13: =F13
A14: =CONCATENATE("NAME_MOVE_", SUBSTITUTE(UPPER(B14), " ", "")) | B14: Razor Wind | C14: かまいたち | D14: Coupe-Vent | E14: Klingensturm | F14: Viento Cortante | G14: Ventagliente | H14: 칼바람 | I14: 旋風刀 | J14: =IFERROR(__xludf.DUMMYFUNCTION("GOOGLETRANSLATE(I14,""zh_HANT"",""zh_HANS"")"),"旋风刀") | K14: =F14
A15: =CONCATENATE("NAME_MOVE_", SUBSTITUTE(UPPER(B15), " ", "")) | B15: Swords Dance | C15: つるぎのまい | D15: Danse-Lames | E15: Schwerttanz | F15: Danza Espada | G15: =SUBSTITUTE(F15," E","") | H15: 칼춤 | I15: 劍舞 | J15: =IFERROR(__xludf.DUMMYFUNCTION("GOOGLETRANSLATE(I15,""zh_HANT"",""zh_HANS"")"),"剑舞") | K15: =F15
A16: =CONCATENATE("NAME_MOVE_", SUBSTITUTE(UPPER(B16), " ", "")) | B16: Cut | C16: いあいぎり | D16: Coupe | E16: Zerschneider | F16: Corte | G16: Taglio | H16: 풀베기 | I16: 居合斬 | J16: 居合劈 | K16: =F16
A17: =CONCATENATE("NAME_MOVE_", SUBSTITUTE(UPPER(B17), " ", "")) | B17: Gust | C17: かざおこし | D17: Tornade | E17: Windstoß | F17: Tornado | G17: Raffica | H17: 바람일으키기 | I17: 起風 | J17: =IFERROR(__xludf.DUMMYFUNCTION("GOOGLETRANSLATE(I17,""zh_HANT"",""zh_HANS"")"),"起风") | K17: =F17
A18: =CONCATENATE("NAME_MOVE_", SUBSTITUTE(UPPER(B18), " ", "")) | B18: Wing Attack | C18: つばさでうつ | D18: Cru-Ailes | E18: Flügelschlag | F18: Ataque Ala | G18: Attacco d'Ala | H18: 날개치기 | I18: 翅膀攻擊 | J18: =IFERROR(__xludf.DUMMYFUNCTION("GOOGLETRANSLATE(I18,""zh_HANT"",""zh_HANS"")"),"翅膀攻击") | K18: =F18
A19: =CONCATENATE("NAME_MOVE_", SUBSTITUTE(UPPER(B19), " ", "")) | B19: Whirlwind | C19: ふきとばし | D19: Cyclone | E19: Wirbelwind | F19: Remolino | G19: Turbine | H19: 날려버리기 | I19: 吹飛 | J19: =IFERROR(__xludf.DUMMYFUNCTION("GOOGLETRANSLATE(I19,""zh_HANT"",""zh_HANS"")"),"吹飞") | K19: =F19
A20: =CONCATENATE("NAME_MOVE_", SUBSTITUTE(UPPER(B20), " ", "")) | B20: Fly | C20: そらをとぶ | D20: Vol | E20: Fliegen | F20: Vuelo | G20: Volo | H20: 공중날기 | I20: 飛翔 | J20: =IFERROR(__xludf.DUMMYFUNCTION("GOOGLETRANSLATE(I20,""zh_HANT"",""zh_HANS"")"),"飞翔") | K20: =F20
A21: =CONCATENATE("NAME_MOVE_", SUBSTITUTE(UPPER(B21), " ", "")) | B21: Bind | C21: しみつける | D21: Étreinte | E21: Klammergriff | F21: Atadura | G21: Legatutto | H21: 조이기 | I21: 綁緊 | J21: =IFERROR(__xludf.DUMMYFUNCTION("GOOGLETRANSLATE(I21,""zh_HANT"",""zh_HANS"")"),"绑紧") | K21: =F21
A22: =CONCATENATE("NAME_MOVE_", SUBSTITUTE(UPPER(B22), " ", "")) | B22: Slam | C22: たたけつける | D22: Souplesse | E22: =B22 | F22: Atizar | G22: Schianto | H22: 힘껏치기 | I22: 摔打 | J22: =I22 | K22: =F22
A23: =CONCATENATE("NAME_MOVE_", SUBSTITUTE(UPPER(B23), " ", "")) | B23: Vine Whip | C23: つるのむち | D23: Fouet Lianes | E23: Rankenhieb | F23: Látigo Cepa | G23: Frustata | H23: 덩굴채찍 | I23: 藤鞭 | J23: =I23 | K23: =F23
A24: =CONCATENATE("NAME_MOVE_", SUBSTITUTE(UPPER(B24), " ", "")) | B24: Stomp | C24: ふみつけ | D24: Écrasement | E24: Stampfer | F24: Pisotón | G24: Pestone | H24: 짓밟기 | I24: 藤鞭 | J24: =I24 | K24: =F24
A25: =CONCATENATE("NAME_MOVE_", SUBSTITUTE(UPPER(B25), " ", "")) | B25: Double Kick | C25: にどげり | D25: Double Pied | E25: Doppelkick | F25: Doble Patada | G25: Doppiocalcio | H25: 두번치기 | I25: 二連踢 | J25: =IFERROR(__xludf.DUMMYFUNCTION("GOOGLETRANSLATE(I25,""zh_HANT"",""zh_HANS"")"),"二连踢") | K25: =F25
A26: =CONCATENATE("NAME_MOVE_", SUBSTITUTE(UPPER(B26), " ", "")) | B26: Mega Kick | C26: メガトンキック | D26: Ultimawashi | E26: Megakick | F26: Megapatada | G26: Megacalcio | H26: 메가톤킥 | I26: 百萬噸重踢 | J26: =IFERROR(__xludf.DUMMYFUNCTION("GOOGLETRANSLATE(I26,""zh_HANT"",""zh_HANS"")"),"百万吨重踢") | K26: =F26
A27: =CONCATENATE("NAME_MOVE_", SUBSTITUTE(UPPER(B27), " ", "")) | B27: Jump Kick | C27: とびげり | D27: Pied Sauté | E27: Sprungkick | F27: Patada Salto | G27: Calciosalto | H27: 점프킥 | I27: 飛踢 | J27: =IFERROR(__xludf.DUMMYFUNCTION("GOOGLETRANSLATE(I27,""zh_HANT"",""zh_HANS"")"),"飞踢") | K27: =F27
A28: =CONCATENATE("NAME_MOVE_", SUBSTITUTE(UPPER(B28), " ", "")) | B28: Rolling Kick | C28: まわしげり | D28: Mawashi Geri | E28: Fegekick | F28: Patada Giro | G28: Calciorullo | H28: 돌려차기 | I28: 迴旋踢 | J28: =IFERROR(__xludf.DUMMYFUNCTION("GOOGLETRANSLATE(I28,""zh_HANT"",""zh_HANS"")"),"回旋踢") | K28: =F28
A29: =CONCATENATE("NAME_MOVE_", SUBSTITUTE(UPPER(B29), " ", "")) | B29: Sand Attack | C29: すなかけ | D29: Jet de Sable | E29: Sandwirbel | F29: Ataque Arena | G29: Turbosabbia | H29: 모래뿌리기 | I29: 潑沙 | J29: =IFERROR(__xludf.DUMMYFUNCTION("GOOGLETRANSLATE(I29,""zh_HANT"",""zh_HANS"")"),"泼沙") | K29: =F29
A30: =CONCATENATE("NAME_MOVE_", SUBSTITUTE(UPPER(B30), " ", "")) | B30: Headbutt | C30: ずつき | D30: Coup d'Boule | E30: Kopfnuss | F30: Golpe Cabeza | G30: Bottintesta | H30: 박치기 | I30: 頭錘 | J30: =IFERROR(__xludf.DUMMYFUNCTION("GOOGLETRANSLATE(I30,""zh_HANT"",""zh_HANS"")"),"头锤") | K30: =F30
A31: =CONCATENATE("NAME_MOVE_", SUBSTITUTE(UPPER(B31), " ", "")) | B31: Horn Attack | C31: つのでつく | D31: Koud'Korne | E31: Hornattacke | F31: Cornada | G31: Incornata | H31: 뿔찌르기 | I31: 角撞 | J31: =I31 | K31: =F31
A32: =CONCATENATE("NAME_MOVE_", SUBSTITUTE(UPPER(B32), " ", "")) | B32: Fury Attack | C32: みだれづき | D32: Furie | E32: Furienschlag | F32: Ataque Furia | G32: Furia | H32: 마구찌르기 | I32: 亂擊 | J32: =IFERROR(__xludf.DUMMYFUNCTION("GOOGLETRANSLATE(I32,""zh_HANT"",""zh_HANS"")"),"乱击") | K32: =F32
A33: =CONCATENATE("NAME_MOVE_", SUBSTITUTE(UPPER(B33), " ", "")) | B33: Horn Drill | C33: つのドリル | D33: Empal'Korne | E33: Hornbohrer | F33: Perforador | G33: Perforcorno | H33: 뿔드릴 | I33: 角鑽 | J33: =IFERROR(__xludf.DUMMYFUNCTION("GOOGLETRANSLATE(I33,""zh_HANT"",""zh_HANS"")"),"角钻") | K33: =F33
A34: =CONCATENATE("NAME_MOVE_", SUBSTITUTE(UPPER(B34), " ", "")) | B34: Tackle | C34: たいあたり | D34: Charge | E34: =B34 | F34: Placaje | G34: Azione | H34: 몸통박치기 | I34: 撞擊 | J34: =IFERROR(__xludf.DUMMYFUNCTION("GOOGLETRANSLATE(I34,""zh_HANT"",""zh_HANS"")"),"撞击") | K34: =F34
A35: =CONCATENATE("NAME_MOVE_", SUBSTITUTE(UPPER(B35), " ", "")) | B35: Body Slam | C35: のしかかり | D35: Plaquage | E35: Bodyslam | F35: Golpe Cuerpo | G35: Corposcontro | H35: 누르기 | I35: 泰山壓頂 | J35: =IFERROR(__xludf.DUMMYFUNCTION("GOOGLETRANSLATE(I35,""zh_HANT"",""zh_HANS"")"),"泰山压顶") | K35: =F35
A36: =CONCATENATE("NAME_MOVE_", SUBSTITUTE(UPPER(B36), " ", "")) | B36: Wrap | C36: まきつく | D36: Ligotage | E36: Wickel | F36: Constricción | G36: Avvolgibotta | H36: 김밥말이 | I36: 緊束 | J36: =IFERROR(__xludf.DUMMYFUNCTION("GOOGLETRANSLATE(I36,""zh_HANT"",""zh_HANS"")"),"紧束") | K36: =F36
A37: =CONCATENATE("NAME_MOVE_", SUBSTITUTE(UPPER(B37), " ", "")) | B37: Take Down | C37: とっしん | D37: Bélier | E37: Bodycheck | F37: Derribo | G37: Riduttore | H37: 돌진 | I37: 猛撞 | J37: =I37 | K37: =F37
A38: =CONCATENATE("NAME_MOVE_", SUBSTITUTE(UPPER(B38), " ", "")) | B38: Thrash | C38: あばれる | D38: Mania | E38: Fuchtler | F38: Golpe | G38: Colpo | H38: 난동부리기 | I38: 大鬧一番 | J38: =IFERROR(__xludf.DUMMYFUNCTION("GOOGLETRANSLATE(I38,""zh_HANT"",""zh_HANS"")"),"大闹一番") | K38: =F38
A39: =CONCATENATE("NAME_MOVE_", SUBSTITUTE(SUBSTITUTE(UPPER(B39), " ", ""), "-", "")) | B39: Double-Edge | C39: すてみッタク | D39: Damoclès | E39: Risikotackle | F39: Doble Filo | G39: Sdoppiatore | H39: 이판사판태클 | I39: 捨身衝撞 | J39: =IFERROR(__xludf.DUMMYFUNCTION("GOOGLETRANSLATE(I39,""zh_HANT"",""zh_HANS"")"),"舍身冲撞") | K39: =F39
A40: =CONCATENATE("NAME_MOVE_", SUBSTITUTE(SUBSTITUTE(UPPER(B40), " ", ""), "-", "")) | B40: Tail Whip | C40: しっぽをふる | D40: Mimi-Queue | E40: Rutenschlag | F40: Látigo | G40: Colpocoda | H40: 꼬리흔들기 | I40: 搖尾巴 | J40: =IFERROR(__xludf.DUMMYFUNCTION("GOOGLETRANSLATE(I40,""zh_HANT"",""zh_HANS"")"),"摇尾巴") | K40: =F40
A41: =CONCATENATE("NAME_MOVE_", SUBSTITUTE(SUBSTITUTE(UPPER(B41), " ", ""), "-", "")) | B41: Poison Sting | C41: どくばり | D41: Dard-Venin | E41: Giftstachel | F41: Picotazo Ven | G41: Velenospina | H41: 독침 | I41: 毒針 | J41: =IFERROR(__xludf.DUMMYFUNCTION("GOOGLETRANSLATE(I41,""zh_HANT"",""zh_HANS"")"),"毒针") | K41: =F41
A42: =CONCATENATE("NAME_MOVE_", SUBSTITUTE(SUBSTITUTE(UPPER(B42), " ", ""), "-", "")) | B42: Twineedle | C42: ダブルニードル | D42: Double Dard | E42: Duonadel | F42: Doble Ataque | G42: Doppio Ago | H42: 더블니들 | I42: 雙針 | J42: =IFERROR(__xludf.DUMMYFUNCTION("GOOGLETRANSLATE(I42,""zh_HANT"",""zh_HANS"")"),"双针") | K42: =F42
A43: =CONCATENATE("NAME_MOVE_", SUBSTITUTE(SUBSTITUTE(UPPER(B43), " ", ""), "-", "")) | B43: Pin Missle | C43: ミサイルばり | D43: Dard-Nuée | E43: Nadelrakete | F43: Pin Misil | G43: Missilspillo | H43: 바늘미사일 | I43: 飛彈針 | J43: =IFERROR(__xludf.DUMMYFUNCTION("GOOGLETRANSLATE(I43,""zh_HANT"",""zh_HANS"")"),"飞弹针") | K43: =F43
A44: =CONCATENATE("NAME_MOVE_", SUBSTITUTE(SUBSTITUTE(UPPER(B44), " ", ""), "-", "")) | B44: Leer | C44: にらみつける | D44: Groz'Yeux | E44: Silberblick | F44: Malicioso | G44: Fulmisguardo | H44: 째려보기 | I44: 瞪眼 | J44: =I44 | K44: =F44
A45: =CONCATENATE("NAME_MOVE_", SUBSTITUTE(SUBSTITUTE(UPPER(B45), " ", ""), "-", "")) | B45: Bite | C45: かみつく | D45: Morsure | E45: Biss | F45: Mordisco | G45: Morso | H45: 물기 | I45: 咬住 | J45: =I45 | K45: =F45
A46: =CONCATENATE("NAME_MOVE_", SUBSTITUTE(SUBSTITUTE(UPPER(B46), " ", ""), "-", "")) | B46: Growl | C46: なきごえ | D46: Rugissement | E46: Heuler | F46: Gruñido | G46: Ruggito | H46: 울음소리 | I46: 叫聲 | J46: =IFERROR(__xludf.DUMMYFUNCTION("GOOGLETRANSLATE(I46,""zh_HANT"",""zh_HANS"")"),"叫声") | K46: =F46
A47: =CONCATENATE("NAME_MOVE_", SUBSTITUTE(SUBSTITUTE(UPPER(B47), " ", ""), "-", "")) | B47: Roar | C47: ほえる | D47: Hurlement | E47: Brüller | F47: Rugido | G47: Boato | H47: 울부짖기 | I47: 吼叫 | J47: =I47 | K47: =F47
A48: =CONCATENATE("NAME_MOVE_", SUBSTITUTE(SUBSTITUTE(UPPER(B48), " ", ""), "-", "")) | B48: Sing | C48: うたう | D48: Berceuse | E48: Gesang | F48: Canto | G48: =F48 | H48: 노래하기 | I48: 唱歌 | J48: =I48 | K48: =F48
A49: =CONCATENATE("NAME_MOVE_", SUBSTITUTE(SUBSTITUTE(UPPER(B49), " ", ""), "-", "")) | B49: Supersonic | C49: ちょうおんぱ | D49: Ultrason | E49: Superschall | F49: Supersónico | G49: Supersuono | H49: 초음파 | I49: 超音波 | J49: =I49 | K49: =F49
A50: =CONCATENATE("NAME_MOVE_", SUBSTITUTE(SUBSTITUTE(UPPER(B50), " ", ""), "-", "")) | B50: Sonic Boom | C50: ソニックブーム | D50: =B50 | E50: Ultraschall | F50: Bomba Sónica | G50: Sonicboom | H50: 소닉붐 | I50: 音爆 | J50: =I50 | K50: =F50
A51: =CONCATENATE("NAME_MOVE_", SUBSTITUTE(SUBSTITUTE(UPPER(B51), " ", ""), "-", "")) | B51: Disable | C51: かなしばり | D51: Entrave | E51: Aussetzer | F51: Anulación | G51: Inibitore | H51: 사슬묶기 | I51: 定身法 | J51: =I51 | K51: =F51
A52: =CONCATENATE("NAME_MOVE_", SUBSTITUTE(SUBSTITUTE(UPPER(B52), " ", ""), "-", "")) | B52: Acid | C52: ようかいえき | D52: Acide | E52: Säure | F52: Ácido | G52: =CONCATENATE(B52,"o") | H52: 용해액 | I52: 溶解液 | J52: =I52 | K52: =F52
A53: =CONCATENATE("NAME_MOVE_", SUBSTITUTE(SUBSTITUTE(UPPER(B53), " ", ""), "-", "")) | B53: Ember | C53: ほのこ | D53: Flammèche | E53: Glut | F53: Ascuas | G53: Braciere | H53: 불꽃세례 | I53: =J53 | J53: 火花 | K53: =F53
A54: =CONCATENATE("NAME_MOVE_", SUBSTITUTE(SUBSTITUTE(UPPER(B54), " ", ""), "-", "")) | B54: Flamethrower | C54: かえんほうしゃ | D54: Lance-Flamme | E54: Flammenwurf | F54: Lanzallamas | G54: Lanciafiamme | H54: 화염방사 | I54: 噴射火焰 | J54: =IFERROR(__xludf.DUMMYFUNCTION("GOOGLETRANSLATE(I54,""zh_HANT"",""zh_HANS"")"),"喷射火焰") | K54: =F54
A55: =CONCATENATE("NAME_MOVE_", SUBSTITUTE(SUBSTITUTE(UPPER(B55), " ", ""), "-", "")) | B55: Mist | C55: しろいきり | D55: Brume | E55: Weißnebel | F55: Neblina | G55: Nebbia | H55: 흰안개 | I55: 白霧 | J55: =IFERROR(__xludf.DUMMYFUNCTION("GOOGLETRANSLATE(I55,""zh_HANT"",""zh_HANS"")"),"白雾") | K55: =F55
A56: =CONCATENATE("NAME_MOVE_", SUBSTITUTE(SUBSTITUTE(UPPER(B56), " ", ""), "-", "")) | B56: Water Gun | C56: みずでっぽう | D56: Pistolet à O | E56: Aquaknarre | F56: Pistola Agua | G56: Pistolacqua | H56: 물대포 | I56: 水槍 | J56: =IFERROR(__xludf.DUMMYFUNCTION("GOOGLETRANSLATE(I56,""zh_HANT"",""zh_HANS"")"),"水枪") | K56: =F56
A57: =CONCATENATE("NAME_MOVE_", SUBSTITUTE(SUBSTITUTE(UPPER(B57), " ", ""), "-", "")) | B57: Hydro Pump | C57: ハイドロポンプ | D57: Hydrocanon | E57: Hydropumpe | F57: Hidrobomba | G57: Idropompa | H57: 하이드로펌프 | I57: 水炮 | J57: =I57 | K57: =F57
A58: =CONCATENATE("NAME_MOVE_", SUBSTITUTE(SUBSTITUTE(UPPER(B58), " ", ""), "-", "")) | B58: Surf | C58: なみのり | D58: =B58 | E58: =CONCATENATE(B58,"er") | F58: =B58 | G58: =B58 | H58: 파도타기 | I58: 衝浪 | J58: =IFERROR(__xludf.DUMMYFUNCTION("GOOGLETRANSLATE(I58,""zh_HANT"",""zh_HANS"")"),"冲浪") | K58: =F58
A59: =CONCATENATE("NAME_MOVE_", SUBSTITUTE(SUBSTITUTE(UPPER(B59), " ", ""), "-", "")) | B59: Ice Beam | C59: れいとうビーム | D59: Laser Glace | E59: Eisstrahl | F59: Rayo Hielo | G59: Geloraggio | H59: 냉동빔 | I59: 冰凍光束 | J59: =IFERROR(__xludf.DUMMYFUNCTION("GOOGLETRANSLATE(I59,""zh_HANT"",""zh_HANS"")"),"冰冻光束") | K59: =F59
A60: =CONCATENATE("NAME_MOVE_", SUBSTITUTE(SUBSTITUTE(UPPER(B60), " ", ""), "-", "")) | B60: Blizzard | C60: ふぶき | D60: =B60 | E60: =B60 | F60: Ventisca | G60: Bora | H60: 눈보라 | I60: 暴風雪 | J60: =IFERROR(__xludf.DUMMYFUNCTION("GOOGLETRANSLATE(I60,""zh_HANT"",""zh_HANS"")"),"暴风雪") | K60: =F60
A61: =CONCATENATE("NAME_MOVE_", SUBSTITUTE(SUBSTITUTE(UPPER(B61), " ", ""), "-", "")) | B61: Psybeam | C61: サイケこうせん | D61: Rafale Psy | E61: Psystrahl | F61: Psicorrayo | G61: Psicoraggio | H61: 환상빔 | I61: 幻象光線 | J61: =IFERROR(__xludf.DUMMYFUNCTION("GOOGLETRANSLATE(I61,""zh_HANT"",""zh_HANS"")"),"幻象光线") | K61: =F61
A62: =CONCATENATE("NAME_MOVE_", SUBSTITUTE(SUBSTITUTE(UPPER(B62), " ", ""), "-", "")) | B62: Bubble Beam | C62: バボルこうせん | D62: Bulles d'O | E62: Blubbstrahl | F62: Rayo Burbuja | G62: Bollaraggio | H62: 거품광선 | I62: 泡沫光線 | J62: =IFERROR(__xludf.DUMMYFUNCTION("GOOGLETRANSLATE(I62,""zh_HANT"",""zh_HANS"")"),"泡沫光线") | K62: =F62
A63: =CONCATENATE("NAME_MOVE_", SUBSTITUTE(SUBSTITUTE(UPPER(B63), " ", ""), "-", "")) | B63: Aurora Beam | C63: オーロラビーム | D63: Onde Boréale | E63: Aurorastrahl | F63: Rayo Aurora | G63: Raggiaurora | H63: 오로라빔 | I63: 極光束 | J63: =IFERROR(__xludf.DUMMYFUNCTION("GOOGLETRANSLATE(I63,""zh_HANT"",""zh_HANS"")"),"极光束") | K63: =F63
A64: =CONCATENATE("NAME_MOVE_", SUBSTITUTE(SUBSTITUTE(UPPER(B64), " ", ""), "-", "")) | B64: Hyper Beam | C64: はかいこうせん | D64: Ultra Laser | E64: Hyperstrahl | F64: Hiperrayo | G64: Iper Raggio | H64: 파괴광선 | I64: 破壞光線 | J64: =IFERROR(__xludf.DUMMYFUNCTION("GOOGLETRANSLATE(I64,""zh_HANT"",""zh_HANS"")"),"破坏光线") | K64: =F64
A65: =CONCATENATE("NAME_MOVE_", SUBSTITUTE(SUBSTITUTE(UPPER(B65), " ", ""), "-", "")) | B65: Peck | C65: つつく | D65: Picpic | E65: Pikser | F65: Picotazo | G65: Beccata | H65: 쪼기 | I65: 啄 | J65: =I65 | K65: =F65
A66: =CONCATENATE("NAME_MOVE_", SUBSTITUTE(SUBSTITUTE(UPPER(B66), " ", ""), "-", "")) | B66: Drill Peck | C66: ドリルくちばし | D66: Bec Vrille | E66: Bohrschnabel | F66: Pico Taladro | G66: Perforbecco | H66: 회전부리 | I66: 啄鑽 | J66: =IFERROR(__xludf.DUMMYFUNCTION("GOOGLETRANSLATE(I66,""zh_HANT"",""zh_HANS"")"),"啄钻") | K66: =F66
A67: =CONCATENATE("NAME_MOVE_", SUBSTITUTE(SUBSTITUTE(UPPER(B67), " ", ""), "-", "")) | B67: Submission | C67: じごくぐるま | D67: Sacrifice | E67: Überroller | F67: Sumisión | G67: Sottomissione | H67: 지옥의바퀴 | I67: 地獄翻滾 | J67: 深渊翻滚 | K67: =F67
A68: =CONCATENATE("NAME_MOVE_", SUBSTITUTE(SUBSTITUTE(UPPER(B68), " ", ""), "-", "")) | B68: Low Kick | C68: けたぐり | D68: Balayage | E68: Fußkick | F68: Patada Baja | G68: Colpo Basso | H68: 안다리걸기 | I68: 踢倒 | J68: =I68 | K68: =F68
A69: =CONCATENATE("NAME_MOVE_", SUBSTITUTE(SUBSTITUTE(UPPER(B69), " ", ""), "-", "")) | B69: Counter | C69: カウンター | D69: Riposte | E69: Konter | F69: Contraataque | G69: Contrattacco | H69: 카운터 | I69: 雙倍奉還 | J69: =IFERROR(__xludf.DUMMYFUNCTION("GOOGLETRANSLATE(I69,""zh_HANT"",""zh_HANS"")"),"双倍奉还") | K69: =F69
A70: =CONCATENATE("NAME_MOVE_", SUBSTITUTE(SUBSTITUTE(UPPER(B70), " ", ""), "-", "")) | B70: Seismic Toss | C70: ちきゅうなげ | D70: Frappe Atlas | E70: Geowurf | F70: Sísmico | G70: Movim. Sismico | H70: 지구던지기 | I70: 地球上投 | J70: =I70 | K70: =F70
A71: =CONCATENATE("NAME_MOVE_", SUBSTITUTE(SUBSTITUTE(UPPER(B71), " ", ""), "-", "")) | B71: Strength | C71: かいりき | D71: Force | E71: Stärke | F71: Fuerza | G71: Forza | H71: 괴력 | I71: 怪力 | J71: =I71 | K71: =F71
A72: =CONCATENATE("NAME_MOVE_", SUBSTITUTE(SUBSTITUTE(UPPER(B72), " ", ""), "-", "")) | B72: Absorb | C72: すいとる | D72: Vole-Vie | E72: =CONCATENATE(B72,"er") | F72: Absorber | G72: Assorbimento | H72: 흡수 | I72: 吸取 | J72: =I72 | K72: =F72
A73: =CONCATENATE("NAME_MOVE_", SUBSTITUTE(SUBSTITUTE(UPPER(B73), " ", ""), "-", "")) | B73: Mega Drain | C73: メガドレイン | D73: Mega-Sangsue | E73: Megasauger | F73: Megaagotar | G73: Megassorbimento | H73: 메가드레인 | I73: 超級吸取 | J73: =IFERROR(__xludf.DUMMYFUNCTION("GOOGLETRANSLATE(I73,""zh_HANT"",""zh_HANS"")"),"超级吸取") | K73: =F73
A74: =CONCATENATE("NAME_MOVE_", SUBSTITUTE(SUBSTITUTE(UPPER(B74), " ", ""), "-", "")) | B74: Leech Seed | C74: やどりぎのタネ | D74: Vampigraine | E74: Egelsamen | F74: Drenadoras | G74: Parassiseme | H74: 씨뿌리기 | I74: 寄生種子 | J74: =IFERROR(__xludf.DUMMYFUNCTION("GOOGLETRANSLATE(I74,""zh_HANT"",""zh_HANS"")"),"寄生种子") | K74: =F74
A75: =CONCATENATE("NAME_MOVE_", SUBSTITUTE(SUBSTITUTE(UPPER(B75), " ", ""), "-", "")) | B75: Growth | C75: せいちょう | D75: Croissance | E75: Wachstum | F75: Desarrollo | G75: Crescita | H75: 성장 | I75: 生長 | J75: =IFERROR(__xludf.DUMMYFUNCTION("GOOGLETRANSLATE(I75,""zh_HANT"",""zh_HANS"")"),"生长") | K75: =F75
A76: =CONCATENATE("NAME_MOVE_", SUBSTITUTE(SUBSTITUTE(UPPER(B76), " ", ""), "-", "")) | B76: Razor Leaf | C76: はっぱカッター | D76: Tranch'Herbe | E76: Rasierblatt | F76: Hoja Afilada | G76: Foglielama | H76: 잎날가르기 | I76: 飛葉快刀 | J76: =IFERROR(__xludf.DUMMYFUNCTION("GOOGLETRANSLATE(I76,""zh_HANT"",""zh_HANS"")"),"飞叶快刀") | K76: =F76
A77: =CONCATENATE("NAME_MOVE_", SUBSTITUTE(SUBSTITUTE(UPPER(B77), " ", ""), "-", "")) | B77: Solar Beam | C77: ソーラービーム | D77: Lance-Soleil | E77: Solarstrahl | F77: Rayo Solar | G77: Solarraggio | H77: 솔라빔 | I77: 日光束 | J77: =I77 | K77: =F77
A78: =CONCATENATE("NAME_MOVE_", SUBSTITUTE(SUBSTITUTE(UPPER(B78), " ", ""), "-", "")) | B78: Poison Powder | C78: どくのこな | D78: Poudre Toxik | E78: Giftpuder | F78: Polvo Veneno | G78: Velenpolvere | H78: 독가루 | I78: 毒粉 | J78: =I78 | K78: =F78
A79: =CONCATENATE("NAME_MOVE_", SUBSTITUTE(SUBSTITUTE(UPPER(B79), " ", ""), "-", "")) | B79: Stun Spore | C79: しびれごな | D79: Para-Spore | E79: Stachelspore | F79: Paralizador | G79: Paralizzante | H79: 저리가루 | I79: 麻痺粉 | J79: =I79 | K79: =F79
A80: =CONCATENATE("NAME_MOVE_", SUBSTITUTE(SUBSTITUTE(UPPER(B80), " ", ""), "-", "")) | B80: Sleep Powder | C80: ねむりごな | D80: Poudre Dodo | E80: Schlafpuder | F80: Somnífero | G80: Sonnifero | H80: 수면가루 | I80: 催眠粉 | J80: =I80 | K80: =F80
A81: =CONCATENATE("NAME_MOVE_", SUBSTITUTE(SUBSTITUTE(UPPER(B81), " ", ""), "-", "")) | B81: Petal Dance | C81: はなびらのまい | D81: Danse-Fleur | E81: Blättertanz | F81: Danza Pétalo | G81: Petalodanza | H81: 꽃잎댄스 | I81: 花瓣舞 | J81: =I81 | K81: =F81
A82: =CONCATENATE("NAME_MOVE_", SUBSTITUTE(SUBSTITUTE(UPPER(B82), " ", ""), "-", "")) | B82: String Shot | C82: いとおはく | D82: Sécrétion | E82: Fadenschuss | F82: Disp. Demora | G82: Millebave | H82: 실뿜기 | I82: 吐絲 | J82: =IFERROR(__xludf.DUMMYFUNCTION("GOOGLETRANSLATE(I82,""zh_HANT"",""zh_HANS"")"),"吐丝") | K82: =F82
A83: =CONCATENATE("NAME_MOVE_", SUBSTITUTE(SUBSTITUTE(UPPER(B83), " ", ""), "-", "")) | B83: Dragon Rage | C83: りゅうのいかり | D83: Draco-Rage | E83: Drachenwut | F83: Furia Dragón | G83: Ira di Drago | H83: 용의분노 | I83: 龍之怒 | J83: =IFERROR(__xludf.DUMMYFUNCTION("GOOGLETRANSLATE(I83,""zh_HANT"",""zh_HANS"")"),"龙之怒") | K83: =F83
A84: =CONCATENATE("NAME_MOVE_", SUBSTITUTE(SUBSTITUTE(UPPER(B84), " ", ""), "-", "")) | B84: Fire Spin | C84: ほのおのうず | D84: Danse Flammes | E84: Feuerwirbel | F84: Giro Fuego | G84: Turbofuoco | H84: 회오리불꽃 | I84: 火焰旋渦 | J84: =IFERROR(__xludf.DUMMYFUNCTION("GOOGLETRANSLATE(I84,""zh_HANT"",""zh_HANS"")"),"火焰旋涡") | K84: =F84
A85: =CONCATENATE("NAME_MOVE_", SUBSTITUTE(SUBSTITUTE(UPPER(B85), " ", ""), "-", "")) | B85: Thunder Shock | C85: でんきショック | D85: Éclair | E85: Donnerschock | F85: Impactrueno | G85: =CONCATENATE(G88,"shock") | H85: 전기쇼크 | I85: 電擊 | J85: =IFERROR(__xludf.DUMMYFUNCTION("GOOGLETRANSLATE(I85,""zh_HANT"",""zh_HANS"")"),"电击") | K85: =F85
A86: =CONCATENATE("NAME_MOVE_", SUBSTITUTE(SUBSTITUTE(UPPER(B86), " ", ""), "-", "")) | B86: Thunderbolt | C86: １０まいボルト | D86: Tonnerre | E86: Donnerblitz | F86: Rayo | G86: Fulmine | H86: １０만볼트 | I86: 十萬伏特 | J86: =IFERROR(__xludf.DUMMYFUNCTION("GOOGLETRANSLATE(I86,""zh_HANT"",""zh_HANS"")"),"十万伏特") | K86: =F86
A87: =CONCATENATE("NAME_MOVE_", SUBSTITUTE(SUBSTITUTE(UPPER(B87), " ", ""), "-", "")) | B87: Thunder Wave | C87: でんじは | D87: Cage-Éclair | E87: Donnerwelle | F87: Onda Trueno | G87: =CONCATENATE(G88,"nda") | H87: 전기자석파 | I87: 電磁波 | J87: =IFERROR(__xludf.DUMMYFUNCTION("GOOGLETRANSLATE(I87,""zh_HANT"",""zh_HANS"")"),"电磁波") | K87: =F87
A88: =CONCATENATE("NAME_MOVE_", SUBSTITUTE(SUBSTITUTE(UPPER(B88), " ", ""), "-", "")) | B88: Thunder | C88: かみなり | D88: Fatal-Foudre | E88: Donner | F88: Trueno | G88: Tuono | H88: 번개 | I88: 打雷 | J88: =IFERROR(__xludf.DUMMYFUNCTION("GOOGLETRANSLATE(I88,""zh_HANT"",""zh_HANS"")"),"打雷") | K88: =F88
A89: =CONCATENATE("NAME_MOVE_", SUBSTITUTE(SUBSTITUTE(UPPER(B89), " ", ""), "-", "")) | B89: Rock Throw | C89: いわおとし | D89: Jet-Pierre | E89: Steinwurf | F89: Lanzarrocas | G89: Sassata | H89: 돌떨구기 | I89: 落石 | J89: =IFERROR(__xludf.DUMMYFUNCTION("GOOGLETRANSLATE(I89,""zh_HANT"",""zh_HANS"")"),"落石") | K89: =F89
A90: =CONCATENATE("NAME_MOVE_", SUBSTITUTE(SUBSTITUTE(UPPER(B90), " ", ""), "-", "")) | B90: Earthquake | C90: じしん | D90: Séisme | E90: Erdbeben | F90: Terremoto | G90: =F90 | H90: 지진 | I90: 地震 | J90: =IFERROR(__xludf.DUMMYFUNCTION("GOOGLETRANSLATE(I90,""zh_HANT"",""zh_HANS"")"),"地震") | K90: =F90
A91: =CONCATENATE("NAME_MOVE_", SUBSTITUTE(SUBSTITUTE(UPPER(B91), " ", ""), "-", "")) | B91: Fissure | C91: じわれ | D91: Abîme | E91: Geofissur | F91: Fisura | G91: Abisso | H91: 땅가르기 | I91: 地裂 | J91: =IFERROR(__xludf.DUMMYFUNCTION("GOOGLETRANSLATE(I91,""zh_HANT"",""zh_HANS"")"),"地裂") | K91: =F91
A92: =CONCATENATE("NAME_MOVE_", SUBSTITUTE(SUBSTITUTE(UPPER(B92), " ", ""), "-", "")) | B92: Dig | C92: あなをほる | D92: Tunnel | E92: Schaufler | F92: Excavar | G92: Fossa | H92: 구멍파기 | I92: 挖洞 | J92: =IFERROR(__xludf.DUMMYFUNCTION("GOOGLETRANSLATE(I92,""zh_HANT"",""zh_HANS"")"),"挖洞") | K92: =F92
A93: =CONCATENATE("NAME_MOVE_", SUBSTITUTE(SUBSTITUTE(UPPER(B93), " ", ""), "-", "")) | B93: Toxic | C93: どくどく | D93: Toxik | E93: Toxin | F93: Tóxico | G93: Tossina | H93: 맹독 | I93: 劇毒 | J93: =IFERROR(__xludf.DUMMYFUNCTION("GOOGLETRANSLATE(I93,""zh_HANT"",""zh_HANS"")"),"剧毒") | K93: =F93
A94: =CONCATENATE("NAME_MOVE_", SUBSTITUTE(SUBSTITUTE(UPPER(B94), " ", ""), "-", "")) | B94: Confusion | C94: ねんりき | D94: Choc Mental | E94: Konfusion | F94: Confusión | G94: =CONCATENATE(B94,"e") | H94: 염동력 | I94: 念力 | J94: =I94 | K94: =F94
A95: =CONCATENATE("NAME_MOVE_", SUBSTITUTE(SUBSTITUTE(UPPER(B95), " ", ""), "-", "")) | B95: Psychic | C95: サイコキネシス | D95: Psycho | E95: Psychokinese | F95: Psíquico | G95: Psichico | H95: 사이코키네시스 | I95: 精神強念 | J95: =IFERROR(__xludf.DUMMYFUNCTION("GOOGLETRANSLATE(I95,""zh_HANT"",""zh_HANS"")"),"精神强念") | K95: =F95
A96: =CONCATENATE("NAME_MOVE_", SUBSTITUTE(SUBSTITUTE(UPPER(B96), " ", ""), "-", "")) | B96: Hypnosis | C96: さいみんじゅっつ | D96: Hypnose | E96: =D96 | F96: Hipnosis | G96: Ipnosi | H96: 최면술 | I96: 催眠術 | J96: =IFERROR(__xludf.DUMMYFUNCTION("GOOGLETRANSLATE(I96,""zh_HANT"",""zh_HANS"")"),"催眠术") | K96: =F96
A97: =CONCATENATE("NAME_MOVE_", SUBSTITUTE(SUBSTITUTE(UPPER(B97), " ", ""), "-", "")) | B97: Meditate | C97: ヨガのポース | D97: Yoga | E97: Meditation | F97: Meditación | G97: Meditazione | H97: 요가포즈 | I97: 瑜伽姿勢 | J97: =IFERROR(__xludf.DUMMYFUNCTION("GOOGLETRANSLATE(I97,""zh_HANT"",""zh_HANS"")"),"瑜伽姿势") | K97: =F97
A98: =CONCATENATE("NAME_MOVE_", SUBSTITUTE(SUBSTITUTE(UPPER(B98), " ", ""), "-", "")) | B98: Agility | C98: こうそくいどう | D98: Hâte | E98: Agilität | F98: Agilidad | G98: Agilità | H98: 고속이동 | I98: 高速移動 | J98: =IFERROR(__xludf.DUMMYFUNCTION("GOOGLETRANSLATE(I98,""zh_HANT"",""zh_HANS"")"),"高速移动") | K98: =F98
A99: =CONCATENATE("NAME_MOVE_", SUBSTITUTE(SUBSTITUTE(UPPER(B99), " ", ""), "-", "")) | B99: Quick Attack | C99: でんこうせっか | D99: Vive-Attaque | E99: Ruckzuckhieb | F99: Ataque Rápido | G99: Attacco Rapido | H99: 전광석화 | I99: 電光一閃 | J99: =IFERROR(__xludf.DUMMYFUNCTION("GOOGLETRANSLATE(I99,""zh_HANT"",""zh_HANS"")"),"电光一闪") | K99: =F99
A100: =CONCATENATE("NAME_MOVE_", SUBSTITUTE(SUBSTITUTE(UPPER(B100), " ", ""), "-", "")) | B100: Rage | C100: いかり | D100: Frénésie | E100: Raserei | F100: Furia | G100: Ira | H100: 분노 | I100: 憤怒 | J100: =I100 | K100: =F100
...

Sheet Abilities
A1: =Pokemon!A1 | B1: =Pokemon!B1 | C1: =Pokemon!C1 | D1: =Pokemon!D1 | E1: =Pokemon!E1 | F1: =Pokemon!F1 | G1: =Pokemon!G1 | H1: =Pokemon!H1 | ... K1: =Pokemon!K1
A2: =CONCATENATE("NAME_ABILITY_", SUBSTITUTE(UPPER(B2), " ", "")) | B2: Stench | C2: あくしゅう | D2: Puanteur | E2: Duftnote | F2: Hedor | G2: Tanfo | H2: 악취 | I2: 惡臭 | J2: =IFERROR(__xludf.DUMMYFUNCTION("GOOGLETRANSLATE(I2,""zh_HANT"",""zh_HANS"")"),"恶臭") | K2: =F2
A3: =CONCATENATE("NAME_ABILITY_", SUBSTITUTE(UPPER(B3), " ", "")) | B3: Drizzle | C3: あめふらし | D3: Crachin | E3: Niesel | F3: Llovizna | G3: Piovischio | H3: 잔비 | I3: 降雨 | J3: =I3 | K3: =F3
A4: =CONCATENATE("NAME_ABILITY_", SUBSTITUTE(UPPER(B4), " ", "")) | B4: Speed Boost | C4: かそく | D4: Turbo | E4: Temposchub | F4: Impulso | G4: Acceleratore | H4: 가속 | I4: 加速 | J4: =I4 | K4: =F4
A5: =CONCATENATE("NAME_ABILITY_", SUBSTITUTE(UPPER(B5), " ", "")) | B5: Battle Armor | C5: カブトアーマー | D5: Armurbaston | E5: Kampfpanzer | F5: Armadura Batalla | G5: Lottascudo | H5: 전투 무장 | I5: 戰鬥盔甲 | J5: =IFERROR(__xludf.DUMMYFUNCTION("GOOGLETRANSLATE(I5,""zh_HANT"",""zh_HANS"")"),"战斗盔甲") | K5: =F5
A6: =CONCATENATE("NAME_ABILITY_", SUBSTITUTE(UPPER(B6), " ", "")) | B6: Sturdy | C6: がんじょう | D6: Fermeté | E6: Robustheit | F6: Robustez | G6: Vigore | H6: 옹골참 | I6: 結實 | J6: =IFERROR(__xludf.DUMMYFUNCTION("GOOGLETRANSLATE(I6,""zh_HANT"",""zh_HANS"")"),"结实") | K6: =F6
A7: =CONCATENATE("NAME_ABILITY_", SUBSTITUTE(UPPER(B7), " ", "")) | B7: Damp | C7: しめりけ | D7: Moiteur | E7: Feuchtigkeit | F7: Humedad | G7: Umidità | H7: 습기 | I7: 濕氣 | J7: =IFERROR(__xludf.DUMMYFUNCTION("GOOGLETRANSLATE(I7,""zh_HANT"",""zh_HANS"")"),"湿气") | K7: =F7
A8: =CONCATENATE("NAME_ABILITY_", SUBSTITUTE(UPPER(B8), " ", "")) | B8: Limber | C8: じゅうなん | D8: Échauffement | E8: Flexibilität | F8: Flexibilidad | G8: Scioltezza | H8: 유연 | I8: 柔軟 | J8: =IFERROR(__xludf.DUMMYFUNCTION("GOOGLETRANSLATE(I8,""zh_HANT"",""zh_HANS"")"),"柔软") | K8: =F8
A9: =CONCATENATE("NAME_ABILITY_", SUBSTITUTE(UPPER(B9), " ", "")) | B9: Sand Veil | C9: すながくれ | D9: Voile Sable | E9: Sandschleier | F9: Velo Arena | G9: Sabbiavelo | H9: 모래숨기 | I9: 沙隱 | J9: =IFERROR(__xludf.DUMMYFUNCTION("GOOGLETRANSLATE(I9,""zh_HANT"",""zh_HANS"")"),"沙隐") | K9: =F9
A10: =CONCATENATE("NAME_ABILITY_", SUBSTITUTE(UPPER(B10), " ", "")) | B10: Static | C10: せいでんき | D10: Statik | E10: =D10 | F10: Elec. Estática | G10: =CONCATENATE(B10,"o") | H10: 정전기 | I10: 靜電 | J10: =IFERROR(__xludf.DUMMYFUNCTION("GOOGLETRANSLATE(I10,""zh_HANT"",""zh_HANS"")"),"静电") | K10: =F10
A11: =CONCATENATE("NAME_ABILITY_", SUBSTITUTE(UPPER(B11), " ", "")) | B11: Volt Absorb | C11: ちくでん | D11: Absorbe-Volt | E11: Voltabsorber | F11: Absorbe Elec. | G11: Assorbivolt | H11: 축전 | I11: 蓄電 | J11: =IFERROR(__xludf.DUMMYFUNCTION("GOOGLETRANSLATE(I11,""zh_HANT"",""zh_HANS"")"),"蓄电") | K11: =F11
A12: =CONCATENATE("NAME_ABILITY_", SUBSTITUTE(UPPER(B12), " ", "")) | B12: Water Absorb | C12: ちょすい | D12: Absorbe-Eau | E12: H2O-Absorber | F12: Absorbe Agua | G12: Assorbacqua | H12: 저수 | I12: 儲水 | J12: =IFERROR(__xludf.DUMMYFUNCTION("GOOGLETRANSLATE(I12,""zh_HANT"",""zh_HANS"")"),"储水") | K12: =F12
A13: =CONCATENATE("NAME_ABILITY_", SUBSTITUTE(UPPER(B13), " ", "")) | B13: Oblivious | C13: どんかん | D13: Benêt | E13: Dösigkeit | F13: Despiste | G13: Indifferenza | H13: 둔감 | I13: 遲鈍 | J13: =IFERROR(__xludf.DUMMYFUNCTION("GOOGLETRANSLATE(I13,""zh_HANT"",""zh_HANS"")"),"迟钝") | K13: =F13
A14: =CONCATENATE("NAME_ABILITY_", SUBSTITUTE(UPPER(B14), " ", "")) | B14: Cloud Nine | C14: ノーてんき | D14: Ciel Gris | E14: Wolke Sieben | F14: Aclimatación | G14: Antimeteo | H14: 날씨 부정 | I14: 無關天氣 | J14: =IFERROR(__xludf.DUMMYFUNCTION("GOOGLETRANSLATE(I14,""zh_HANT"",""zh_HANS"")"),"无关天气") | K14: =F14
A15: =CONCATENATE("NAME_ABILITY_", SUBSTITUTE(UPPER(B15), " ", "")) | B15: Compund Eyes | C15: ふくがん | D15: Oeil Composé | E15: Facettenauge | F15: Ojo Compuesto | G15: Insettochi | H15: 복안 | I15: 複眼 | J15: =IFERROR(__xludf.DUMMYFUNCTION("GOOGLETRANSLATE(I15,""zh_HANT"",""zh_HANS"")"),"复眼") | K15: =F15
A16: =CONCATENATE("NAME_ABILITY_", SUBSTITUTE(UPPER(B16), " ", "")) | B16: Insomia | C16: ふみん | D16: =B16 | E16: =B16 | F16: Insomnio | G16: Insonnia | H16: 불면 | I16: 不眠 | J16: =I16 | K16: =F16
A17: =CONCATENATE("NAME_ABILITY_", SUBSTITUTE(UPPER(B17), " ", "")) | B17: Color Change | C17: へんしょく | D17: Homochromie | E17: Farbwechsel | F17: Cambio Color | G17: Cambiacolore | H17: 변색 | I17: 變色 | J17: =IFERROR(__xludf.DUMMYFUNCTION("GOOGLETRANSLATE(I17,""zh_HANT"",""zh_HANS"")"),"变色") | K17: =F17
A18: =CONCATENATE("NAME_ABILITY_", SUBSTITUTE(UPPER(B18), " ", "")) | B18: Immunity | C18: めんえき | D18: Vaccin | E18: Immunität | F18: Inmunidad | G18: Immunità | H18: 면역 | I18: 免疫 | J18: =I18 | K18: =F18
A19: =CONCATENATE("NAME_ABILITY_", SUBSTITUTE(UPPER(B19), " ", "")) | B19: Flash Fire | C19: もらいび | D19: Torche | E19: Feuerfänger | F19: Absorbe Fuego | G19: Fuocardore | H19: 타오르는 불꽃 | I19: 引火 | J19: =I19 | K19: =F19
A20: =CONCATENATE("NAME_ABILITY_", SUBSTITUTE(UPPER(B20), " ", "")) | B20: Shield Dust | C20: りんぷん | D20: Écran Poudre | E20: Puderabwehr | F20: Polvo Escudo | G20: Polvoscudo | H20: 인분 | I20: 鱗粉 | J20: =IFERROR(__xludf.DUMMYFUNCTION("GOOGLETRANSLATE(I20,""zh_HANT"",""zh_HANS"")"),"鳞粉") | K20: =F20
A21: =CONCATENATE("NAME_ABILITY_", SUBSTITUTE(UPPER(B21), " ", "")) | B21: Own Tempo | C21: マイペース | D21: Tempo Perso | E21: Tempomacher | F21: Ritmo Propio | G21: Mente Locale | H21: 마이페이스 | I21: 我行我素 | J21: =I21 | K21: =F21
A22: =CONCATENATE("NAME_ABILITY_", SUBSTITUTE(UPPER(B22), " ", "")) | B22: Suction Cups | C22: きゅうばん | D22: Ventouse | E22: Saugnapf | F22: Ventosas | G22: Ventose | H22: 흡반 | I22: 吸盤 | J22: =IFERROR(__xludf.DUMMYFUNCTION("GOOGLETRANSLATE(I22,""zh_HANT"",""zh_HANS"")"),"吸盘") | K22: =F22
A23: =CONCATENATE("NAME_ABILITY_", SUBSTITUTE(UPPER(B23), " ", "")) | B23: Intimidate | C23: いかく | D23: Intimidation | E23: Bedroher | F23: Intimidación | G23: Prepotenza | H23: 위협 | I23: 威嚇 | J23: =IFERROR(__xludf.DUMMYFUNCTION("GOOGLETRANSLATE(I23,""zh_HANT"",""zh_HANS"")"),"威吓") | K23: =F23
A24: =CONCATENATE("NAME_ABILITY_", SUBSTITUTE(UPPER(B24), " ", "")) | B24: Shadow Tag | C24: かげふみ | D24: Marque Ombre | E24: Wegsperre | F24: Sombra Trampa | G24: Pedinombra | H24: 그림자 밟기 | I24: 踩影 | J24: =I24 | K24: =F24
A25: =CONCATENATE("NAME_ABILITY_", SUBSTITUTE(UPPER(B25), " ", "")) | B25: Rough Skin | C25: さめはだ | D25: Peau Dure | E25: Rauhaut | F25: Piel Tosca | G25: Cartavetro | H25: 까칠한 피부 | I25: 粗糙皮膚 | J25: =IFERROR(__xludf.DUMMYFUNCTION("GOOGLETRANSLATE(I25,""zh_HANT"",""zh_HANS"")"),"粗糙皮肤") | K25: =F25
A26: =CONCATENATE("NAME_ABILITY_", SUBSTITUTE(UPPER(B26), " ", "")) | B26: Wonder Guard | C26: ふしぎなまもり | D26: Garde Mystik | E26: Wunderwache | F26: Superguarda | G26: Magidifesa | H26: 불가사의 부적 | I26: 神奇守護 | J26: =IFERROR(__xludf.DUMMYFUNCTION("GOOGLETRANSLATE(I26,""zh_HANT"",""zh_HANS"")"),"神奇守护") | K26: =F26
A27: =CONCATENATE("NAME_ABILITY_", SUBSTITUTE(UPPER(B27), " ", "")) | B27: Levitate | C27: ふゆう | D27: Lévitation | E27: Schwebe | F27: Levitación | G27: Levitazione | H27: 부유 | I27: 飄浮 | J27: =IFERROR(__xludf.DUMMYFUNCTION("GOOGLETRANSLATE(I27,""zh_HANT"",""zh_HANS"")"),"飘浮") | K27: =F27
A28: =CONCATENATE("NAME_ABILITY_", SUBSTITUTE(UPPER(B28), " ", "")) | B28: Effect Spore | C28: ほうし | D28: Pose Spore | E28: Sporenwirt | F28: Efecto Espora | G28: Spargispora | H28: 포자 | I28: 孢子 | J28: =I28 | K28: =F28
A29: =CONCATENATE("NAME_ABILITY_", SUBSTITUTE(UPPER(B29), " ", "")) | B29: Synchonize | C29: シンクロ | D29: Synchro | E29: =D29 | F29: Sincronía | G29: Sincronismo | H29: 싱크로 | I29: 同步 | J29: =I29 | K29: =F29
A30: =CONCATENATE("NAME_ABILITY_", SUBSTITUTE(UPPER(B30), " ", "")) | B30: Clear Body | C30: クリアボヂィ | D30: Corps Sain | E30: Neutraltorso | F30: Cuerpo Puro | G30: Corpochiaro | H30: 클리어 바디 | I30: 恆淨之軀 | J30: =IFERROR(__xludf.DUMMYFUNCTION("GOOGLETRANSLATE(I30,""zh_HANT"",""zh_HANS"")"),"恒净之躯") | K30: =F30
A31: =CONCATENATE("NAME_ABILITY_", SUBSTITUTE(UPPER(B31), " ", "")) | B31: Natural Cure | C31: しぜんかいふく | D31: Médic Nature | E31: Innere Kraft | F31: Cura Natural | G31: Alternacura | H31: 자연회복 | I31: 自然回復 | J31: =IFERROR(__xludf.DUMMYFUNCTION("GOOGLETRANSLATE(I31,""zh_HANT"",""zh_HANS"")"),"自然回复") | K31: =F31
A32: =CONCATENATE("NAME_ABILITY_", SUBSTITUTE(UPPER(B32), " ", "")) | B32: Lightning Rod | C32: ひらいしん | D32: Paratonnerre | E32: Blitzfänger | F32: Pararrayos | G32: Parafulmine | H32: 피뢰침 | I32: 避雷針 | J32: =IFERROR(__xludf.DUMMYFUNCTION("GOOGLETRANSLATE(I32,""zh_HANT"",""zh_HANS"")"),"避雷针") | K32: =F32
A33: =CONCATENATE("NAME_ABILITY_", SUBSTITUTE(UPPER(B33), " ", "")) | B33: Serene Grace | C33: てんのめぐみ | D33: Sérénité | E33: Edelmut | F33: Dicha | G33: Leggiadro | H33: 하늘의 은총 | I33: 天恩 | J33: =I33 | K33: =F33
A34: =CONCATENATE("NAME_ABILITY_", SUBSTITUTE(UPPER(B34), " ", "")) | B34: Swift Swim | C34: すいすい | D34: Glissade | E34: Wassertempo | F34: Nado Rápido | G34: Nuotovelox | H34: 쓱쓱 | I34: 悠游自如 | J34: =I34 | K34: =F34
A35: =CONCATENATE("NAME_ABILITY_", SUBSTITUTE(UPPER(B35), " ", "")) | B35: Chlorophyll | C35: ようりょくそ | D35: Chlorophylle | E35: =B35 | F35: Clorofila | G35: Clorofilla | H35: 엽록소 | I35: 葉綠素 | J35: =IFERROR(__xludf.DUMMYFUNCTION("GOOGLETRANSLATE(I35,""zh_HANT"",""zh_HANS"")"),"叶绿素") | K35: =F35
A36: =CONCATENATE("NAME_ABILITY_", SUBSTITUTE(UPPER(B36), " ", "")) | B36: Illuminate | C36: はっこう | D36: Lumiattirance | E36: Erleuchtung | F36: Iluminación | G36: Risplendi | H36: 발광 | I36: 發光 | J36: =IFERROR(__xludf.DUMMYFUNCTION("GOOGLETRANSLATE(I36,""zh_HANT"",""zh_HANS"")"),"发光") | K36: =F36
A37: =CONCATENATE("NAME_ABILITY_", SUBSTITUTE(UPPER(B37), " ", "")) | B37: Trace | C37: トレース | D37: Calque | E37: Fährte | F37: Rastro | G37: Traccia | H37: 트레이스 | I37: 複製 | J37: =IFERROR(__xludf.DUMMYFUNCTION("GOOGLETRANSLATE(I37,""zh_HANT"",""zh_HANS"")"),"克隆") | K37: =F37
A38: =CONCATENATE("NAME_ABILITY_", SUBSTITUTE(UPPER(B38), " ", "")) | B38: Huge Power | C38: ちからもち | D38: Coloforce | E38: Kraftkoloss | F38: Potencia | G38: Macroforza | H38: 천하장사 | I38: 大力士 | J38: =I38 | K38: =F38
A39: =CONCATENATE("NAME_ABILITY_", SUBSTITUTE(UPPER(B39), " ", "")) | B39: Poison Point | C39: どくのトゲ | D39: Point Poison | E39: Giftdorn | F39: Punto Tóxico | G39: Velenopunto | H39: 독가시 | I39: 毒刺 | J39: =I39 | K39: =F39
A40: =CONCATENATE("NAME_ABILITY_", SUBSTITUTE(UPPER(B40), " ", "")) | B40: Inner Focus | C40: せいしんりょく | D40: Attention | E40: Konzentrator | F40: Foco Interno | G40: Forza Interiore | H40: 정신력 | I40: 精神力 | J40: =I40 | K40: =F40
A41: =CONCATENATE("NAME_ABILITY_", SUBSTITUTE(UPPER(B41), " ", "")) | B41: Magma Armor | C41: マグマのよろい | D41: Armumagma | E41: Magmapanzer | F41: Escudo Magma | G41: Magmascudo | H41: 마그마의 무장 | I41: 熔岩鎧甲 | J41: =IFERROR(__xludf.DUMMYFUNCTION("GOOGLETRANSLATE(I41,""zh_HANT"",""zh_HANS"")"),"熔岩铠甲") | K41: =F41
A42: =CONCATENATE("NAME_ABILITY_", SUBSTITUTE(UPPER(B42), " ", "")) | B42: Water Veil | C42: みずのベール | D42: Ignifu-Voile | E42: Aquahülle | F42: Velo Agua | G42: Idrovelo | H42: 수의 베일 | I42: 水幕 | J42: =I42 | K42: =F42
A43: =CONCATENATE("NAME_ABILITY_", SUBSTITUTE(UPPER(B43), " ", "")) | B43: Magnet Pull | C43: じりょく | D43: Magnépiège | E43: Magnetfalle | F43: Imán | G43: Magnetismo | H43: 자력 | I43: 磁力 | J43: =I43 | K43: =F43
A44: =CONCATENATE("NAME_ABILITY_", SUBSTITUTE(UPPER(B44), " ", "")) | B44: Soundproof | C44: ぼうおん | D44: Anti-Bruit | E44: Lärmschutz | F44: Insonorizar | G44: Antisuono | H44: 방음 | I44: 隔音 | J44: =I44 | K44: =F44
A45: =CONCATENATE("NAME_ABILITY_", SUBSTITUTE(UPPER(B45), " ", "")) | B45: Rain Dish | C45: あめうけざら | D45: Cuvette | E45: Regengenuss | F45: Cura Lluvia | G45: Copripioggia | H45: 젖은접시 | I45: 雨盤 | J45: =IFERROR(__xludf.DUMMYFUNCTION("GOOGLETRANSLATE(I45,""zh_HANT"",""zh_HANS"")"),"雨盘") | K45: =F45
A46: =CONCATENATE("NAME_ABILITY_", SUBSTITUTE(UPPER(B46), " ", "")) | B46: Sand Stream | C46: すなおこし | D46: Sable Volant | E46: Sandsturm | F46: Chorro Arena | G46: Sabbiafiume | H46: 모래날림 | I46: 揚沙 | J46: =IFERROR(__xludf.DUMMYFUNCTION("GOOGLETRANSLATE(I46,""zh_HANT"",""zh_HANS"")"),"扬沙") | K46: =F46
A47: =CONCATENATE("NAME_ABILITY_", SUBSTITUTE(UPPER(B47), " ", "")) | B47: Pressure | C47: プレッシャー | D47: Pression | E47: Erzwinger | F47: Presión | G47: =CONCATENATE(D47,"e") | H47: 프레셔 | I47: 壓迫感 | J47: =IFERROR(__xludf.DUMMYFUNCTION("GOOGLETRANSLATE(I47,""zh_HANT"",""zh_HANS"")"),"压迫感") | K47: =F47
A48: =CONCATENATE("NAME_ABILITY_", SUBSTITUTE(UPPER(B48), " ", "")) | B48: Thick Fat | C48: あついしぼう | D48: Isograisse | E48: Speckschicht | F48: Sebo | G48: Grassospesso | H48: 두꺼운 지방 | I48: 厚脂肪 | J48: =I48 | K48: =F48
A49: =CONCATENATE("NAME_ABILITY_", SUBSTITUTE(UPPER(B49), " ", "")) | B49: Early Bird | C49: はやおき | D49: Matinal | E49: Frühwecker | F49: Madrugar | G49: Sveglialampo | H49: 일찍 기상 | I49: 早起 | J49: =I49 | K49: =F49
A50: =CONCATENATE("NAME_ABILITY_", SUBSTITUTE(UPPER(B50), " ", "")) | B50: Flame Body | C50: ほのおのからだ | D50: Corps Ardent | E50: Flammkörper | F50: Cuerpo Llama | G50: Corpodifuoco | H50: 불꽃몸 | I50: 火焰之軀 | J50: =IFERROR(__xludf.DUMMYFUNCTION("GOOGLETRANSLATE(I50,""zh_HANT"",""zh_HANS"")"),"火焰之躯") | K50: =F50
A51: =CONCATENATE("NAME_ABILITY_", SUBSTITUTE(UPPER(B51), " ", "")) | B51: Run Away | C51: にげあし | D51: Fuite | E51: Angsthase | F51: Fuga | G51: =CONCATENATE(F51,"facile") | H51: 도주 | I51: 逃跑 | J51: =I51 | K51: =F51
A52: =CONCATENATE("NAME_ABILITY_", SUBSTITUTE(UPPER(B52), " ", "")) | B52: Keen Eye | C52: するどいめ | D52: Regard Vif | E52: Adlerauge | F52: Vista Lince | G52: Sguardofermo | H52: 날카로운 눈 | I52: 銳利目光 | J52: =IFERROR(__xludf.DUMMYFUNCTION("GOOGLETRANSLATE(I52,""zh_HANT"",""zh_HANS"")"),"锐利目光") | K52: =F52
A53: =CONCATENATE("NAME_ABILITY_", SUBSTITUTE(UPPER(B53), " ", "")) | B53: Hyper Cutter | C53: かいりきバサミ | D53: =B53 | E53: Scherenmacht | F53: Corte Fuerte | G53: Ipertaglio | H53: 괴력집게 | I53: 怪力鉗 | J53: =IFERROR(__xludf.DUMMYFUNCTION("GOOGLETRANSLATE(I53,""zh_HANT"",""zh_HANS"")"),"怪力钳") | K53: =F53
A54: =CONCATENATE("NAME_ABILITY_", SUBSTITUTE(UPPER(B54), " ", "")) | B54: Pickup | C54: ものひろい | D54: Ramassage | E54: Mitnahme | F54: Recogida | G54: Raccolta | H54: 픽업 | I54: 撿拾 | J54: =IFERROR(__xludf.DUMMYFUNCTION("GOOGLETRANSLATE(I54,""zh_HANT"",""zh_HANS"")"),"捡拾") | K54: =F54
A55: =CONCATENATE("NAME_ABILITY_", SUBSTITUTE(UPPER(B55), " ", "")) | B55: Truant | C55: なまけ | D55: Absentéisme | E55: Schnarchnase | F55: Ausente | G55: Pigrone | H55: 게으름 | I55: 懶惰 | J55: =IFERROR(__xludf.DUMMYFUNCTION("GOOGLETRANSLATE(I55,""zh_HANT"",""zh_HANS"")"),"懒惰") | K55: =F55
A56: =CONCATENATE("NAME_ABILITY_", SUBSTITUTE(UPPER(B56), " ", "")) | B56: Hustle | C56: はりきり | D56: Agitation | E56: Übereifer | F56: Entusiasmo | G56: Tuttafretta | H56: 의욕 | I56: 活力 | J56: =I56 | K56: =F56
A57: =CONCATENATE("NAME_ABILITY_", SUBSTITUTE(UPPER(B57), " ", "")) | B57: Cute Charm | C57: メロメロボディ | D57: Joli Sourire | E57: Charmebolzen | F57: Gran Encanto | G57: Incantevole | H57: 헤롱헤롱 바디 | I57: 迷人之軀 | J57: =IFERROR(__xludf.DUMMYFUNCTION("GOOGLETRANSLATE(I57,""zh_HANT"",""zh_HANS"")"),"迷人之躯") | K57: =F57
A58: =CONCATENATE("NAME_ABILITY_", SUBSTITUTE(UPPER(B58), " ", "")) | B58: Plus | C58: プラス | D58: =B58 | E58: =B58 | F58: Más | G58: Più | H58: 플러스 | I58: 正電 | J58: =IFERROR(__xludf.DUMMYFUNCTION("GOOGLETRANSLATE(I58,""zh_HANT"",""zh_HANS"")"),"正电") | K58: =F58
A59: =CONCATENATE("NAME_ABILITY_", SUBSTITUTE(UPPER(B59), " ", "")) | B59: Minus | C59: マイナス | D59: =B59 | E59: =B59 | F59: Menos | G59: Meno | H59: 마이너스 | I59: 負電 | J59: =IFERROR(__xludf.DUMMYFUNCTION("GOOGLETRANSLATE(I59,""zh_HANT"",""zh_HANS"")"),"负电") | K59: =F59
A60: =CONCATENATE("NAME_ABILITY_", SUBSTITUTE(UPPER(B60), " ", "")) | B60: Forecast | C60: たんきや | D60: Météo | E60: Prognose | F60: Predicción | G60: Previsioni | H60: 기분파 | I60: 陰晴不定 | J60: =IFERROR(__xludf.DUMMYFUNCTION("GOOGLETRANSLATE(I60,""zh_HANT"",""zh_HANS"")"),"阴晴不定") | K60: =F60
A61: =CONCATENATE("NAME_ABILITY_", SUBSTITUTE(UPPER(B61), " ", "")) | B61: Sticky Hold | C61: ねんちゃく | D61: Glue | E61: Wertehalter | F61: Viscosidad | G61: Antifurto | H61: 점착 | I61: 黏著 | J61: =IFERROR(__xludf.DUMMYFUNCTION("GOOGLETRANSLATE(I61,""zh_HANT"",""zh_HANS"")"),"黏着") | K61: =F61
A62: =CONCATENATE("NAME_ABILITY_", SUBSTITUTE(UPPER(B62), " ", "")) | B62: Shed Skin | C62: だっぴ | D62: Mue | E62: Expidermis | F62: Mudar | G62: Muta | H62: 탈피 | I62: 蛻皮 | J62: =IFERROR(__xludf.DUMMYFUNCTION("GOOGLETRANSLATE(I62,""zh_HANT"",""zh_HANS"")"),"蜕皮") | K62: =F62
A63: =CONCATENATE("NAME_ABILITY_", SUBSTITUTE(UPPER(B63), " ", "")) | B63: Guts | C63: こんじょう | D63: Cran | E63: Adrenalin | F63: Agallas | G63: Dentistretti | H63: 근성 | I63: 毅力 | J63: =I63 | K63: =F63
A64: =CONCATENATE("NAME_ABILITY_", SUBSTITUTE(UPPER(B64), " ", "")) | B64: Marvel Scale | C64: ふしぎなうろこ | D64: Écaille Spéciale | E64: Notschutz | F64: Escama Especial | G64: Pelledura | H64: 이상한 비늘 | I64: 神奇鱗片 | J64: =IFERROR(__xludf.DUMMYFUNCTION("GOOGLETRANSLATE(I64,""zh_HANT"",""zh_HANS"")"),"神奇鳞片") | K64: =F64
A65: =CONCATENATE("NAME_ABILITY_", SUBSTITUTE(UPPER(B65), " ", "")) | B65: Liquid Ooze | C65: ヘドロえき | D65: Suintement | E65: Kloakensoße | F65: Lodo Líquido | G65: Melma | H65: 해감액 | I65: 污泥漿 | J65: =IFERROR(__xludf.DUMMYFUNCTION("GOOGLETRANSLATE(I65,""zh_HANT"",""zh_HANS"")"),"污泥浆") | K65: =F65
A66: =CONCATENATE("NAME_ABILITY_", SUBSTITUTE(UPPER(B66), " ", "")) | B66: Overgrow | C66: しんりょく | D66: Engrais | E66: Notdünger | F66: Espesura | G66: Erbaiuto | H66: 심록 | I66: 茂盛 | J66: =I66 | K66: =F66
A67: =CONCATENATE("NAME_ABILITY_", SUBSTITUTE(UPPER(B67), " ", "")) | B67: Blaze | C67: もうか | D67: Brasier | E67: Großbrand | F67: Mar Llamas | G67: Aiutofuoco | H67: 맹화 | I67: 猛火 | J67: =I67 | K67: =F67
A68: =CONCATENATE("NAME_ABILITY_", SUBSTITUTE(UPPER(B68), " ", "")) | B68: Torrent | C68: げきりゅう | D68: =B68 | E68: Sturzbach | F68: Torrente | G68: Acquaiuto | H68: 급류 | I68: 激流 | J68: =I68 | K68: =F68
A69: =CONCATENATE("NAME_ABILITY_", SUBSTITUTE(UPPER(B69), " ", "")) | B69: Swarm | C69: むしのしらせ | D69: Essaim | E69: Hexaplaga | F69: Enjambre | G69: Aiutinsetto | H69: 벌레의 알림 | I69: 蟲之預感 | J69: =IFERROR(__xludf.DUMMYFUNCTION("GOOGLETRANSLATE(I69,""zh_HANT"",""zh_HANS"")"),"虫之预感") | K69: =F69
A70: =CONCATENATE("NAME_ABILITY_", SUBSTITUTE(UPPER(B70), " ", "")) | B70: Rock Head | C70: いしあたま | D70: Tête de Roc | E70: Steinhaupt | F70: Cabeza Roca | G70: Testadura | H70: 돌머리 | I70: 堅硬腦袋 | J70: =IFERROR(__xludf.DUMMYFUNCTION("GOOGLETRANSLATE(I70,""zh_HANT"",""zh_HANS"")"),"坚硬脑袋") | K70: =F70
A71: =CONCATENATE("NAME_ABILITY_", SUBSTITUTE(UPPER(B71), " ", "")) | B71: Drought | C71: ひでり | D71: Sécheresse | E71: Dürre | F71: Sequía | G71: Siccità | H71: 가뭄 | I71: 日照 | J71: =I71 | K71: =F71
A72: =CONCATENATE("NAME_ABILITY_", SUBSTITUTE(UPPER(B72), " ", "")) | B72: Arena Trap | C72: ありじごく | D72: Piège | E72: Ausweglos | F72: Trampa Arena | G72: Trappoarena | H72: 개미지옥 | I72: 沙穴 | J72: =I72 | K72: =F72
A73: =CONCATENATE("NAME_ABILITY_", SUBSTITUTE(UPPER(B73), " ", "")) | B73: Vital Spirit | C73: やるき | D73: Esprit Vital | E73: Munterkeit | F73: Espíritu Vital | G73: Spiritovivo | H73: 의기양양 | I73: 幹勁 | J73: =IFERROR(__xludf.DUMMYFUNCTION("GOOGLETRANSLATE(I73,""zh_HANT"",""zh_HANS"")"),"干劲") | K73: =F73
A74: =CONCATENATE("NAME_ABILITY_", SUBSTITUTE(UPPER(B74), " ", "")) | B74: White Smoke | C74: しろいけむり | D74: Écran Fumée | E74: Pulverrauch | F74: Humo Blanco | G74: Fumochario | H74: 하얀연기 | I74: 白色煙霧 | J74: =IFERROR(__xludf.DUMMYFUNCTION("GOOGLETRANSLATE(I74,""zh_HANT"",""zh_HANS"")"),"白色烟雾") | K74: =F74
A75: =CONCATENATE("NAME_ABILITY_", SUBSTITUTE(UPPER(B75), " ", "")) | B75: Pure Power | C75: ヨガパワー | D75: Force Pure | E75: Mentalkraft | F75: Energía Pura | G75: Forzapura | H75: 순수한힘 | I75: 瑜伽之力 | J75: =I75 | K75: =F75
A76: =CONCATENATE("NAME_ABILITY_", SUBSTITUTE(UPPER(B76), " ", "")) | B76: Shell Armor | C76: シェルアーマー | D76: Coque Armure | E76: Panzerhaut | F76: Caparazón | G76: Guscioscudo | H76: 조가비 갑옷 | I76: 硬殼盔甲 | J76: =IFERROR(__xludf.DUMMYFUNCTION("GOOGLETRANSLATE(I76,""zh_HANT"",""zh_HANS"")"),"硬壳盔甲") | K76: =F76
A77: =CONCATENATE("NAME_ABILITY_", SUBSTITUTE(UPPER(B77), " ", "")) | B77: Air Lock | C77: エアロック | D77: Air Lock | E77: Klimaschutz | F77: Bucle Aire | G77: Riparo | H77: 에어록 | I77: 氣閘 | J77: =IFERROR(__xludf.DUMMYFUNCTION("GOOGLETRANSLATE(I77,""zh_HANT"",""zh_HANS"")"),"气闸") | K77: =F77
A78: =CONCATENATE("NAME_ABILITY_", SUBSTITUTE(UPPER(B78), " ", "")) | B78: Tangled Feet | C78: ちどりあし | D78: Pieds Confus | E78: Fußangel | F78: Tumbos | G78: Intricopiedi | H78: 갈지자걸음 | I78: 蹣跚 | J78: =IFERROR(__xludf.DUMMYFUNCTION("GOOGLETRANSLATE(I78,""zh_HANT"",""zh_HANS"")"),"蹒跚") | K78: =F78
A79: =CONCATENATE("NAME_ABILITY_", SUBSTITUTE(UPPER(B79), " ", "")) | B79: Motor Drive | C79: でんきエンジン | D79: Motorisé | E79: Starthilfe | F79: Electromotor | G79: Elettrorapid | H79: 전기엔진 | I79: 電氣引擎 | J79: =IFERROR(__xludf.DUMMYFUNCTION("GOOGLETRANSLATE(I79,""zh_HANT"",""zh_HANS"")"),"电气引擎") | K79: =F79
A80: =CONCATENATE("NAME_ABILITY_", SUBSTITUTE(UPPER(B80), " ", "")) | B80: Rivalry | C80: とうそうしん | D80: Rivalité | E80: Rivalität | F80: Rivalidad | G80: Antagonismo | H80: 투쟁심 | I80: 鬥爭心 | J80: =IFERROR(__xludf.DUMMYFUNCTION("GOOGLETRANSLATE(I80,""zh_HANT"",""zh_HANS"")"),"斗争心") | K80: =F80
A81: =CONCATENATE("NAME_ABILITY_", SUBSTITUTE(UPPER(B81), " ", "")) | B81: Steadfast | C81: ふくつのこころ | D81: Impassible | E81: Felsenfest | F81: Impasible | G81: Cuordeciso | H81: 불굴의 마음 | I81: 不屈之心 | J81: =I81 | K81: =F81
A82: =CONCATENATE("NAME_ABILITY_", SUBSTITUTE(UPPER(B82), " ", "")) | B82: Snow Cloak | C82: ゆきがくれ | D82: Rideau Neige | E82: Schneemantel | F82: Manto Níveo | G82: Mantelneve | H82: 눈숨기 | I82: 雪隱 | J82: =IFERROR(__xludf.DUMMYFUNCTION("GOOGLETRANSLATE(I82,""zh_HANT"",""zh_HANS"")"),"雪隐") | K82: =F82
A83: =CONCATENATE("NAME_ABILITY_", SUBSTITUTE(UPPER(B83), " ", "")) | B83: Gluttony | C83: くいしんぼう | D83: Gloutonnerie | E83: Völlerei | F83: Gula | G83: Voracità | H83: 먹보 | I83: 貪吃鬼 | J83: =IFERROR(__xludf.DUMMYFUNCTION("GOOGLETRANSLATE(I83,""zh_HANT"",""zh_HANS"")"),"贪吃鬼") | K83: =F83
A84: =CONCATENATE("NAME_ABILITY_", SUBSTITUTE(UPPER(B84), " ", "")) | B84: Anger Point | C84: いかりのつぼ | D84: Colérique | E84: Kurzschluss | F84: Irascible | G84: Grancollera | H84: 분노의 경혈 | I84: 憤怒穴位 | J84: =IFERROR(__xludf.DUMMYFUNCTION("GOOGLETRANSLATE(I84,""zh_HANT"",""zh_HANS"")"),"愤怒穴位") | K84: =F84
A85: =CONCATENATE("NAME_ABILITY_", SUBSTITUTE(UPPER(B85), " ", "")) | B85: Unburden | C85: かるわざ | D85: Délestage | E85: Entlastung | F85: Liviano | G85: Agiltecnica | H85: 곡예 | I85: 輕裝 | J85: =IFERROR(__xludf.DUMMYFUNCTION("GOOGLETRANSLATE(I85,""zh_HANT"",""zh_HANS"")"),"轻装") | K85: =F85
A86: =CONCATENATE("NAME_ABILITY_", SUBSTITUTE(UPPER(B86), " ", "")) | B86: Heatproof | C86: たいねつ | D86: Ignifugé | E86: Hitzeschutz | F86: Ignífugo | G86: Antifuoco | H86: 내열 | I86: 耐熱 | J86: =IFERROR(__xludf.DUMMYFUNCTION("GOOGLETRANSLATE(I86,""zh_HANT"",""zh_HANS"")"),"耐热") | K86: =F86
A87: =CONCATENATE("NAME_ABILITY_", SUBSTITUTE(UPPER(B87), " ", "")) | B87: Simple | C87: たんじゅん | D87: Simple | E87: Wankelmut | F87: Simple | G87: Disinvoltura | H87: 단순 | I87: 單純 | J87: =IFERROR(__xludf.DUMMYFUNCTION("GOOGLETRANSLATE(I87,""zh_HANT"",""zh_HANS"")"),"单纯") | K87: =F87
A88: =CONCATENATE("NAME_ABILITY_", SUBSTITUTE(UPPER(B88), " ", "")) | B88: Dry Skin | C88: かんそうはだ | D88: Peau Sèche | E88: Trockenheit | F88: Piel Seca | G88: Pellearsa | H88: 건조피부 | I88: 乾燥皮膚 | J88: =IFERROR(__xludf.DUMMYFUNCTION("GOOGLETRANSLATE(I88,""zh_HANT"",""zh_HANS"")"),"干燥皮肤") | K88: =F88
A89: =CONCATENATE("NAME_ABILITY_", SUBSTITUTE(UPPER(B89), " ", "")) | B89: Download | C89: ダウンロード | D89: Télécharge | E89: =B89 | F89: Descarga | G89: =B89 | H89: 다운로드 | I89: 下載 | J89: =IFERROR(__xludf.DUMMYFUNCTION("GOOGLETRANSLATE(I89,""zh_HANT"",""zh_HANS"")"),"下载") | K89: =F89
A90: =CONCATENATE("NAME_ABILITY_", SUBSTITUTE(UPPER(B90), " ", "")) | B90: Iron Fist | C90: てすのこぶし | D90: Poing de Fer | E90: Eisenfaust | F90: Puño Férreo | G90: Ferropungo | H90: 철주먹 | I90: 鐵拳 | J90: =IFERROR(__xludf.DUMMYFUNCTION("GOOGLETRANSLATE(I90,""zh_HANT"",""zh_HANS"")"),"铁拳") | K90: =F90
A91: =CONCATENATE("NAME_ABILITY_", SUBSTITUTE(UPPER(B91), " ", "")) | B91: Poison Heal | C91: ポイズンヒール | D91: Soin Poison | E91: Aufheber | F91: Antídoto | G91: Velencura | H91: 포이즌힐 | I91: 毒療 | J91: =IFERROR(__xludf.DUMMYFUNCTION("GOOGLETRANSLATE(I91,""zh_HANT"",""zh_HANS"")"),"毒疗") | K91: =F91
A92: =CONCATENATE("NAME_ABILITY_", SUBSTITUTE(UPPER(B92), " ", "")) | B92: Adaptability | C92: てきおうりょく | D92: Adaptabilité | E92: Anpassung | F92: Adaptable | G92: Adattabilità | H92: 적응력 | I92: 適應力 | J92: =IFERROR(__xludf.DUMMYFUNCTION("GOOGLETRANSLATE(I92,""zh_HANT"",""zh_HANS"")"),"适应力") | K92: =F92
A93: =CONCATENATE("NAME_ABILITY_", SUBSTITUTE(UPPER(B93), " ", "")) | B93: Skill Link | C93: スキルリンク | D93: Multi-Coups | E93: Wertelink | F93: Encadenado | G93: Abillegame | H93: 스킬링크 | I93: 連續攻擊 | J93: =IFERROR(__xludf.DUMMYFUNCTION("GOOGLETRANSLATE(I93,""zh_HANT"",""zh_HANS"")"),"连续攻击") | K93: =F93
A94: =CONCATENATE("NAME_ABILITY_", SUBSTITUTE(UPPER(B94), " ", "")) | B94: Hydration | C94: うるおいボディ | D94: Hydratation | E94: =B94 | F94: Hidratación | G94: Idratazione | H94: 촉촉바디 | I94: 濕潤之軀 | J94: =IFERROR(__xludf.DUMMYFUNCTION("GOOGLETRANSLATE(I94,""zh_HANT"",""zh_HANS"")"),"湿润之躯") | K94: =F94
A95: =CONCATENATE("NAME_ABILITY_", SUBSTITUTE(UPPER(B95), " ", "")) | B95: Solar Power | C95: サンパワー | D95: Force Soleil | E95: Solarkraft | F95: Poder Solar | G95: Solarpotere | H95: 선파워 | I95: 太陽之力 | J95: =IFERROR(__xludf.DUMMYFUNCTION("GOOGLETRANSLATE(I95,""zh_HANT"",""zh_HANS"")"),"太阳之力") | K95: =F95
A96: =CONCATENATE("NAME_ABILITY_", SUBSTITUTE(UPPER(B96), " ", "")) | B96: Quick Feet | C96: はやあし | D96: Pied Véloce | E96: Rasanz | F96: Pies Rápidos | G96: Piedisvelti | H96: 속보 | I96: 飛毛腿 | J96: =IFERROR(__xludf.DUMMYFUNCTION("GOOGLETRANSLATE(I96,""zh_HANT"",""zh_HANS"")"),"飞毛腿") | K96: =F96
A97: =CONCATENATE("NAME_ABILITY_", SUBSTITUTE(UPPER(B97), " ", "")) | B97: Normalize | C97: ノーマルスキン | D97: Normalise | E97: Regulierung | F97: Normalidad | G97: Normalità | H97: 노말스킨 | I97: 一般皮膚 | J97: =IFERROR(__xludf.DUMMYFUNCTION("GOOGLETRANSLATE(I97,""zh_HANT"",""zh_HANS"")"),"一般皮肤") | K97: =F97
A98: =CONCATENATE("NAME_ABILITY_", SUBSTITUTE(UPPER(B98), " ", "")) | B98: Sniper | C98: スナイパー | D98: Sniper | E98: Superschütze | F98: Francotirador | G98: Cecchino | H98: 스나이퍼 | I98: 狙擊手 | J98: =IFERROR(__xludf.DUMMYFUNCTION("GOOGLETRANSLATE(I98,""zh_HANT"",""zh_HANS"")"),"狙击手") | K98: =F98
A99: =CONCATENATE("NAME_ABILITY_", SUBSTITUTE(UPPER(B99), " ", "")) | B99: Magic Guard | C99: マジックガード | D99: Garde Magik | E99: Magieschild | F99: Muro Mágico | G99: Magicscudo | H99: 매직가드 | I99: 魔法防守 | J99: =I99 | K99: =F99
A100: =CONCATENATE("NAME_ABILITY_", SUBSTITUTE(UPPER(B100), " ", "")) | B100: No Guard | C100: ノーガード | D100: Annule Garde | E100: Schildlos | F100: Indefenso | G100: Nullodifesa | H100: 노가드 | I100: 無防守 | J100: =IFERROR(__xludf.DUMMYFUNCTION("GOOGLETRANSLATE(I100,""zh_HANT"",""zh_HANS"")"),"无防守") | K100: =F100
...

Sheet Natures
A1: =Pokemon!A1 | B1: =Pokemon!B1 | C1: =Pokemon!C1 | D1: =Pokemon!D1 | E1: =Pokemon!E1 | F1: =Pokemon!F1 | G1: =Pokemon!G1 | H1: =Pokemon!H1 | ... K1: =Pokemon!K1
A2: =CONCATENATE("NAME_NATURE_", UPPER(B2)) | B2: Adamant | C2: いじっぱり | D2: Rigide | E2: Hart | F2: Firme | G2: Decisa | H2: 고집 | I2: 固執 | J2: =IFERROR(__xludf.DUMMYFUNCTION("GOOGLETRANSLATE(I2,""zh_HANT"",""zh_HANS"")"),"固执") | K2: =F2
A3: =CONCATENATE("NAME_NATURE_", UPPER(B3)) | B3: Bashful | C3: てれや | D3: Pudique | E3: Zaghaft | F3: Tímida | G3: Ritrosa | H3: 수줍음 | I3: 害羞 | J3: =I3 | K3: =F3
A4: =CONCATENATE("NAME_NATURE_", UPPER(B4)) | B4: Bold | C4: ずぶとい | D4: Assuré | E4: Kühn | F4: Osada | G4: Sicura | H4: 대담 | I4: 大膽 | J4: =IFERROR(__xludf.DUMMYFUNCTION("GOOGLETRANSLATE(I4,""zh_HANT"",""zh_HANS"")"),"大胆") | K4: =F4
A5: =CONCATENATE("NAME_NATURE_", UPPER(B5)) | B5: Brave | C5: ゆうかん | D5: =B5 | E5: Mutig | F5: Audaz | G5: Audace | H5: 용감 | I5: 勇敢 | J5: =I5 | K5: =F5
A6: =CONCATENATE("NAME_NATURE_", UPPER(B6)) | B6: Calm | C6: おだやか | D6: Calme | E6: Still | F6: Serena | G6: Calma | H6: 차분 | I6: 溫和 | J6: =IFERROR(__xludf.DUMMYFUNCTION("GOOGLETRANSLATE(I6,""zh_HANT"",""zh_HANS"")"),"温和") | K6: =F6
A7: =CONCATENATE("NAME_NATURE_", UPPER(B7)) | B7: Careful | C7: しんちょう | D7: Prudent | E7: Sacht | F7: Cauta | G7: Cauta | H7: 신중 | I7: 慎重 | J7: =I7 | K7: =F7
A8: =CONCATENATE("NAME_NATURE_", UPPER(B8)) | B8: Docile | C8: すなお | D8: =B8 | E8: Sanft | F8: Dócil | G8: Docile | H8: 온순 | I8: 坦率 | J8: =I8 | K8: =F8
A9: =CONCATENATE("NAME_NATURE_", UPPER(B9)) | B9: Gentle | C9: おとなしい | D9: Gentil | E9: Zart | F9: Amable | G9: Gentile | H9: 얌전 | I9: 溫順 | J9: =IFERROR(__xludf.DUMMYFUNCTION("GOOGLETRANSLATE(I9,""zh_HANT"",""zh_HANS"")"),"温顺") | K9: =F9
A10: =CONCATENATE("NAME_NATURE_", UPPER(B10)) | B10: Hardy | C10: がんばりや | D10: Hardi | E10: Robust | F10: Fuerte | G10: Ardita | H10: 노력 | I10: 勤奮 | J10: =IFERROR(__xludf.DUMMYFUNCTION("GOOGLETRANSLATE(I10,""zh_HANT"",""zh_HANS"")"),"勤奋") | K10: =F10
A11: =CONCATENATE("NAME_NATURE_", UPPER(B11)) | B11: Hasty | C11: せっかち | D11: Pressé | E11: Hastig | F11: Activa | G11: Lesta | H11: 성급 | I11: 急躁 | J11: =I11 | K11: =F11
A12: =CONCATENATE("NAME_NATURE_", UPPER(B12)) | B12: Impish | C12: わんぱく | D12: Malin | E12: Pfiffig | F12: Agitada | G12: Scaltra | H12: 장난꾸러기 | I12: 淘氣 | J12: =IFERROR(__xludf.DUMMYFUNCTION("GOOGLETRANSLATE(I12,""zh_HANT"",""zh_HANS"")"),"淘气") | K12: =F12
A13: =CONCATENATE("NAME_NATURE_", UPPER(B13)) | B13: Jolly | C13: ようき | D13: Jovial | E13: Froh | F13: Alegre | G13: Allegra | H13: 명랑 | I13: 爽朗 | J13: =I13 | K13: =F13
A14: =CONCATENATE("NAME_NATURE_", UPPER(B14)) | B14: Lax | C14: のうてんき | D14: Lâche | E14: Lasch | F14: Floja | G14: Fiacca | H14: 촐랑 | I14: 樂天 | J14: =IFERROR(__xludf.DUMMYFUNCTION("GOOGLETRANSLATE(I14,""zh_HANT"",""zh_HANS"")"),"乐天") | K14: =F14
A15: =CONCATENATE("NAME_NATURE_", UPPER(B15)) | B15: Lonely | C15: さみしがり | D15: Solo | E15: =D15 | F15: Huraña | G15: Schiva | H15: 외로움 | I15: 怕寂寞 | J15: =I15 | K15: =F15
A16: =CONCATENATE("NAME_NATURE_", UPPER(B16)) | B16: Mild | C16: おっとり | D16: Doux | E16: =B16 | F16: Afable | G16: Mite | H16: 의젓 | I16: 慢吞吞 | J16: =I16 | K16: =F16
A17: =CONCATENATE("NAME_NATURE_", UPPER(B17)) | B17: Modest | C17: ひかえめ | D17: Modeste | E17: Mäßig | F17: Modesta | G17: Modesta | H17: 조심 | I17: 內斂 | J17: =IFERROR(__xludf.DUMMYFUNCTION("GOOGLETRANSLATE(I17,""zh_HANT"",""zh_HANS"")"),"内敛") | K17: =F17
A18: =CONCATENATE("NAME_NATURE_", UPPER(B18)) | B18: Naive | C18: むじゃき | D18: Naïf | E18: Naiv | F18: Ingenua | G18: Ingenua | H18: 천진난만 | I18: 天真 | J18: =I18 | K18: =F18
A19: =CONCATENATE("NAME_NATURE_", UPPER(B19)) | B19: Naughty | C19: やんちゃ | D19: Mauvais | E19: Frech | F19: Pícara | G19: Birbona | H19: 개구쟁이 | I19: 頑皮 | J19: =IFERROR(__xludf.DUMMYFUNCTION("GOOGLETRANSLATE(I19,""zh_HANT"",""zh_HANS"")"),"顽皮") | K19: =F19
A20: =CONCATENATE("NAME_NATURE_", UPPER(B20)) | B20: Quiet | C20: れいせい | D20: Discret | E20: Ruhig | F20: Mansa | G20: Quieta | H20: 냉정 | I20: 冷靜 | J20: =IFERROR(__xludf.DUMMYFUNCTION("GOOGLETRANSLATE(I20,""zh_HANT"",""zh_HANS"")"),"冷静") | K20: =F20
A21: =CONCATENATE("NAME_NATURE_", UPPER(B21)) | B21: Quirky | C21: きまぐれ | D21: Bizarre | E21: Kauzig | F21: Rara | G21: Furba | H21: 변덕 | I21: 浮躁 | J21: =I21 | K21: =F21
A22: =CONCATENATE("NAME_NATURE_", UPPER(B22)) | B22: Rash | C22: うっかりや | D22: Foufou | E22: Hitzig | F22: Alocada | G22: Ardente | H22: 덜렁 | I22: 馬虎 | J22: =IFERROR(__xludf.DUMMYFUNCTION("GOOGLETRANSLATE(I22,""zh_HANT"",""zh_HANS"")"),"马虎") | K22: =F22
A23: =CONCATENATE("NAME_NATURE_", UPPER(B23)) | B23: Relaxed | C23: のんき | D23: Relax | E23: Locker | F23: Plácida | G23: Placida | H23: 무사태평 | I23: 悠閒 | J23: =IFERROR(__xludf.DUMMYFUNCTION("GOOGLETRANSLATE(I23,""zh_HANT"",""zh_HANS"")"),"悠闲") | K23: =F23
A24: =CONCATENATE("NAME_NATURE_", UPPER(B24)) | B24: Sassy | C24: なまいき | D24: Malpoli | E24: Forsch | F24: Grosera | G24: Vivace | H24: 건방 | I24: 自大 | J24: =I24 | K24: =F24
A25: =CONCATENATE("NAME_NATURE_", UPPER(B25)) | B25: Serious | C25: まじめ | D25: Sérieux | E25: Ernst | F25: Seria | G25: Seria | H25: 성실 | I25: 認真 | J25: =IFERROR(__xludf.DUMMYFUNCTION("GOOGLETRANSLATE(I25,""zh_HANT"",""zh_HANS"")"),"认真") | K25: =F25
A26: =CONCATENATE("NAME_NATURE_", UPPER(B26)) | B26: Timid | C26: おくびょう | D26: Timide | E26: Scheu | F26: Miedosa | G26: Timida | H26: 겁쟁이 | I26: 膽小 | J26: =IFERROR(__xludf.DUMMYFUNCTION("GOOGLETRANSLATE(I26,""zh_HANT"",""zh_HANS"")"),"胆小") | K26: =F26

Sheet Characteristics
A1: =Pokemon!A1 | B1: =Pokemon!B1 | C1: =Pokemon!C1 | D1: =Pokemon!D1 | E1: =Pokemon!E1 | F1: =Pokemon!F1 | G1: =Pokemon!G1 | H1: =Pokemon!H1 | ... K1: =Pokemon!K1
A2: CHARACTERISTIC_HP-0 | B2: Loves to eat | C2: 食べるのが 大好き | D2: Adore manger | E2: Liebt es zu essen | F2: Le encanta comer | G2: Adora mangiare | H2: 먹는 것을 제일 좋아함 | I2: 非常喜歡吃東西 | J2: =IFERROR(__xludf.DUMMYFUNCTION("GOOGLETRANSLATE(I2,""zh_HANT"",""zh_HANS"")"),"非常喜欢吃东西") | K2: =F2
A3: CHARACTERISTIC_HP-1 | B3: Takes plenty of siestas | C3: 昼寝を よくする | D3: S'assoupit souvent | E3: Nickt oft ein | F3: A menudo se duerme | G3: Si addormenta spesso | H3: 낮잠을 잘 잠 | I3: 經常睡午覺 | J3: =IFERROR(__xludf.DUMMYFUNCTION("GOOGLETRANSLATE(I3,""zh_HANT"",""zh_HANS"")"),"经常睡午觉") | K3: Le encanta dormir la siesta.
A4: CHARACTERISTIC_HP-2 | B4: Nods off a lot | C4: 居眠りが 多い | D4: Dort beaucoup | E4: Schläft gern | F4: Duerme mucho | G4: Dorme a lungo | H4: 말뚝잠이 많음 | I4: 常常打瞌睡 | J4: =I4 | K4: =F4
A5: CHARACTERISTIC_HP-3 | B5: Scatter things often | C5: ものを よく 散らかす | D5: Éparpille des choses | E5: Macht oft Unordnung | F5: Suele desordenar cosas | G5: Lascia cose in giro | H5: 물건을 잘 어지름 | I5: 經常亂扔東西 | J5: =IFERROR(__xludf.DUMMYFUNCTION("GOOGLETRANSLATE(I5,""zh_HANT"",""zh_HANS"")"),"经常乱扔东西") | K5: =F5
A6: CHARACTERISTIC_HP-4 | B6: Likes to relax | C6: のんびりするのが 好き | D6: Aime se détendre | E6: Mag es, sich zu entspannen | F6: Le gusta relajarse | G6: Adora rilassarsi | H6: 유유자적함을 좋아함 | I6: 喜歡悠然自在 | J6: =IFERROR(__xludf.DUMMYFUNCTION("GOOGLETRANSLATE(I6,""zh_HANT"",""zh_HANS"")"),"喜欢悠然自在") | K6: =F6
A7: CHARACTERISTIC_ATK-0 | B7: Proud of its power | C7: 力が 自慢 | D7: Est fier de sa puissance | E7: Ist stolz auf seine Stärke | F7: Orgulloso de su fuerza | G7: La forza è il suo vanto | H7: 힘자랑이 특기임 | I7: 以力氣大為傲 | J7: =IFERROR(__xludf.DUMMYFUNCTION("GOOGLETRANSLATE(I7,""zh_HANT"",""zh_HANS"")"),"以力气大为傲") | K7: =F7
A8: CHARACTERISTIC_ATK-1 | B8: Likes to thrash about | C8: 暴れることが 好き | D8: Aime se démener | E8: Prügelt sich gern | F8: Le gusta revolverse | G8: Adora dimenarsi | H8: 난동부리기를 좋아함 | I8: 喜歡胡鬧 | J8: =IFERROR(__xludf.DUMMYFUNCTION("GOOGLETRANSLATE(I8,""zh_HANT"",""zh_HANS"")"),"喜欢胡闹") | K8: Le gusta revolcarse.
A9: CHARACTERISTIC_ATK-2 | B9: A little quick tempered | C9: ちょっと 怒りっぽい | D9: Un peu coléreux | E9: Besitzt Temperament | F9: A veces se enfada | G9: Si arrabbia facilmente | H9: 약간 화를 잘 내는 성미임 | I9: 有點容易生氣 | J9: =IFERROR(__xludf.DUMMYFUNCTION("GOOGLETRANSLATE(I9,""zh_HANT"",""zh_HANS"")"),"有点容易生气") | K9: A veces se enoja.
A10: CHARACTERISTIC_ATK-3 | B10: Likes to fight | C10: ケンカを するのが 好き | D10: Aime combattre | E10: Liebt Kämpfe | F10: Le gusta luchar | G10: Adora combattere | H10: 싸움을 좋아함 | I10: 喜歡打架 | J10: =IFERROR(__xludf.DUMMYFUNCTION("GOOGLETRANSLATE(I10,""zh_HANT"",""zh_HANS"")"),"喜欢打架") | K10: Le gusta pelear.
A11: CHARACTERISTIC_ATK-4 | B11: Quick tempered | C11: 血の気が 多い | D11: S'emporte facilement | E11: Ist impulsiv | F11: Tiene mal genio | G11: È facilmente irritabile | H11: 혈기가 왕성함 | I11: 血氣方剛 | J11: =IFERROR(__xludf.DUMMYFUNCTION("GOOGLETRANSLATE(I11,""zh_HANT"",""zh_HANS"")"),"血气方刚") | K11: Tiene mal carácter.
A12: CHARACTERISTIC_DEF-0 | B12: Sturdy Body | C12: 体が 丈夫 | D12: Corps robuste | E12: Hat einen robusten Körper | F12: Cuerpo resistente | G12: Ha un corpo robusto | H12: 몸이 튼튼함 | I12: 身體強壯 | J12: =IFERROR(__xludf.DUMMYFUNCTION("GOOGLETRANSLATE(I12,""zh_HANT"",""zh_HANS"")"),"身体强壮") | K12: =F12
A13: CHARACTERISTIC_DEF-1 | B13: Capable of taking hits | C13: 打たれ強い | D13: Sait encaisser les coups | E13: Kann Treffer gut verkraften | F13: Es buen fajador | G13: Incassa bene i colpi | H13: 맷집이 강함 | I13: 抗打能力強 | J13: =IFERROR(__xludf.DUMMYFUNCTION("GOOGLETRANSLATE(I13,""zh_HANT"",""zh_HANS"")"),"抗打能力强") | K13: Resiste bien los ataques.
A14: CHARACTERISTIC_DEF-2 | B14: Highly persistent | C14: 粘り強い | D14: Très obstiné | E14: Ist äußerst ausdauernd | F14: Muy persistente | G14: È molto ostinato | H14: 끈질김 | I14: 頑強不屈 | J14: =IFERROR(__xludf.DUMMYFUNCTION("GOOGLETRANSLATE(I14,""zh_HANT"",""zh_HANS"")"),"顽强不屈") | K14: =F14
A15: CHARACTERISTIC_DEF-3 | B15: Good endurance | C15: 辛抱強い | D15: Bonne endurance | E15: Hat eine gute Ausdauer | F15: Muy resistente | G15: È molto paziente | H15: 인내심이 강함 | I15: 能吃苦耐勞 | J15: =IFERROR(__xludf.DUMMYFUNCTION("GOOGLETRANSLATE(I15,""zh_HANT"",""zh_HANS"")"),"能吃苦耐劳") | K15: =F15
A16: CHARACTERISTIC_DEF-4 | B16: Good perseverance | C16: 我慢強い | D16: Persévérant | E16: Ist beharrlich | F16: Muy perseverante | G16: È molto tenace | H16: 잘 참음 | I16: 善於忍耐 | J16: =IFERROR(__xludf.DUMMYFUNCTION("GOOGLETRANSLATE(I16,""zh_HANT"",""zh_HANS"")"),"善于忍耐") | K16: =F16
A17: CHARACTERISTIC_SPA-0 | B17: Highly curious | C17: 好奇心が 強い | D17: Extrêmement curieux | E17: Ist sehr neugierig | F17: Extremadamente curioso | G17: È un grande ficcanaso | H17: 호기심이 강함 | I17: 好奇心強 | J17: =IFERROR(__xludf.DUMMYFUNCTION("GOOGLETRANSLATE(I17,""zh_HANT"",""zh_HANS"")"),"好奇心强") | K17: =F17
A18: CHARACTERISTIC_SPA-1 | B18: Mischevious | C18: イタズラが 好き | D18: Coquin | E18: Ist hinterhältig | F18: Le gusta hacer travesuras | G18: È alquanto vivace | H18: 장난을 좋아함 | I18: 喜歡惡作劇 | J18: =IFERROR(__xludf.DUMMYFUNCTION("GOOGLETRANSLATE(I18,""zh_HANT"",""zh_HANS"")"),"喜欢恶作剧") | K18: =F18
A19: CHARACTERISTIC_SPA-2 | B19: Thoroughly cunning | C19: 抜け目が ない | D19: Très astucieux | E19: Ist äußerst gerissen | F19: Muy astuto | G19: È estremamente sagace | H19: 빈틈이 없음 | I19: 做事萬無一失 | J19: =IFERROR(__xludf.DUMMYFUNCTION("GOOGLETRANSLATE(I19,""zh_HANT"",""zh_HANS"")"),"做事万无一失") | K19: =F19
A20: CHARACTERISTIC_SPA-3 | B20: Often lost in thought | C20: 考え事が 多い | D20: Souvent dans la lune | E20: Ist oft in Gedanken | F20: A menudo está en Babia | G20: Si perde nel suo mondo | H20: 걱정거리가 많음 | I20: 經常思考 | J20: =IFERROR(__xludf.DUMMYFUNCTION("GOOGLETRANSLATE(I20,""zh_HANT"",""zh_HANS"")"),"经常思考") | K20: Vive en su propio mundo.
A21: CHARACTERISTIC_SPA-4 | B21: Very finicky | C21: とても きちょうめん | D21: Très particulier | E21: Ist sehr pedantisch | F21: Muy melindroso | G21: È molto esigente | H21: 매우 꼼꼼함 | I21: 一絲不苟 | J21: =IFERROR(__xludf.DUMMYFUNCTION("GOOGLETRANSLATE(I21,""zh_HANT"",""zh_HANS"")"),"一丝不苟") | K21: Es muy exigente.
A22: CHARACTERISTIC_SPD-0 | B22: Strong willed | C22: 気が 強い | D22: Très volontaire | E22: Besitzt einen starken Willen | F22: Voluntarioso | G22: Sa il fatto suo | H22: 기가 센 성격임 | I22: 性格強勢 | J22: =IFERROR(__xludf.DUMMYFUNCTION("GOOGLETRANSLATE(I22,""zh_HANT"",""zh_HANS"")"),"性格强势") | K22: =F22
A23: CHARACTERISTIC_SPD-1 | B23: Somewhat vain | C23: ちょっぴり みえっぱり | D23: Un peu vaniteux | E23: Ist etwas eitel | F23: Es algo orgulloso | G23: È abbastanza superficiale | H23: 조금 겉치레를 좋아함 | I23: 有一點點愛慕虛榮 | J23: =IFERROR(__xludf.DUMMYFUNCTION("GOOGLETRANSLATE(I23,""zh_HANT"",""zh_HANS"")"),"有一点点爱慕虚荣") | K23: Es un poco arrogante.
A24: CHARACTERISTIC_SPD-2 | B24: Strongly defiant | C24: 負けん気が 強い | D24: Esprit rebelle | E24: Ist sehr aufsässig | F24: Muy insolente | G24: È molto insolente | H24: 오기가 센 성격임 | I24: 爭強好勝 | J24: =IFERROR(__xludf.DUMMYFUNCTION("GOOGLETRANSLATE(I24,""zh_HANT"",""zh_HANS"")"),"争强好胜") | K24: =F24
A25: CHARACTERISTIC_SPD-3 | B25: Hates to lose | C25: 負けず嫌い | D25: A horreur de perdre | E25: Hasst Niederlagen | F25: Odia perder | G25: Non sopporta perdere | H25: 지기 싫어함 | I25: 不服輸 | J25: =IFERROR(__xludf.DUMMYFUNCTION("GOOGLETRANSLATE(I25,""zh_HANT"",""zh_HANS"")"),"不服输") | K25: =F25
A26: CHARACTERISTIC_SPD-4 | B26: Somewhat stubborn | C26: ちょっぴり 強情 | D26: Assez entêté | E26: Ist dickköpfig | F26: Un poco cabezota | G26: È un po' testardo | H26: 조금 고집통이임 | I26: 有一點點固執 | J26: =IFERROR(__xludf.DUMMYFUNCTION("GOOGLETRANSLATE(I26,""zh_HANT"",""zh_HANS"")"),"有一点点固执") | K26: Es un poco cabeza dura.
A27: CHARACTERISTIC_SPE-0 | B27: Likes to run | C27: 駆けっこが 好き | D27: Aime courir | E27: Liebt es zu rennen | F27: Le gusta correr | G27: Adora correre | H27: 약간 우쭐쟁이임 | I27: 喜歡比誰跑得快 | J27: =IFERROR(__xludf.DUMMYFUNCTION("GOOGLETRANSLATE(I27,""zh_HANT"",""zh_HANS"")"),"喜欢比谁跑得快") | K27: =F27
A28: CHARACTERISTIC_SPE-1 | B28: Alert to sounds | C28: 物音に 敏感 | D28: Attentif aux sons | E28: Achtet auf Geräusche | F28: Siempre tiene el oído alerta | G28: Fa attenzione ai suoni | H28: 주위 소리에 민감함 | I28: 對聲音敏感 | J28: =IFERROR(__xludf.DUMMYFUNCTION("GOOGLETRANSLATE(I28,""zh_HANT"",""zh_HANS"")"),"对声音敏感") | K28: =F28
A29: CHARACTERISTIC_SPE-2 | B29: Impetuous and silly | C29: おっちょこちょい | D29: Bête et impulsif | E29: Ist ungestüm und einfältig | F29: Impetuoso y bobo | G29: È irruente e semplice | H29: 촐랑대는 성격임 | I29: 冒冒失失 | J29: =I29 | K29: =F29
A30: CHARACTERISTIC_SPE-3 | B30: Somewhat of a clown | C30: すこし おっ調子者 | D30: Aime faire le pitre | E30: Ist ein bisschen albern | F30: Es un poco payaso | G30: È una specie di buffone | H30: 약간 우쭐쟁이임 | I30: 有點容易得意忘形 | J30: =IFERROR(__xludf.DUMMYFUNCTION("GOOGLETRANSLATE(I30,""zh_HANT"",""zh_HANS"")"),"有点容易得意忘形") | K30: =F30
A31: CHARACTERISTIC_SPE-4 | B31: Quick to flee | C31: 逃げるのが はやい | D31: Fuit rapidement | E31: Flüchtet schnell | F31: Huye rápido | G31: Sa fuggire velocemente | H31: 도망에는 선수임 | I31: 逃得快 | J31: =I31 | K31: =F31

Sheet Items
A1: =Pokemon!A1 | B1: =Pokemon!B1 | C1: =Pokemon!C1 | D1: =Pokemon!D1 | E1: =Pokemon!E1 | F1: =Pokemon!F1 | G1: =Pokemon!G1 | H1: =Pokemon!H1 | ... K1: =Pokemon!K1
A2: =CONCATENATE("NAME_ITEM_", SUBSTITUTE(UPPER(B2), " ", "")) | B2: Potion | C2: キズぐすり | D2: =B2 | E2: Trank | F2: Poción | G2: Pozione | H2: 상처약 | I2: 傷藥 | J2: =IFERROR(__xludf.DUMMYFUNCTION("GOOGLETRANSLATE(I2,""zh_HANT"",""zh_HANS"")"),"伤药") | K2: =F2
A3: =CONCATENATE("NAME_ITEM_", SUBSTITUTE(UPPER(B3), " ", "")) | B3: Antidote | C3: どくけし | D3: =B3 | E3: Gegengift | F3: Antídoto | G3: Antidoto | H3: 해독제 | I3: 解毒藥 | J3: =IFERROR(__xludf.DUMMYFUNCTION("GOOGLETRANSLATE(I3,""zh_HANT"",""zh_HANS"")"),"解毒药") | K3: =F3
A4: =CONCATENATE("NAME_ITEM_", SUBSTITUTE(UPPER(B4), " ", "")) | B4: Burn Heal | C4: やけどなおし | D4: Anti-Brûle | E4: Feuerheiler | F4: Antiquemar | G4: Antiscottatura | H4: 화상치료제 | I4: 灼傷藥 | J4: =IFERROR(__xludf.DUMMYFUNCTION("GOOGLETRANSLATE(I4,""zh_HANT"",""zh_HANS"")"),"灼伤药") | K4: =F4
A5: =CONCATENATE("NAME_ITEM_", SUBSTITUTE(UPPER(B5), " ", "")) | B5: Ice Heal | C5: こおりなおし | D5: Anti-Gel | E5: Eisheiler | F5: Antihielo | G5: Antigelo | H5: 얼음상태치료제 | I5: 解凍藥 | J5: =IFERROR(__xludf.DUMMYFUNCTION("GOOGLETRANSLATE(I5,""zh_HANT"",""zh_HANS"")"),"解冻药") | K5: =F5
A6: =CONCATENATE("NAME_ITEM_", SUBSTITUTE(UPPER(B6), " ", "")) | B6: Awakening | C6: ねむけざまし | D6: Réveil | E6: Aufwecker | F6: Despertar | G6: Sveglia | H6: 잠깨는약 | I6: 解眠藥 | J6: =IFERROR(__xludf.DUMMYFUNCTION("GOOGLETRANSLATE(I6,""zh_HANT"",""zh_HANS"")"),"解眠药") | K6: =F6
A7: =CONCATENATE("NAME_ITEM_", SUBSTITUTE(UPPER(B7), " ", "")) | B7: Paralyze Heal | C7: まひなおし | D7: Anti-Para | E7: Para-Heiler | F7: Antiparalizador | G7: Antiparalisi | H7: 마비치료제 | I7: 解麻藥 | J7: =IFERROR(__xludf.DUMMYFUNCTION("GOOGLETRANSLATE(I7,""zh_HANT"",""zh_HANS"")"),"解麻药") | K7: =F7
A8: =CONCATENATE("NAME_ITEM_", SUBSTITUTE(UPPER(B8), " ", "")) | B8: Full Restore | C8: かいふくのくすり | D8: Guérison | E8: Top-Genesung | F8: Restaurar Todo | G8: Ricarica totale | H8: 회복약 | I8: 全復藥 | J8: =IFERROR(__xludf.DUMMYFUNCTION("GOOGLETRANSLATE(I8,""zh_HANT"",""zh_HANS"")"),"全复药") | K8: =F8
A9: =CONCATENATE("NAME_ITEM_", SUBSTITUTE(UPPER(B9), " ", "")) | B9: Max Potion | C9: まんたんのくすり | D9: Potion Max | E9: Top-Trank | F9: Poción Máxima | G9: =CONCATENATE(G2," Max") | H9: 풀회복약 | I9: 全滿藥 | J9: =IFERROR(__xludf.DUMMYFUNCTION("GOOGLETRANSLATE(I9,""zh_HANT"",""zh_HANS"")"),"全满药") | K9: =F9
A10: =CONCATENATE("NAME_ITEM_", SUBSTITUTE(UPPER(B10), " ", "")) | B10: Hyper Potion | C10: =CONCATENATE("すごい",C2) | D10: =B10 | E10: Hypertrank | F10: Hiperpoción | G10: Iperpozione | H10: 고급상처약 | I10: 厲害傷藥 | J10: =IFERROR(__xludf.DUMMYFUNCTION("GOOGLETRANSLATE(I10,""zh_HANT"",""zh_HANS"")"),"厉害伤药") | K10: =F10
A11: =CONCATENATE("NAME_ITEM_", SUBSTITUTE(UPPER(B11), " ", "")) | B11: Super Potion | C11: =CONCATENATE("いい",C2) | D11: =B11 | E11: Supertrank | F11: Superpoción | G11: Superpozione | H11: 좋은상처약 | I11: 好傷藥 | J11: =IFERROR(__xludf.DUMMYFUNCTION("GOOGLETRANSLATE(I11,""zh_HANT"",""zh_HANS"")"),"好伤药") | K11: =F11
A12: =CONCATENATE("NAME_ITEM_", SUBSTITUTE(UPPER(B12), " ", "")) | B12: Full Heal | C12: なんでもなおし | D12: Total Soin | E12: Hyperheiler | F12: Cura Total | G12: Cura totale | H12: 만병통치약 | I12: 萬靈藥 | J12: =IFERROR(__xludf.DUMMYFUNCTION("GOOGLETRANSLATE(I12,""zh_HANT"",""zh_HANS"")"),"万灵药") | K12: =F12
A13: =CONCATENATE("NAME_ITEM_", SUBSTITUTE(UPPER(B13), " ", "")) | B13: Revive | C13: げんきのかけら | D13: Rappel | E13: Beleber | F13: Revivir | G13: Revitalizzante | H13: 기력의조각 | I13: 活力碎片 | J13: =I13 | K13: =F13
A14: =CONCATENATE("NAME_ITEM_", SUBSTITUTE(UPPER(B14), " ", "")) | B14: Max Revive | C14: げんきのかたまり | D14: Rappel Max | E14: =CONCATENATE("Top-",E13) | F14: Revivir Máximo | G14: Revitalizz. Max | H14: 기력의덩어리 | I14: 活力塊 | J14: =IFERROR(__xludf.DUMMYFUNCTION("GOOGLETRANSLATE(I14,""zh_HANT"",""zh_HANS"")"),"活力块") | K14: =F14
A15: =CONCATENATE("NAME_ITEM_", SUBSTITUTE(UPPER(B15), " ", "")) | B15: Fresh Water | C15: おいしみず | D15: Eau Fraiche | E15: Tafelwasser | F15: Agua Fresca | G15: Acqua Fresca | H15: 맛있는물 | I15: 美味之水 | J15: =I15 | K15: =F15
A16: =CONCATENATE("NAME_ITEM_", SUBSTITUTE(UPPER(B16), " ", "")) | B16: Soda Pop | C16: サイコソーダ | D16: Soda Cool | E16: Sprudel | F16: Refresco | G16: Gassora | H16: 미네랄사이다 | I16: 勁爽汽水 | J16: =IFERROR(__xludf.DUMMYFUNCTION("GOOGLETRANSLATE(I16,""zh_HANT"",""zh_HANS"")"),"劲爽汽水") | K16: =F16
A17: =CONCATENATE("NAME_ITEM_", SUBSTITUTE(UPPER(B17), " ", "")) | B17: Lemonade | C17: ミックスオレ | D17: Limonade | E17: =D17 | F17: Limonada | G17: Lemonsucco | H17: 후르츠밀크 | I17: 果汁牛奶 | J17: =I17 | K17: =F17
A18: =CONCATENATE("NAME_ITEM_", SUBSTITUTE(UPPER(B18), " ", "")) | B18: Ether | C18: ピーピーエイド | D18: Huile | E18: Äther | F18: Éter | G18: Etere | H18: ＰＰ에이드 | I18: ＰＰ單項小補劑 | J18: =IFERROR(__xludf.DUMMYFUNCTION("GOOGLETRANSLATE(I18,""zh_HANT"",""zh_HANS"")"),"ＰＰ单项小补剂") | K18: =F18
A19: =CONCATENATE("NAME_ITEM_", SUBSTITUTE(UPPER(B19), " ", "")) | B19: Max Ether | C19: ピーピーリカバー | D19: Huile Max | E19: =CONCATENATE("Top-",E18) | F19: Éter Máximo | G19: =CONCATENATE(G18," Max") | H19: ＰＰ회복 | I19: ＰＰ單項全補劑 | J19: =IFERROR(__xludf.DUMMYFUNCTION("GOOGLETRANSLATE(I19,""zh_HANT"",""zh_HANS"")"),"ＰＰ单项全补剂") | K19: =F19
A20: =CONCATENATE("NAME_ITEM_", SUBSTITUTE(UPPER(B20), " ", "")) | B20: Elixir | C20: ピーピーエイダー | D20: Élixir | E20: Elixier | F20: Elixir | G20: Elisir | H20: ＰＰ에이더 | I20: ＰＰ多項小補劑 | J20: =IFERROR(__xludf.DUMMYFUNCTION("GOOGLETRANSLATE(I20,""zh_HANT"",""zh_HANS"")"),"ＰＰ多项小补剂") | K20: =F20
A21: =CONCATENATE("NAME_ITEM_", SUBSTITUTE(UPPER(B21), " ", "")) | B21: Max Elixir | C21: ピーピーマックス | D21: =CONCATENATE(D20," Max") | E21: =CONCATENATE("Top-",E20) | F21: Elixir Máximo | G21: =CONCATENATE(G20," Max") | H21: ＰＰ맥스 | I21: ＰＰ多項全補劑 | J21: =IFERROR(__xludf.DUMMYFUNCTION("GOOGLETRANSLATE(I21,""zh_HANT"",""zh_HANS"")"),"ＰＰ多项全补剂") | K21: =F21
A22: =CONCATENATE("NAME_ITEM_", SUBSTITUTE(UPPER(B22), " ", "")) | B22: HP Up | C22: マックスアップ | D22: PV Plus | E22: KP-Plus | F22: Más PS | G22: PS-Su | H22: 맥스업 | I22: ＨＰ增強劑 | J22: =IFERROR(__xludf.DUMMYFUNCTION("GOOGLETRANSLATE(I22,""zh_HANT"",""zh_HANS"")"),"ＨＰ增强剂") | K22: =F22
A23: =CONCATENATE("NAME_ITEM_", SUBSTITUTE(UPPER(B23), " ", "")) | B23: Protein | C23: タウリン | D23: Protéine | E23: =B23 | F23: Proteína | G23: Proteina | H23: 타우린 | I23: 攻擊增強劑 | J23: =IFERROR(__xludf.DUMMYFUNCTION("GOOGLETRANSLATE(I23,""zh_HANT"",""zh_HANS"")"),"攻击增强剂") | K23: =F23
A24: =CONCATENATE("NAME_ITEM_", SUBSTITUTE(UPPER(B24), " ", "")) | B24: Iron | C24: ブロムヘキシン | D24: Fer | E24: Eisen | F24: Hierro | G24: Ferro | H24: 사포닌 | I24: 防禦增強劑 | J24: =IFERROR(__xludf.DUMMYFUNCTION("GOOGLETRANSLATE(I24,""zh_HANT"",""zh_HANS"")"),"防御增强剂") | K24: =F24
A25: =CONCATENATE("NAME_ITEM_", SUBSTITUTE(UPPER(B25), " ", "")) | B25: Carbos | C25: インドメタシン | D25: =CONCATENATE(E25,"e") | E25: Carbon | F25: Carburante | G25: =F25 | H25: 알칼로이드 | I25: 速度增強劑 | J25: =IFERROR(__xludf.DUMMYFUNCTION("GOOGLETRANSLATE(I25,""zh_HANT"",""zh_HANS"")"),"速度增强剂") | K25: =F25
A26: =CONCATENATE("NAME_ITEM_", SUBSTITUTE(UPPER(B26), " ", "")) | B26: Calcium | C26: リゾチウム | D26: =B26 | E26: Kalzium | F26: Calcio | G26: =F26 | H26: 리보플라빈 | I26: 特攻增強劑 | J26: =IFERROR(__xludf.DUMMYFUNCTION("GOOGLETRANSLATE(I26,""zh_HANT"",""zh_HANS"")"),"特攻增强剂") | K26: =F26
A27: =CONCATENATE("NAME_ITEM_", SUBSTITUTE(UPPER(B27), " ", "")) | B27: Rare Candy | C27: ふしぎなアメ | D27: Super Bonbon | E27: Sonderbonbon | F27: Carameloraro | G27: Caramella roro | H27: 이상한사탕 | I27: 神奇糖果 | J27: =I27 | K27: =F27
A28: =CONCATENATE("NAME_ITEM_", SUBSTITUTE(UPPER(B28), " ", "")) | B28: PP Up | C28: ポイントアップ | D28: PP Plus | E28: AP-Plus | F28: Más PP | G28: PP-Su | H28: 포인트업 | I28: ＰＰ提升劑 | J28: =IFERROR(__xludf.DUMMYFUNCTION("GOOGLETRANSLATE(I28,""zh_HANT"",""zh_HANS"")"),"ＰＰ提升剂") | K28: =F28
A29: =CONCATENATE("NAME_ITEM_", SUBSTITUTE(UPPER(B29), " ", "")) | B29: Moomoo Milk | C29: モーモーミルク | D29: Lait Meumeu | E29: Kuhmuh-Milch | F29: Leche Mu-Mu | G29: Latte Mumu | H29: 튼튼밀크 | I29: 哞哞鮮奶 | J29: =IFERROR(__xludf.DUMMYFUNCTION("GOOGLETRANSLATE(I29,""zh_HANT"",""zh_HANS"")"),"哞哞鲜奶") | K29: =F29
A30: =CONCATENATE("NAME_ITEM_", SUBSTITUTE(UPPER(B30), " ", "")) | B30: Energy Powder | C30: ちからのこな | D30: Poudre Énergie | E30: Energiestaub | F30: Polvo Energía | G30: Polvenergia | H30: 힘의가루 | I30: 元氣粉 | J30: =IFERROR(__xludf.DUMMYFUNCTION("GOOGLETRANSLATE(I30,""zh_HANT"",""zh_HANS"")"),"元气粉") | K30: =F30
A31: =CONCATENATE("NAME_ITEM_", SUBSTITUTE(UPPER(B31), " ", "")) | B31: Energy Root | C31: ちからのねっこ | D31: Racine Énergie | E31: Kraftwurzel | F31: Raíz Energía | G31: Radicenergia | H31: 힘의뿌리 | I31: 元氣根 | J31: =IFERROR(__xludf.DUMMYFUNCTION("GOOGLETRANSLATE(I31,""zh_HANT"",""zh_HANS"")"),"元气根") | K31: =F31
A32: =CONCATENATE("NAME_ITEM_", SUBSTITUTE(UPPER(B32), " ", "")) | B32: Heal Powder | C32: ばんおうごな | D32: Poudre Soin | E32: Heilpuder | F32: Polvo Curación | G32: Polvocura | H32: 만능가루 | I32: 萬能粉 | J32: =IFERROR(__xludf.DUMMYFUNCTION("GOOGLETRANSLATE(I32,""zh_HANT"",""zh_HANS"")"),"万能粉") | K32: =F32
A33: =CONCATENATE("NAME_ITEM_", SUBSTITUTE(UPPER(B33), " ", "")) | B33: Revival Herb | C33: ふっかつそう | D33: Herbe Rappel | E33: Vitalkraut | F33: Hierba Revivir | G33: Vitalerba | H33: 부활초 | I33: 復活草 | J33: =IFERROR(__xludf.DUMMYFUNCTION("GOOGLETRANSLATE(I33,""zh_HANT"",""zh_HANS"")"),"复活草") | K33: =F33
A34: =CONCATENATE("NAME_ITEM_", SUBSTITUTE(UPPER(B34), " ", "")) | B34: Berry Juice | C34: きのみジュース | D34: Jus de Baie | E34: Beerensaft | F34: Jugo de Bayas | G34: Succodibacca | H34: 나무열매쥬스 | I34: 樹果汁 | J34: =IFERROR(__xludf.DUMMYFUNCTION("GOOGLETRANSLATE(I34,""zh_HANT"",""zh_HANS"")"),"树果汁") | K34: =F34
A35: =CONCATENATE("NAME_ITEM_", SUBSTITUTE(UPPER(B35), " ", "")) | B35: Sacred Ash | C35: せいなるはい | D35: Cendre Sacrée | E35: Zauberasche | F35: Ceniza Sagrada | G35: Ceneremagica | H35: 성스러운분말 | I35: 聖灰 | J35: =IFERROR(__xludf.DUMMYFUNCTION("GOOGLETRANSLATE(I35,""zh_HANT"",""zh_HANS"")"),"圣灰") | K35: =F35
A36: =CONCATENATE("NAME_ITEM_", SUBSTITUTE(UPPER(B36), " ", "")) | B36: Rage Candy Bar | C36: いかりまんじゅう | D36: Bonbon Rage | E36: Wutkeks | F36: Caramelo Furia | G36: Iramella | H36: 분노의호두과자 | I36: 憤怒饅頭 | J36: =IFERROR(__xludf.DUMMYFUNCTION("GOOGLETRANSLATE(I36,""zh_HANT"",""zh_HANS"")"),"愤怒馒头") | K36: =F36
A37: =CONCATENATE("NAME_ITEM_", SUBSTITUTE(UPPER(B37), " ", "")) | B37: Lava Cookie | C37: ふえんせんべい | D37: =B37 | E37: Lavakeks | F37: Galleta Lava | G37: Lavottino | H37: 용암전병 | I37: 釜炎仙貝 | J37: =IFERROR(__xludf.DUMMYFUNCTION("GOOGLETRANSLATE(I37,""zh_HANT"",""zh_HANS"")"),"釜炎仙贝") | K37: =F37
A38: =CONCATENATE("NAME_ITEM_", SUBSTITUTE(UPPER(B38), " ", "")) | B38: Zinc | C38: キトサン | D38: Zinc | E38: Zink | F38: Zinc | G38: =CONCATENATE(B38,"o") | H38: 키토산 | I38: 特防增強劑 | J38: =IFERROR(__xludf.DUMMYFUNCTION("GOOGLETRANSLATE(I38,""zh_HANT"",""zh_HANS"")"),"特防增强剂") | K38: =F38
A39: =CONCATENATE("NAME_ITEM_", SUBSTITUTE(UPPER(B39), " ", "")) | B39: PP Max | C39: ポイントマックス | D39: =B39 | E39: AP-Top | F39: PP Máximos | G39: PP-Max | H39: 포인트맥스 | I39: ＰＰ極限提升劑 | J39: =IFERROR(__xludf.DUMMYFUNCTION("GOOGLETRANSLATE(I39,""zh_HANT"",""zh_HANS"")"),"ＰＰ极限提升剂") | K39: =F39
A40: =CONCATENATE("NAME_ITEM_", SUBSTITUTE(UPPER(B40), " ", "")) | B40: Old Gateau | C40: もりのヨウカン | D40: Vieux Gâteau | E40: Spezialität | F40: Barrita Plus | G40: Dolce Gateau | H40: 숲의양갱 | I40: 森之羊羹 | J40: =I40 | K40: =F40
A41: =CONCATENATE("NAME_ITEM_", SUBSTITUTE(UPPER(B41), " ", "")) | B41: Sweet Heart | C41: ハートスイーツ | D41: Chococœur | E41: Herzkonfekt | F41: Corazón Dulce | G41: Dolcecuore | H41: 하트스위트 | I41: 心形甜點 | J41: =IFERROR(__xludf.DUMMYFUNCTION("GOOGLETRANSLATE(I41,""zh_HANT"",""zh_HANS"")"),"心形甜点") | K41: =F41
A42: =CONCATENATE("NAME_ITEM_", SUBSTITUTE(UPPER(B42), " ", "")) | B42: Health Feather | C42: たいりょくのハネ | D42: Plume Santé | E42: Heilfeder | F42: Pluma Vigor | G42: Piumsalute | H42: 체력날개 | I42: 體力之羽 | J42: =IFERROR(__xludf.DUMMYFUNCTION("GOOGLETRANSLATE(I42,""zh_HANT"",""zh_HANS"")"),"体力之羽") | K42: =F42
A43: =CONCATENATE("NAME_ITEM_", SUBSTITUTE(UPPER(B43), " ", "")) | B43: Muscle Feather | C43: きんりょくのハネ | D43: Plume Force | E43: Kraftfeder | F43: Pluma Músculo | G43: Piumpotenza | H43: 근력날개 | I43: 肌力之羽 | J43: =I43 | K43: =F43
A44: =CONCATENATE("NAME_ITEM_", SUBSTITUTE(UPPER(B44), " ", "")) | B44: Resist Feather | C44: ていこうのハネ | D44: Plume Armure | E44: Abwehrfeder | F44: Pluma Aguante | G44: Piumtutela | H44: 저항력날개 | I44: 抵抗之羽 | J44: =I44 | K44: =F44
A45: =CONCATENATE("NAME_ITEM_", SUBSTITUTE(UPPER(B45), " ", "")) | B45: Genius Feather | C45: ちりょくのハネ | D45: Plume Esprit | E45: Geniefeder | F45: Pluma Intelecto | G45: Piumingegno | H45: 지력날개 | I45: 智力之羽 | J45: =I45 | K45: =F45
A46: =CONCATENATE("NAME_ITEM_", SUBSTITUTE(UPPER(B46), " ", "")) | B46: Clever Feather | C46: せいしんのハネ | D46: Plume Mental | E46: Espritfeder | F46: Pluma Mente | G46: Piumintuito | H46: 정신력날개 | I46: 精神之羽 | J46: =I46 | K46: =F46
A47: =CONCATENATE("NAME_ITEM_", SUBSTITUTE(UPPER(B47), " ", "")) | B47: Swift Feather | C47: しゅんぱつのハネ | D47: Plume Sprint | E47: Flinkfeder | F47: Pluma Impetu | G47: Piumreazione | H47: 순발력날개 | I47: 瞬發之羽 | J47: =IFERROR(__xludf.DUMMYFUNCTION("GOOGLETRANSLATE(I47,""zh_HANT"",""zh_HANS"")"),"瞬发之羽") | K47: =F47
A48: =CONCATENATE("NAME_ITEM_", SUBSTITUTE(UPPER(B48), " ", "")) | B48: Casteliacone | C48: ヒウンアイス | D48: Glace Volute | E48: Stratos-Eis | F48: Porcehelado | G48: Conostropoli | H48: 구름아이스 | I48: 飛雲冰淇淋 | J48: =IFERROR(__xludf.DUMMYFUNCTION("GOOGLETRANSLATE(I48,""zh_HANT"",""zh_HANS"")"),"飞云冰淇淋") | K48: =F48
A49: =CONCATENATE("NAME_ITEM_", SUBSTITUTE(UPPER(B49), " ", "")) | B49: Ability Capsule | C49: とくせいカプセル | D49: Pilule Talent | E49: Fähigk.-Kapsel | F49: Cápsula Habilidad | G49: Cáps. Habilidad | H49: 특성캡슐 | I49: 特性膠囊 | J49: =IFERROR(__xludf.DUMMYFUNCTION("GOOGLETRANSLATE(I49,""zh_HANT"",""zh_HANS"")"),"特性胶囊") | K49: =F49
A50: =CONCATENATE("NAME_ITEM_", SUBSTITUTE(UPPER(B50), " ", "")) | B50: Lumiose Galette | C50: ミアレガレット | D50: Galette Illumis | E50: Illumina-Galette | F50: Crêpe Luminalia | G50: Pan di Lumi | H50: 미르갈레트 | I50: 密阿雷格雷派餅 | J50: =IFERROR(__xludf.DUMMYFUNCTION("GOOGLETRANSLATE(I50,""zh_HANT"",""zh_HANS"")"),"密阿雷格雷派饼") | K50: =F50
A51: =CONCATENATE("NAME_ITEM_", SUBSTITUTE(UPPER(B51), " ", "")) | B51: Shalour Sable | C51: シャラセブレ | D51: Sablé Yantreizh | E51: Yantara-Sablé | F51: Galleta Yantra | G51: Yantafrollino | H51: 사라사블레 | I51: 娑羅沙布蕾 | J51: =IFERROR(__xludf.DUMMYFUNCTION("GOOGLETRANSLATE(I51,""zh_HANT"",""zh_HANS"")"),"娑罗沙布蕾") | K51: =F51
A52: =CONCATENATE("NAME_ITEM_", SUBSTITUTE(UPPER(B52), " ", "")) | B52: Big Malasada | C52: おおきいマラサダ | D52: Malasada Maxi | E52: Maxi-Malasada | F52: =D52 | G52: =D52 | H52: 큰 말라사다 | I52: 大馬拉薩達 | J52: =IFERROR(__xludf.DUMMYFUNCTION("GOOGLETRANSLATE(I52,""zh_HANT"",""zh_HANS"")"),"大马拉萨达") | K52: =F52
A53: =CONCATENATE("NAME_ITEM_", SUBSTITUTE(UPPER(B53), " ", "")) | B53: Pewter Crunchies | C53: ニビあられ | D53: Crok'Argenta | E53: Marmoria-Kräcker | F53: Rokikos | G53: Plumbeosalatini | H53: 회색강정 | I53: 深灰米果 | J53: =I53 | K53: =F53
A54: =CONCATENATE("NAME_ITEM_", SUBSTITUTE(SUBSTITUTE(UPPER(B54), " ", ""), ".", "")) | B54: Exp. Candy XS | C54: けいかんアメＸＳ | D54: Bonbon Exp. XS | E54: EP-Bonbon XS | F54: Caramelo Exp. XS | G54: Caram. Exp. XS | H54: 경험사탕ＸＳ | I54: =IFERROR(__xludf.DUMMYFUNCTION("GOOGLETRANSLATE(J54,""zh_HANS"",""zh_HANT"")"),"經驗糖果ＸＳ") | J54: 经验糖果ＸＳ | K54: =F54
A55: =CONCATENATE("NAME_ITEM_", SUBSTITUTE(SUBSTITUTE(UPPER(B55), " ", ""), ".", "")) | B55: Exp. Candy S | C55: けいかんアメＳ | D55: Bonbon Exp. S | E55: EP-Bonbon S | F55: Caramelo Exp. S | G55: Caram. Exp. S | H55: 경험사탕Ｓ | I55: =IFERROR(__xludf.DUMMYFUNCTION("GOOGLETRANSLATE(J55,""zh_HANS"",""zh_HANT"")"),"經驗糖果Ｓ") | J55: 经验糖果Ｓ | K55: =F55
A56: =CONCATENATE("NAME_ITEM_", SUBSTITUTE(SUBSTITUTE(UPPER(B56), " ", ""), ".", "")) | B56: Exp. Candy M | C56: けいかんアメＭ | D56: Bonbon Exp. M | E56: EP-Bonbon M | F56: Caramelo Exp. M | G56: Caram. Exp. M | H56: 경험사탕Ｍ | I56: =IFERROR(__xludf.DUMMYFUNCTION("GOOGLETRANSLATE(J56,""zh_HANS"",""zh_HANT"")"),"經驗糖果Ｍ") | J56: 经验糖果Ｍ | K56: =F56
A57: =CONCATENATE("NAME_ITEM_", SUBSTITUTE(SUBSTITUTE(UPPER(B57), " ", ""), ".", "")) | B57: Exp. Candy L | C57: けいかんアメＬ | D57: Bonbon Exp. L | E57: EP-Bonbon L | F57: Caramelo Exp. L | G57: Caram. Exp. L | H57: 경험사탕Ｌ | I57: =IFERROR(__xludf.DUMMYFUNCTION("GOOGLETRANSLATE(J57,""zh_HANS"",""zh_HANT"")"),"經驗糖果Ｌ") | J57: 经验糖果Ｌ | K57: =F57
A58: =CONCATENATE("NAME_ITEM_", SUBSTITUTE(SUBSTITUTE(UPPER(B58), " ", ""), ".", "")) | B58: Exp. Candy XL | C58: けいかんアメＸＬ | D58: Bonbon Exp. XL | E58: EP-Bonbon XL | F58: Caramelo Exp. XL | G58: Caram. Exp. XL | H58: 경험사탕ＸＬ | I58: =IFERROR(__xludf.DUMMYFUNCTION("GOOGLETRANSLATE(J58,""zh_HANS"",""zh_HANT"")"),"經驗糖果ＸＬ") | J58: 经验糖果ＸＬ | K58: =F58
A59: =CONCATENATE("NAME_ITEM_", SUBSTITUTE(UPPER(B59), " ", "")) | B59: Dynamax Candy | C59: ダイマックスアメ | D59: Bonbon Dynamax | E59: Dynamax-Bonbon | F59: Caramelo Dinamax | G59: Caram. Dynamax | H59: 다이맥스사탕 | I59: =IFERROR(__xludf.DUMMYFUNCTION("GOOGLETRANSLATE(J59,""zh_HANS"",""zh_HANT"")"),"極鉅糖果") | J59: 极巨糖果 | K59: =F59
A60: =CONCATENATE("NAME_ITEM_", SUBSTITUTE(UPPER(B60), " ", "")) | B60: =CONCATENATE(Natures!B2, " Mint") | C60: =CONCATENATE(Natures!C2, "ミント") | D60: =CONCATENATE("Aromate ",Natures!D2) | E60: =CONCATENATE(Natures!E2, "-Minze") | F60: =CONCATENATE("Menta ",Natures!F2) | G60: =CONCATENATE("Menta ",Natures!G2) | H60: =CONCATENATE(Natures!H2, "민트") | I60: =CONCATENATE(Natures!I2, "薄荷") | J60: =CONCATENATE(Natures!J2, "薄荷") | K60: =F60
A61: =CONCATENATE("NAME_ITEM_", SUBSTITUTE(UPPER(B61), " ", "")) | B61: =CONCATENATE(Natures!B4, " Mint") | C61: =CONCATENATE(Natures!C4, "ミント") | D61: =CONCATENATE("Aromate ",Natures!D4) | E61: =CONCATENATE(Natures!E4, "-Minze") | F61: =CONCATENATE("Menta ",Natures!F4) | G61: =CONCATENATE("Menta ",Natures!G3) | H61: =CONCATENATE(Natures!H4, "민트") | I61: =CONCATENATE(Natures!I4, "薄荷") | J61: =CONCATENATE(Natures!J4, "薄荷") | K61: =F61
A62: =CONCATENATE("NAME_ITEM_", SUBSTITUTE(UPPER(B62), " ", "")) | B62: =CONCATENATE(Natures!B5, " Mint") | C62: =CONCATENATE(Natures!C5, "ミント") | D62: =CONCATENATE("Aromate ",Natures!D5) | E62: =CONCATENATE(Natures!E5, "-Minze") | F62: =CONCATENATE("Menta ",Natures!F5) | G62: =CONCATENATE("Menta ",Natures!G4) | H62: =CONCATENATE(Natures!H5, "민트") | I62: =CONCATENATE(Natures!I5, "薄荷") | J62: =CONCATENATE(Natures!J5, "薄荷") | K62: =F62
A63: =CONCATENATE("NAME_ITEM_", SUBSTITUTE(UPPER(B63), " ", "")) | B63: =CONCATENATE(Natures!B6, " Mint") | C63: =CONCATENATE(Natures!C6, "ミント") | D63: =CONCATENATE("Aromate ",Natures!D6) | E63: =CONCATENATE(Natures!E6, "-Minze") | F63: =CONCATENATE("Menta ",Natures!F6) | G63: =CONCATENATE("Menta ",Natures!G5) | H63: =CONCATENATE(Natures!H6, "민트") | I63: =CONCATENATE(Natures!I6, "薄荷") | J63: =CONCATENATE(Natures!J6, "薄荷") | K63: =F63
A64: =CONCATENATE("NAME_ITEM_", SUBSTITUTE(UPPER(B64), " ", "")) | B64: =CONCATENATE(Natures!B7, " Mint") | C64: =CONCATENATE(Natures!C7, "ミント") | D64: =CONCATENATE("Aromate ",Natures!D7) | E64: =CONCATENATE(Natures!E7, "-Minze") | F64: =CONCATENATE("Menta ",Natures!F7) | G64: =CONCATENATE("Menta ",Natures!G6) | H64: =CONCATENATE(Natures!H7, "민트") | I64: =CONCATENATE(Natures!I7, "薄荷") | J64: =CONCATENATE(Natures!J7, "薄荷") | K64: =F64
A65: =CONCATENATE("NAME_ITEM_", SUBSTITUTE(UPPER(B65), " ", "")) | B65: =CONCATENATE(Natures!B9, " Mint") | C65: =CONCATENATE(Natures!C9, "ミント") | D65: =CONCATENATE("Aromate ",Natures!D9) | E65: =CONCATENATE(Natures!E9, "-Minze") | F65: =CONCATENATE("Menta ",Natures!F9) | G65: =CONCATENATE("Menta ",Natures!G8) | H65: =CONCATENATE(Natures!H9, "민트") | I65: =CONCATENATE(Natures!I9, "薄荷") | J65: =CONCATENATE(Natures!J9, "薄荷") | K65: =F65
A66: =CONCATENATE("NAME_ITEM_", SUBSTITUTE(UPPER(B66), " ", "")) | B66: =CONCATENATE(Natures!B11, " Mint") | C66: =CONCATENATE(Natures!C11, "ミント") | D66: =CONCATENATE("Aromate ",Natures!D11) | E66: =CONCATENATE(Natures!E11, "-Minze") | F66: =CONCATENATE("Menta ",Natures!F11) | G66: =CONCATENATE("Menta ",Natures!G10) | H66: =CONCATENATE(Natures!H11, "민트") | I66: =CONCATENATE(Natures!I11, "薄荷") | J66: =CONCATENATE(Natures!J11, "薄荷") | K66: =F66
A67: =CONCATENATE("NAME_ITEM_", SUBSTITUTE(UPPER(B67), " ", "")) | B67: =CONCATENATE(Natures!B12, " Mint") | C67: =CONCATENATE(Natures!C12, "ミント") | D67: =CONCATENATE("Aromate ",Natures!D12) | E67: =CONCATENATE(Natures!E12, "-Minze") | F67: =CONCATENATE("Menta ",Natures!F12) | G67: =CONCATENATE("Menta ",Natures!G11) | H67: =CONCATENATE(Natures!H12, "민트") | I67: =CONCATENATE(Natures!I12, "薄荷") | J67: =CONCATENATE(Natures!J12, "薄荷") | K67: =F67
A68: =CONCATENATE("NAME_ITEM_", SUBSTITUTE(UPPER(B68), " ", "")) | B68: =CONCATENATE(Natures!B13, " Mint") | C68: =CONCATENATE(Natures!C13, "ミント") | D68: =CONCATENATE("Aromate ",Natures!D13) | E68: =CONCATENATE(Natures!E13, "-Minze") | F68: =CONCATENATE("Menta ",Natures!F13) | G68: =CONCATENATE("Menta ",Natures!G12) | H68: =CONCATENATE(Natures!H13, "민트") | I68: =CONCATENATE(Natures!I13, "薄荷") | J68: =CONCATENATE(Natures!J13, "薄荷") | K68: =F68
A69: =CONCATENATE("NAME_ITEM_", SUBSTITUTE(UPPER(B69), " ", "")) | B69: =CONCATENATE(Natures!B14, " Mint") | C69: =CONCATENATE(Natures!C14, "ミント") | D69: =CONCATENATE("Aromate ",Natures!D14) | E69: =CONCATENATE(Natures!E14, "-Minze") | F69: =CONCATENATE("Menta ",Natures!F14) | G69: =CONCATENATE("Menta ",Natures!G13) | H69: =CONCATENATE(Natures!H14, "민트") | I69: =CONCATENATE(Natures!I14, "薄荷") | J69: =CONCATENATE(Natures!J14, "薄荷") | K69: =F69
A70: =CONCATENATE("NAME_ITEM_", SUBSTITUTE(UPPER(B70), " ", "")) | B70: =CONCATENATE(Natures!B15, " Mint") | C70: =CONCATENATE(Natures!C15, "ミント") | D70: =CONCATENATE("Aromate ",Natures!D15) | E70: =CONCATENATE(Natures!E15, "-Minze") | F70: =CONCATENATE("Menta ",Natures!F15) | G70: =CONCATENATE("Menta ",Natures!G14) | H70: =CONCATENATE(Natures!H15, "민트") | I70: =CONCATENATE(Natures!I15, "薄荷") | J70: =CONCATENATE(Natures!J15, "薄荷") | K70: =F70
A71: =CONCATENATE("NAME_ITEM_", SUBSTITUTE(UPPER(B71), " ", "")) | B71: =CONCATENATE(Natures!B16, " Mint") | C71: =CONCATENATE(Natures!C16, "ミント") | D71: =CONCATENATE("Aromate ",Natures!D16) | E71: =CONCATENATE(Natures!E16, "-Minze") | F71: =CONCATENATE("Menta ",Natures!F16) | G71: =CONCATENATE("Menta ",Natures!G15) | H71: =CONCATENATE(Natures!H16, "민트") | I71: =CONCATENATE(Natures!I16, "薄荷") | J71: =CONCATENATE(Natures!J16, "薄荷") | K71: =F71
A72: =CONCATENATE("NAME_ITEM_", SUBSTITUTE(UPPER(B72), " ", "")) | B72: =CONCATENATE(Natures!B17, " Mint") | C72: =CONCATENATE(Natures!C17, "ミント") | D72: =CONCATENATE("Aromate ",Natures!D17) | E72: =CONCATENATE(Natures!E17, "-Minze") | F72: =CONCATENATE("Menta ",Natures!F17) | G72: =CONCATENATE("Menta ",Natures!G16) | H72: =CONCATENATE(Natures!H17, "민트") | I72: =CONCATENATE(Natures!I17, "薄荷") | J72: =CONCATENATE(Natures!J17, "薄荷") | K72: =F72
A73: =CONCATENATE("NAME_ITEM_", SUBSTITUTE(UPPER(B73), " ", "")) | B73: =CONCATENATE(Natures!B18, " Mint") | C73: =CONCATENATE(Natures!C18, "ミント") | D73: =CONCATENATE("Aromate ",Natures!D18) | E73: =CONCATENATE(Natures!E18, "-Minze") | F73: =CONCATENATE("Menta ",Natures!F18) | G73: =CONCATENATE("Menta ",Natures!G17) | H73: =CONCATENATE(Natures!H18, "민트") | I73: =CONCATENATE(Natures!I18, "薄荷") | J73: =CONCATENATE(Natures!J18, "薄荷") | K73: =F73
A74: =CONCATENATE("NAME_ITEM_", SUBSTITUTE(UPPER(B74), " ", "")) | B74: =CONCATENATE(Natures!B19, " Mint") | C74: =CONCATENATE(Natures!C19, "ミント") | D74: =CONCATENATE("Aromate ",Natures!D19) | E74: =CONCATENATE(Natures!E19, "-Minze") | F74: =CONCATENATE("Menta ",Natures!F19) | G74: =CONCATENATE("Menta ",Natures!G18) | H74: =CONCATENATE(Natures!H19, "민트") | I74: =CONCATENATE(Natures!I19, "薄荷") | J74: =CONCATENATE(Natures!J19, "薄荷") | K74: =F74
A75: =CONCATENATE("NAME_ITEM_", SUBSTITUTE(UPPER(B75), " ", "")) | B75: =CONCATENATE(Natures!B20, " Mint") | C75: =CONCATENATE(Natures!C20, "ミント") | D75: =CONCATENATE("Aromate ",Natures!D20) | E75: =CONCATENATE(Natures!E20, "-Minze") | F75: =CONCATENATE("Menta ",Natures!F20) | G75: =CONCATENATE("Menta ",Natures!G19) | H75: =CONCATENATE(Natures!H20, "민트") | I75: =CONCATENATE(Natures!I20, "薄荷") | J75: =CONCATENATE(Natures!J20, "薄荷") | K75: =F75
A76: =CONCATENATE("NAME_ITEM_", SUBSTITUTE(UPPER(B76), " ", "")) | B76: =CONCATENATE(Natures!B22, " Mint") | C76: =CONCATENATE(Natures!C22, "ミント") | D76: =CONCATENATE("Aromate ",Natures!D22) | E76: =CONCATENATE(Natures!E22, "-Minze") | F76: =CONCATENATE("Menta ",Natures!F22) | G76: =CONCATENATE("Menta ",Natures!G21) | H76: =CONCATENATE(Natures!H22, "민트") | I76: =CONCATENATE(Natures!I22, "薄荷") | J76: =CONCATENATE(Natures!J22, "薄荷") | K76: =F76
A77: =CONCATENATE("NAME_ITEM_", SUBSTITUTE(UPPER(B77), " ", "")) | B77: =CONCATENATE(Natures!B23, " Mint") | C77: =CONCATENATE(Natures!C23, "ミント") | D77: =CONCATENATE("Aromate ",Natures!D23) | E77: =CONCATENATE(Natures!E23, "-Minze") | F77: =CONCATENATE("Menta ",Natures!F23) | G77: =CONCATENATE("Menta ",Natures!G22) | H77: =CONCATENATE(Natures!H23, "민트") | I77: =CONCATENATE(Natures!I23, "薄荷") | J77: =CONCATENATE(Natures!J23, "薄荷") | K77: =F77
A78: =CONCATENATE("NAME_ITEM_", SUBSTITUTE(UPPER(B78), " ", "")) | B78: =CONCATENATE(Natures!B24, " Mint") | C78: =CONCATENATE(Natures!C24, "ミント") | D78: =CONCATENATE("Aromate ",Natures!D24) | E78: =CONCATENATE(Natures!E24, "-Minze") | F78: =CONCATENATE("Menta ",Natures!F24) | G78: =CONCATENATE("Menta ",Natures!G23) | H78: =CONCATENATE(Natures!H24, "민트") | I78: =CONCATENATE(Natures!I24, "薄荷") | J78: =CONCATENATE(Natures!J24, "薄荷") | K78: =F78
A79: =CONCATENATE("NAME_ITEM_", SUBSTITUTE(UPPER(B79), " ", "")) | B79: =CONCATENATE(Natures!B25, " Mint") | C79: =CONCATENATE(Natures!C25, "ミント") | D79: =CONCATENATE("Aromate ",Natures!D25) | E79: =CONCATENATE(Natures!E25, "-Minze") | F79: =CONCATENATE("Menta ",Natures!F25) | G79: =CONCATENATE("Menta ",Natures!G24) | H79: =CONCATENATE(Natures!H25, "민트") | I79: =CONCATENATE(Natures!I25, "薄荷") | J79: =CONCATENATE(Natures!J25, "薄荷") | K79: =F79
A80: =CONCATENATE("NAME_ITEM_", SUBSTITUTE(UPPER(B80), " ", "")) | B80: =CONCATENATE(Natures!B26, " Mint") | C80: =CONCATENATE(Natures!C26, "ミント") | D80: =CONCATENATE("Aromate ",Natures!D26) | E80: =CONCATENATE(Natures!E26, "-Minze") | F80: =CONCATENATE("Menta ",Natures!F26) | G80: =CONCATENATE("Menta ",Natures!G25) | H80: =CONCATENATE(Natures!H26, "민트") | I80: =CONCATENATE(Natures!I26, "薄荷") | J80: =CONCATENATE(Natures!J26, "薄荷") | K80: =F80
A81: =CONCATENATE("NAME_ITEM_", SUBSTITUTE(UPPER(B81), " ", "")) | B81: Ability Patch | C81: とくせいパッチ | D81: Patch Talent | E81: Fähigk.-Pflaster | F81: Parche Habilidad | G81: Cerotto abilità | H81: 특성패치 | I81: 特性膏藥 | J81: =IFERROR(__xludf.DUMMYFUNCTION("GOOGLETRANSLATE(I81,""zh_HANT"",""zh_HANS"")"),"特性膏药") | K81: =F81
A82: =CONCATENATE("NAME_ITEM_", SUBSTITUTE(UPPER(B82), " ", "")) | B82: =CONCATENATE(Types!B2, " Tera Shard") | C82: =CONCATENATE("テラピース",Types!C2) | D82: =CONCATENATE("Téra-Éclat ",Types!D2) | E82: =CONCATENATE("Tera-Stück (",Types!E2, ")") | F82: =CONCATENATE("Teralito ",Types!F2) | G82: =CONCATENATE("Teralite ",Types!G2) | H82: =CONCATENATE("테라피스 ",Types!H2) | I82: =CONCATENATE(Types!I2, "太晶碎塊") | J82: =CONCATENATE(Types!J2, "太晶碎块") | K82: =F82
A83: =CONCATENATE("NAME_ITEM_", SUBSTITUTE(UPPER(B83), " ", "")) | B83: =CONCATENATE(Types!B3, " Tera Shard") | C83: =CONCATENATE("テラピース",Types!C3) | D83: =CONCATENATE("Téra-Éclat ",Types!D3) | E83: =CONCATENATE("Tera-Stück (",Types!E3, ")") | F83: =CONCATENATE("Teralito ",Types!F3) | G83: =CONCATENATE("Teralite ",Types!G3) | H83: =CONCATENATE("테라피스 ",Types!H3) | I83: =CONCATENATE(Types!I3, "太晶碎塊") | J83: =CONCATENATE(Types!J3, "太晶碎块") | K83: =F83
A84: =CONCATENATE("NAME_ITEM_", SUBSTITUTE(UPPER(B84), " ", "")) | B84: =CONCATENATE(Types!B4, " Tera Shard") | C84: =CONCATENATE("テラピース",Types!C4) | D84: =CONCATENATE("Téra-Éclat ",Types!D4) | E84: =CONCATENATE("Tera-Stück (",Types!E4, ")") | F84: =CONCATENATE("Teralito ",Types!F4) | G84: =CONCATENATE("Teralite ",Types!G4) | H84: =CONCATENATE("테라피스 ",Types!H4) | I84: =CONCATENATE(Types!I4, "太晶碎塊") | J84: =CONCATENATE(Types!J4, "太晶碎块") | K84: =F84
A85: =CONCATENATE("NAME_ITEM_", SUBSTITUTE(UPPER(B85), " ", "")) | B85: =CONCATENATE(Types!B5, " Tera Shard") | C85: =CONCATENATE("テラピース",Types!C5) | D85: =CONCATENATE("Téra-Éclat ",Types!D5) | E85: =CONCATENATE("Tera-Stück (",Types!E5, ")") | F85: =CONCATENATE("Teralito ",Types!F5) | G85: =CONCATENATE("Teralite ",Types!G5) | H85: =CONCATENATE("테라피스 ",Types!H5) | I85: =CONCATENATE(Types!I5, "太晶碎塊") | J85: =CONCATENATE(Types!J5, "太晶碎块") | K85: =F85
A86: =CONCATENATE("NAME_ITEM_", SUBSTITUTE(UPPER(B86), " ", "")) | B86: =CONCATENATE(Types!B6, " Tera Shard") | C86: =CONCATENATE("テラピース",Types!C6) | D86: =CONCATENATE("Téra-Éclat ",Types!D6) | E86: =CONCATENATE("Tera-Stück (",Types!E6, ")") | F86: =CONCATENATE("Teralito ",Types!F6) | G86: =CONCATENATE("Teralite ",Types!G6) | H86: =CONCATENATE("테라피스 ",Types!H6) | I86: =CONCATENATE(Types!I6, "太晶碎塊") | J86: =CONCATENATE(Types!J6, "太晶碎块") | K86: =F86
A87: =CONCATENATE("NAME_ITEM_", SUBSTITUTE(UPPER(B87), " ", "")) | B87: =CONCATENATE(Types!B7, " Tera Shard") | C87: =CONCATENATE("テラピース",Types!C7) | D87: =CONCATENATE("Téra-Éclat ",Types!D7) | E87: =CONCATENATE("Tera-Stück (",Types!E7, ")") | F87: =CONCATENATE("Teralito ",Types!F7) | G87: =CONCATENATE("Teralite ",Types!G7) | H87: =CONCATENATE("테라피스 ",Types!H7) | I87: =CONCATENATE(Types!I7, "太晶碎塊") | J87: =CONCATENATE(Types!J7, "太晶碎块") | K87: =F87
A88: =CONCATENATE("NAME_ITEM_", SUBSTITUTE(UPPER(B88), " ", "")) | B88: =CONCATENATE(Types!B8, " Tera Shard") | C88: =CONCATENATE("テラピース",Types!C8) | D88: =CONCATENATE("Téra-Éclat ",Types!D8) | E88: =CONCATENATE("Tera-Stück (",Types!E8, ")") | F88: =CONCATENATE("Teralito ",Types!F8) | G88: =CONCATENATE("Teralite ",Types!G8) | H88: =CONCATENATE("테라피스 ",Types!H8) | I88: =CONCATENATE(Types!I8, "太晶碎塊") | J88: =CONCATENATE(Types!J8, "太晶碎块") | K88: =F88
A89: =CONCATENATE("NAME_ITEM_", SUBSTITUTE(UPPER(B89), " ", "")) | B89: =CONCATENATE(Types!B9, " Tera Shard") | C89: =CONCATENATE("テラピース",Types!C9) | D89: =CONCATENATE("Téra-Éclat ",Types!D9) | E89: =CONCATENATE("Tera-Stück (",Types!E9, ")") | F89: =CONCATENATE("Teralito ",Types!F9) | G89: =CONCATENATE("Teralite ",Types!G9) | H89: =CONCATENATE("테라피스 ",Types!H9) | I89: =CONCATENATE(Types!I9, "太晶碎塊") | J89: =CONCATENATE(Types!J9, "太晶碎块") | K89: =F89
A90: =CONCATENATE("NAME_ITEM_", SUBSTITUTE(UPPER(B90), " ", "")) | B90: =CONCATENATE(Types!B10, " Tera Shard") | C90: =CONCATENATE("テラピース",Types!C10) | D90: =CONCATENATE("Téra-Éclat ",Types!D10) | E90: =CONCATENATE("Tera-Stück (",Types!E10, ")") | F90: =CONCATENATE("Teralito ",Types!F10) | G90: =CONCATENATE("Teralite ",Types!G10) | H90: =CONCATENATE("테라피스 ",Types!H10) | I90: =CONCATENATE(Types!I10, "太晶碎塊") | J90: =CONCATENATE(Types!J10, "太晶碎块") | K90: =F90
A91: =CONCATENATE("NAME_ITEM_", SUBSTITUTE(UPPER(B91), " ", "")) | B91: =CONCATENATE(Types!B11, " Tera Shard") | C91: =CONCATENATE("テラピース",Types!C11) | D91: =CONCATENATE("Téra-Éclat ",Types!D11) | E91: =CONCATENATE("Tera-Stück (",Types!E11, ")") | F91: =CONCATENATE("Teralito ",Types!F11) | G91: =CONCATENATE("Teralite ",Types!G11) | H91: =CONCATENATE("테라피스 ",Types!H11) | I91: =CONCATENATE(Types!I11, "太晶碎塊") | J91: =CONCATENATE(Types!J11, "太晶碎块") | K91: =F91
A92: =CONCATENATE("NAME_ITEM_", SUBSTITUTE(UPPER(B92), " ", "")) | B92: =CONCATENATE(Types!B12, " Tera Shard") | C92: =CONCATENATE("テラピース",Types!C12) | D92: =CONCATENATE("Téra-Éclat ",Types!D12) | E92: =CONCATENATE("Tera-Stück (",Types!E12, ")") | F92: =CONCATENATE("Teralito ",Types!F12) | G92: =CONCATENATE("Teralite ",Types!G12) | H92: =CONCATENATE("테라피스 ",Types!H12) | I92: =CONCATENATE(Types!I12, "太晶碎塊") | J92: =CONCATENATE(Types!J12, "太晶碎块") | K92: =F92
A93: =CONCATENATE("NAME_ITEM_", SUBSTITUTE(UPPER(B93), " ", "")) | B93: =CONCATENATE(Types!B13, " Tera Shard") | C93: =CONCATENATE("テラピース",Types!C13) | D93: =CONCATENATE("Téra-Éclat ",Types!D13) | E93: =CONCATENATE("Tera-Stück (",Types!E13, ")") | F93: =CONCATENATE("Teralito ",Types!F13) | G93: =CONCATENATE("Teralite ",Types!G13) | H93: =CONCATENATE("테라피스 ",Types!H13) | I93: =CONCATENATE(Types!I13, "太晶碎塊") | J93: =CONCATENATE(Types!J13, "太晶碎块") | K93: =F93
... A100: =CONCATENATE("NAME_ITEM_", SUBSTITUTE(UPPER(B100), " ", "")) | B100: =CONCATENATE(Types!B20, " Tera Shard") | C100: =CONCATENATE("テラピース",Types!C20) | D100: =CONCATENATE("Téra-Éclat ",Types!D20) | E100: =CONCATENATE("Tera-Stück (",Types!E20, ")") | F100: =CONCATENATE("Teralito ",Types!F20) | G100: =CONCATENATE("Teralite ",Types!G20) | H100: =CONCATENATE("테라피스 ",Types!H20) | I100: =CONCATENATE(Types!I20, "太晶碎塊") | J100: =CONCATENATE(Types!J20, "太晶碎块") | K100: =F100
A101: =CONCATENATE("NAME_ITEM_", SUBSTITUTE(UPPER(B101), " ", "")) | B101: Health Mochi | C101: たいりょくのもち | D101: Mochi Santé | E101: Heil-Mochi | F101: Mochi Vigor | G101: Mochi della salute | H101: 체력떡 | I101: 體力糬 | J101: 体力粘糕 | K101: =F101
A102: =CONCATENATE("NAME_ITEM_", SUBSTITUTE(UPPER(B102), " ", "")) | B102: Muscle Mochi | C102: きんりょくのもと | D102: Mochi Force | E102: Kraft-Mochi | F102: Mochi Músculo | G102: Mochi della potenza | H102: 근력떡 | I102: 肌力糬 | J102: 肌力粘糕 | K102: =F102
A103: =CONCATENATE("NAME_ITEM_", SUBSTITUTE(UPPER(B103), " ", "")) | B103: Resist Mochi | C103: ていこうのもと | D103: Mochi Armure | E103: Abwehr-Mochi | F103: Mochi Aguante | G103: Mochi della tutela | H103: 저항력떡 | I103: 抵抗糬 | J103: 抵抗粘糕 | K103: =F103
A104: =CONCATENATE("NAME_ITEM_", SUBSTITUTE(UPPER(B104), " ", "")) | B104: Genius Mochi | C104: ちりょくのもち | D104: Mochi Esprite | E104: Genie-Mochi | F104: Mochi Intelecto | G104: Mochi dell’ingegno | H104: 지력떡 | I104: 智力糬 | J104: 智力粘糕 | K104: =F104
A105: =CONCATENATE("NAME_ITEM_", SUBSTITUTE(UPPER(B105), " ", "")) | B105: Clever Mochi | C105: せいしんのもち | D105: Mochi Mental | E105: Esprit-Mochi | F105: Mochi Mente | G105: Mochi dell’intuito | H105: 정신력떡 | I105: 精神糬 | J105: 精神粘糕 | K105: =F105
A106: =CONCATENATE("NAME_ITEM_", SUBSTITUTE(UPPER(B106), " ", "")) | B106: Swift Mochi | C106: しゅんぱつのもち | D106: Mochi Sprint | E106: Flink-Mochi | F106: Mochi Ímpetu | G106: Mochi della reazione | H106: 순발력떡 | I106: 瞬發糬 | J106: 瞬发粘糕 | K106: =F106
...

Sheet Trainer Classes
A1: =Pokemon!A1 | B1: =Pokemon!B1 | C1: =Pokemon!C1 | D1: =Pokemon!D1 | E1: =Pokemon!E1 | F1: =Pokemon!F1 | G1: =Pokemon!G1 | H1: =Pokemon!H1 | ... J1: =Pokemon!J1
A2: NAME_TC_ACETRAINER-M | B2: Ace Trainer | C2: エリートトレーナー | D2: Topdresseur | E2: Ass-Trainer | F2: Entrenador guay | G2: Fantallenatore | H2: 엘리트트레이너 | I2: 精英訓練家 | J2: =IFERROR(__xludf.DUMMYFUNCTION("GOOGLETRANSLATE(I2,""zh_HANT"",""zh_HANS"")"),"精英训练家")
A3: NAME_TC_ACETRAINER-F | B3: =B2 | C3: =C2 | D3: =D2 | E3: =CONCATENATE(E2,"in") | F3: Entrenadora guay | G3: Fantallenatrice | H3: =H2 | I3: =I2 | J3: =J2
A4: =CONCATENATE("NAME_TC_", SUBSTITUTE(UPPER(B4), " ", "")) | B4: Beauty | C4: おとなのおねえさん | D4: Canon | E4: Schönheit | F4: Modelo | G4: Bellezza | H4: 아가씨 | I4: 大姐姐 | J4: =I4
A5: =CONCATENATE("NAME_TC_", SUBSTITUTE(UPPER(B5), " ", "")) | B5: Biker | C5: ぼうそうぞく | D5: Motard | E5: Rowdy | F5: Motorista | G5: Centauro | H5: 폭주족 | I5: =J5 | J5: 暴走族
A6: NAME_TC_BIRDKEEPER-M | B6: Bird Keeper | C6: とりつかい | D6: Ornithologue | E6: Vogel-Profi | F6: Ornitólogo | G6: Avicoltore | H6: 새 조련사 | I6: 養鳥人 | J6: =IFERROR(__xludf.DUMMYFUNCTION("GOOGLETRANSLATE(I6,""zh_HANT"",""zh_HANS"")"),"养鸟人")
A7: NAME_TC_BIRDKEEPER-F | B7: Bird Keeper | C7: とりつかい | D7: Ornithologue | E7: =E6 | F7: Ornitóloga | G7: Avicoltrice | H7: 새 조련사 | I7: 養鳥人 | J7: =IFERROR(__xludf.DUMMYFUNCTION("GOOGLETRANSLATE(I7,""zh_HANT"",""zh_HANS"")"),"养鸟人")
A8: =CONCATENATE("NAME_TC_", SUBSTITUTE(UPPER(B8), " ", "")) | B8: Black Belt | C8: カラテおう | D8: Judoka | E8: Schwarzgurt | F8: Karateka | G8: Citura Nera | H8: 태권왕 | I8: 空手道王 | J8: =I8
A9: =CONCATENATE("NAME_TC_", SUBSTITUTE(UPPER(B9), " ", "")) | B9: Bug Catcher | C9: むしとりしょうねん | D9: Scout | E9: Käfersammler | F9: Cazabichos | G9: Pigliamosche | H9: 곤충채집소년 | I9: 捕蟲少年 | J9: =IFERROR(__xludf.DUMMYFUNCTION("GOOGLETRANSLATE(I9,""zh_HANT"",""zh_HANS"")"),"捕虫少年")
A10: =CONCATENATE("NAME_TC_", SUBSTITUTE(UPPER(B10), " ", "")) | B10: Burglar | C10: かじばどろぼう | D10: Voleur | E10: Dieb | F10: Ladrón | G10: Scassinatore | H10: 불난집 전문털이범 | I10: 趁火打劫者 | J10: =I10
A11: =CONCATENATE("NAME_TC_", SUBSTITUTE(UPPER(B11), " ", "")) | B11: Camper | C11: キャンプボーイ | D11: Campeur | E11: =B11 | F11: Campista | G11: Campeggiatore | H11: 캠프보이 | I11: 露營少年 | J11: =IFERROR(__xludf.DUMMYFUNCTION("GOOGLETRANSLATE(I11,""zh_HANT"",""zh_HANS"")"),"露营少年")
A12: NAME_TC_CHAMPION-M | B12: =CONCATENATE(E12,"ion") | C12: チャンピオン | D12: Maître | E12: Champ | F12: Campeón | G12: =CONCATENATE(B12,"e") | H12: 챔피언 | I12: 冠軍 | J12: =IFERROR(__xludf.DUMMYFUNCTION("GOOGLETRANSLATE(I12,""zh_HANT"",""zh_HANS"")"),"冠军")
A13: NAME_TC_CHAMPION-F | B13: =B12 | C13: =C12 | D13: =D12 | E13: =E12 | F13: Campeona | G13: =CONCATENATE(G12,"ssa") | H13: =H12 | I13: =I12 | J13: =J12
A14: =CONCATENATE("NAME_TC_", SUBSTITUTE(UPPER(B14), " ", "")) | B14: Channeler | C14: きとうし | D14: Exorciste | E14: Exorzistin | F14: Exorcista | G14: =B45 | H14: 주술사 | I14: 祈禱師 | J14: =IFERROR(__xludf.DUMMYFUNCTION("GOOGLETRANSLATE(I14,""zh_HANT"",""zh_HANS"")"),"祈祷师")
A15: =CONCATENATE("NAME_TC_", SUBSTITUTE(UPPER(B15), " ", "")) | B15: Elite Four | C15: してんのう | D15: Conseil 4 | E15: Top Vier | F15: Alto Mando | G15: Superquattro | H15: 사천왕 | I15: 四天王 | J15: =I15
A16: =CONCATENATE("NAME_TC_", SUBSTITUTE(UPPER(B16), " ", "")) | B16: Engineer | C16: でんきやのオヤジ | D16: Mécano | E16: Elektriker | F16: Mecánico | G16: Meccanico | H16: 전기 작업원 | I16: 電工大叔 | J16: =IFERROR(__xludf.DUMMYFUNCTION("GOOGLETRANSLATE(I16,""zh_HANT"",""zh_HANS"")"),"电工大叔")
A17: =CONCATENATE("NAME_TC_", SUBSTITUTE(UPPER(B17), " ", "")) | B17: Fisherman | C17: つりびと | D17: Pêcheur | E17: Angler | F17: Pescador | G17: Pescatore | H17: 낚시꾼 | I17: 釣魚者 | J17: 垂钓者
A18: =CONCATENATE("NAME_TC_", SUBSTITUTE(UPPER(B18), " ", "")) | B18: Gambler | C18: ギャンブラー | D18: Croupier | E18: Rollenspieler | F18: Jugón | G18: Rischiatutto | H18: 갬블러 | I18: 賭徒 | J18: =IFERROR(__xludf.DUMMYFUNCTION("GOOGLETRANSLATE(I18,""zh_HANT"",""zh_HANS"")"),"赌徒")
A19: =CONCATENATE("NAME_TC_", SUBSTITUTE(UPPER(B19), " ", "")) | B19: Gentleman | C19: ジェントルマン | D19: =B19 | E19: =B19 | F19: Aristócrata | G19: Gentiluomo | H19: 신사 | I19: 紳士 | J19: =IFERROR(__xludf.DUMMYFUNCTION("GOOGLETRANSLATE(I19,""zh_HANT"",""zh_HANS"")"),"绅士")
A20: NAME_TC_GYMLEADER-M | B20: Gym Leader | C20: ジムリーダー | D20: Champion d'Arène | E20: Arenaleiter | F20: Líder de gimnasio | G20: Capopalestra | H20: 체육관 관장 | I20: 道館館主 | J20: =IFERROR(__xludf.DUMMYFUNCTION("GOOGLETRANSLATE(I20,""zh_HANT"",""zh_HANS"")"),"道馆馆主")
A21: NAME_TC_GYMLEADER-F | B21: =B20 | C21: =C20 | D21: Championne d'Arène | E21: =CONCATENATE(E20,"in") | F21: =F20 | G21: =G20 | H21: =H20 | I21: =I20 | J21: =J20
A22: =CONCATENATE("NAME_TC_", SUBSTITUTE(UPPER(B22), " ", "")) | B22: Hiker | C22: やまおとこ | D22: Montagnard | E22: Wanderer | F22: Montañero | G22: Montanaro | H22: 등산가 | I22: 登山男 | J22: =I22
A23: =CONCATENATE("NAME_TC_", SUBSTITUTE(UPPER(B23), " ", "")) | B23: Juggler | C23: ジャグラー | D23: Jongleur | E23: =D23 | F23: Malabarista | G23: Giocoliere | H23: 저글러 | I23: 雜耍藝人 | J23: =IFERROR(__xludf.DUMMYFUNCTION("GOOGLETRANSLATE(I23,""zh_HANT"",""zh_HANS"")"),"杂耍艺人")
A24: =CONCATENATE("NAME_TC_", SUBSTITUTE(UPPER(B24), " ", "")) | B24: Lass | C24: ミニスカート | D24: Fillette | E24: Göre | F24: Chica | G24: Teenager | H24: 짧은 치마 | I24: 迷你裙 | J24: =I24
A25: =CONCATENATE("NAME_TC_", SUBSTITUTE(UPPER(B25), " ", "")) | B25: Picnicker | C25: ピクニックガール | D25: Pique-Nique | E25: =B25 | F25: Dominguera | G25: Picnicker | H25: 피크닉걸 | I25: 野餐女孩 | J25: =I25
A26: NAME_TC_POKEMANIAC | B26: Poké Maniac | C26: かいじゅうマニア | D26: Pokémaniac | E26: =D26 | F26: Pokémaníaco | G26: Pokéfanatico | H26: 포켓몬 매니아 | I26: 怪獸狂 | J26: =IFERROR(__xludf.DUMMYFUNCTION("GOOGLETRANSLATE(I26,""zh_HANT"",""zh_HANS"")"),"怪兽狂")
A27: NAME_TC_PSYCHIC-M | B27: Psychic | C27: サイキッカー | D27: Kinésiste | E27: Seher | F27: Médium | G27: Sensitivo | H27: 초능력자 | I27: 超能力者 | J27: =I27
A28: NAME_TC_PSYCHIC-F | B28: =B27 | C28: =C27 | D28: =D27 | E28: =CONCATENATE(E27,"in") | F28: Médium | G28: =G27 | H28: =H27 | I28: =I27 | J28: =J27
A29: =CONCATENATE("NAME_TC_", SUBSTITUTE(UPPER(B29), " ", "")) | B29: Rival | C29: ライバル | D29: =B29 | E29: =G29 | F29: =B29 | G29: Rivale | H29: 라이벌 | I29: 勁敵 | J29: =IFERROR(__xludf.DUMMYFUNCTION("GOOGLETRANSLATE(I29,""zh_HANT"",""zh_HANS"")"),"劲敌")
A30: =CONCATENATE("NAME_TC_", SUBSTITUTE(UPPER(B30), " ", "")) | B30: Rocker | C30: でんきグループ | D30: Électricien | E30: Elektro-Musiker | F30: Técnico | G30: Tecnico del suono | H30: 전기그룹 | I30: 電氣搖滾團 | J30: =IFERROR(__xludf.DUMMYFUNCTION("GOOGLETRANSLATE(I30,""zh_HANT"",""zh_HANS"")"),"电气摇滚团")
A31: =CONCATENATE("NAME_TC_", SUBSTITUTE(UPPER(B31), " ", "")) | B31: Roughneck | C31: スキンヘッズ | D31: Loubard | E31: Raufbold | F31: Calvo | G31: Zuccapelata | H31: 빡빡이 | I31: 光頭男 | J31: =IFERROR(__xludf.DUMMYFUNCTION("GOOGLETRANSLATE(I31,""zh_HANT"",""zh_HANS"")"),"光头男")
A32: =CONCATENATE("NAME_TC_", SUBSTITUTE(UPPER(B32), " ", "")) | B32: Sailor | C32: ふなのり | D32: Marin | E32: Matrose | F32: Marinero | G32: Marinaio | H32: 선원 | I32: 水手 | J32: =I32
A33: NAME_TC_SCIENTIST-M | B33: Scientist | C33: けんきゅういん | D33: Scientifique | E33: Forscher | F33: Científico | G33: Scienziato | H33: 연구원 | I33: 研究員 | J33: =IFERROR(__xludf.DUMMYFUNCTION("GOOGLETRANSLATE(I33,""zh_HANT"",""zh_HANS"")"),"研究员")
A34: NAME_TC_SCIENTIST-F | B34: =B33 | C34: =C33 | D34: =D33 | E34: =CONCATENATE(E33,"in") | F34: Científica | G34: Scienziata | H34: =H33 | I34: =I33 | J34: =J33
A35: =CONCATENATE("NAME_TC_", SUBSTITUTE(UPPER(B35), " ", "")) | B35: Super Nerd | C35: りかけいのおとこ | D35: Intello | E35: Streber | F35: Cerebrito | G35: Cervellone | H35: 이과계의 남자 | I35: 理科男 | J35: =I35
A36: NAME_TC_SWIMMER-M | B36: Swimmer | C36: かいパンやろう | D36: Nageur | E36: Schwimmer | F36: Nadador | G36: Nuotatore | H36: 수영팬티 소년 | I36: 泳褲小伙子 | J36: =IFERROR(__xludf.DUMMYFUNCTION("GOOGLETRANSLATE(I36,""zh_HANT"",""zh_HANS"")"),"泳裤小伙子")
A37: NAME_TC_SWIMMER-F | B37: =B36 | C37: ビキニのおねえさん | D37: Nageuse | E37: Schwimmerin | F37: Nadadora | G37: Nuotatrice | H37: 비키니 아가씨 | I37: 比基尼姐姐 | J37: =I37
A38: =CONCATENATE("NAME_TC_", SUBSTITUTE(UPPER(B38), " ", "")) | B38: Tamer | C38: もうじゅうつかい | D38: Dompteur | E38: =D38 | F38: Domador | G38: Domatore | H38: 맹수 조련사 | I38: 馴獸師 | J38: =IFERROR(__xludf.DUMMYFUNCTION("GOOGLETRANSLATE(I38,""zh_HANT"",""zh_HANS"")"),"驯兽师")
A39: =CONCATENATE("NAME_TC_", SUBSTITUTE(UPPER(B39), " ", "")) | B39: Youngster | C39: たんぱんこぞう | D39: Gamin | E39: Knirps | F39: Joven | G39: Marmocchio | H39: 반바지 꼬마 | I39: 短褲小子 | J39: =IFERROR(__xludf.DUMMYFUNCTION("GOOGLETRANSLATE(I39,""zh_HANT"",""zh_HANS"")"),"短裤小子")
A40: =CONCATENATE("NAME_TC_", SUBSTITUTE(UPPER(B40), " ", "")) | B40: Boarder | C40: ボーダー | D40: Surfer | E40: Snowboarder | F40: Snow-boarder | G40: =E40 | H40: 보더 | I40: =IFERROR(__xludf.DUMMYFUNCTION("GOOGLETRANSLATE(J40,""zh_HANS"",""zh_HANT"")"),"單板玩家") | J40: 单板玩家
A41: =CONCATENATE("NAME_TC_", SUBSTITUTE(UPPER(B41), " ", "")) | B41: Firebreather | C41: ひふきやろう | D41: Crache-Feu | E41: Feuerspucker | F41: Comefuego | G41: Mangiafuoco | H41: 불놀이꾼 | I41: =IFERROR(__xludf.DUMMYFUNCTION("GOOGLETRANSLATE(J41,""zh_HANS"",""zh_HANT"")"),"噴火者") | J41: 喷火者
A42: NAME_TC_GUITARIST-M | B42: Guitarist | C42: ギタリスト | D42: Guitariste | E42: Gitarrist | F42: Guitarrista | G42: Chitarrista | H42: 기타리스트 | I42: 吉他手 | J42: =I42
A43: NAME_TC_GUITARIST-F | B43: =B42 | C43: =C42 | D43: =D42 | E43: =CONCATENATE(E42,"in") | F43: =F42 | G43: =G42 | H43: =H42 | I43: 吉她手 | J43: =I43
A44: =CONCATENATE("NAME_TC_", SUBSTITUTE(UPPER(B44), " ", "")) | B44: Kimono Girl | C44: まいこはん | D44: Kimono | E44: Kimono-Girl | F44: Chica Kimono | G44: =B44 | H44: 전통무용수 | I44: 和服女孩 | J44: =I44
A45: =CONCATENATE("NAME_TC_", SUBSTITUTE(UPPER(B45), " ", "")) | B45: Medium | C45: イタコ | D45: Médium | E45: =B45 | F45: Mentalista | G45: Sensitiva | H45: 무당 | I45: 神婆 | J45: =I45
A46: NAME_TC_POKEFAN | B46: Pokéfan | C46: だいすきクラブ | D46: =B46 | E46: =B46 | F46: Pokéfan | G46: Pokéfan | H46: 애호가클럽 | I46: 發燒友俱樂部 | J46: =IFERROR(__xludf.DUMMYFUNCTION("GOOGLETRANSLATE(I46,""zh_HANT"",""zh_HANS"")"),"发烧友俱乐部")
A47: NAME_TC_PkMnTRAINER-M | B47: Pokémon Trainer | C47: ポケモントレーナー | D47: Dresseur de Pokémon | E47: Pokémon-Trainer | F47: Entrenador Pokémon | G47: Allenatore di Pokémon | H47: 포켓몬 트레이너 | I47: 寶可夢訓練家 | J47: =IFERROR(__xludf.DUMMYFUNCTION("GOOGLETRANSLATE(I47,""zh_HANT"",""zh_HANS"")"),"宝可梦训练家")
A48: NAME_TC_PkMnTRAINER-F | B48: =B47 | C48: =C47 | D48: =D47 | E48: =E47 | F48: Entrenadora Pokémon | G48: Allenatrice di Pokémon | H48: =H47 | I48: =I47 | J48: =J47
A49: =CONCATENATE("NAME_TC_", SUBSTITUTE(UPPER(B49), " ", "")) | B49: Police Officer | C49: あまわりさん | D49: Policier | E49: Polizist | F49: Policía | G49: Guardia | H49: 경찰관 | I49: 警察先生 | J49: =I49
A50: =CONCATENATE("NAME_TC_", SUBSTITUTE(UPPER(B50), " ", "")) | B50: Sage | C50: ぼうず | D50: =B50 | E50: Weiser | F50: Pensador | G50: Saggio | H50: 수행자 | I50: =IFERROR(__xludf.DUMMYFUNCTION("GOOGLETRANSLATE(J50,""zh_HANS"",""zh_HANT"")"),"和尚") | J50: 和尚
A51: =CONCATENATE("NAME_TC_", SUBSTITUTE(UPPER(B51), " ", "")) | B51: Schoolboy | C51: スクールボーイ | D51: Écolier | E51: Schüler | F51: Escolar | G51: Studende | H51: 스쿨보이 | I51: 男學生 | J51: =IFERROR(__xludf.DUMMYFUNCTION("GOOGLETRANSLATE(I51,""zh_HANT"",""zh_HANS"")"),"男学生")
A52: NAME_TC_SKIER-M | B52: Skier | C52: スキーヤー | D52: Skieur | E52: Skifahrer | F52: Esquiador | G52: Sciatore | H52: 스키선수 | I52: 滑雪者 | J52: =I52
A53: NAME_TC_SKIER-F | B53: =B52 | C53: =C52 | D53: Skieuse | E53: =E52 | F53: Esquiadora | G53: Sciatrice | H53: =H52 | I53: =I52 | J53: =J52
A54: =CONCATENATE("NAME_TC_", SUBSTITUTE(UPPER(B54), " ", "")) | B54: Teacher | C54: せんせい | D54: Prof. | E54: Lehrerin | F54: Profesora | G54: Insegnante | H54: 선생님 | I54: 老師 | J54: =IFERROR(__xludf.DUMMYFUNCTION("GOOGLETRANSLATE(I54,""zh_HANT"",""zh_HANS"")"),"老师")
A55: =CONCATENATE("NAME_TC_", SUBSTITUTE(UPPER(B55), " ", "")) | B55: Twins | C55: ふたごちゃん | D55: Jumelles | E55: Zwillinge | F55: Gemelas | G55: Gemelle | H55: 쌍둥이 | I55: 雙胞胎 | J55: =IFERROR(__xludf.DUMMYFUNCTION("GOOGLETRANSLATE(I55,""zh_HANT"",""zh_HANS"")"),"双胞胎")
A56: =CONCATENATE("NAME_TC_", SUBSTITUTE(UPPER(B56), " ", "")) | B56: Mystery Man | C56: なぞのせいねん | D56: Mec Mystère | E56: Mystiker | F56: Enigmático | G56: Fantallenatore | H56: 수수께끼 청년 | I56: =IFERROR(__xludf.DUMMYFUNCTION("GOOGLETRANSLATE(J56,""zh_HANS"",""zh_HANT"")"),"謎之少年") | J56: 謎之少年
A57: =CONCATENATE("NAME_TC_", SUBSTITUTE(UPPER(B57), " ", "")) | B57: Aroma Lady | C57: アロマなおねえちゃん | D57: Aromathérapeute | E57: Aromalady | F57: Señorita aroma | G57: Profumina | H57: 아로마 아가씨 | I57: 香氛姐姐 | J57: =I57
A58: =CONCATENATE("NAME_TC_", SUBSTITUTE(UPPER(B58), " ", "")) | B58: Battle Girl | C58: バトルガール | D58: Combattante | E58: Kämpferin | F58: Luchadora | G58: Combat Girl | H58: 배틀걸 | I58: 對戰少女 | J58: =IFERROR(__xludf.DUMMYFUNCTION("GOOGLETRANSLATE(I58,""zh_HANT"",""zh_HANS"")"),"对战少女")
A59: =CONCATENATE("NAME_TC_", SUBSTITUTE(UPPER(B59), " ", "")) | B59: Bug Maniac | C59: こんちゅうマニア | D59: Entomomaniac | E59: Käfermaniac | F59: Bichomaníaco | G59: Insettologo | H59: 곤충마니아 | I59: 昆蟲狂 | J59: =IFERROR(__xludf.DUMMYFUNCTION("GOOGLETRANSLATE(I59,""zh_HANT"",""zh_HANS"")"),"昆虫狂")
A60: =CONCATENATE("NAME_TC_", SUBSTITUTE(UPPER(B60), " ", "")) | B60: Collector | C60: ポケモンコレクター | D60: Collectionneur | E60: Pokémon-Sammler | F60: Pokécolector | G60: Cercapokémon | H60: 포켓몬 컬렉터 | I60: 寶可夢收藏家 | J60: =IFERROR(__xludf.DUMMYFUNCTION("GOOGLETRANSLATE(I60,""zh_HANT"",""zh_HANS"")"),"宝可梦收藏家")
A61: =CONCATENATE("NAME_TC_", SUBSTITUTE(UPPER(B61), " ", "")) | B61: Dragon Tamer | C61: ドラゴンつかい | D61: Dracologue | E61: Drachenprofi | F61: Domadragón | G61: Domadraghi | H61: 드래곤 조련사 | I61: 馴龍師 | J61: =IFERROR(__xludf.DUMMYFUNCTION("GOOGLETRANSLATE(I61,""zh_HANT"",""zh_HANS"")"),"驯龙师")
A62: NAME_TC_EXPERT-M | B62: Expert | C62: たつじん | D62: =B62 | E62: =D63 | F62: Pokéabu | G62: Specialista | H62: 달인 | I62: 達人 | J62: =I62
A63: NAME_TC_EXPERT-F | B63: =B62 | C63: =C62 | D63: =CONCATENATE(D62,"e") | E63: =CONCATENATE(D62,"in") | F63: Pokéabu | G63: =G62 | H63: =H62 | I63: =I62 | J63: =J62
A64: =CONCATENATE("NAME_TC_", SUBSTITUTE(UPPER(B64), " ", "")) | B64: Hex Maniac | C64: オカルトマニア | D64: Mystimaniac | E64: Hexe | F64: Bruja | G64: Streghetta | H64: 오컬트마니아 | I64: 靈異迷 | J64: =IFERROR(__xludf.DUMMYFUNCTION("GOOGLETRANSLATE(I64,""zh_HANT"",""zh_HANS"")"),"灵异迷")
A65: =CONCATENATE("NAME_TC_", SUBSTITUTE(UPPER(B65), " ", "")) | B65: Interviewers | C65: インタビュアー | D65: Journalistes | E65: Interviewer | F65: Periodistas | G65: Reporter | H65: 인터뷰어 | I65: 採訪者 | J65: =IFERROR(__xludf.DUMMYFUNCTION("GOOGLETRANSLATE(I65,""zh_HANT"",""zh_HANS"")"),"采访者")
A66: =CONCATENATE("NAME_TC_", SUBSTITUTE(UPPER(B66), " ", "")) | B66: Kindler | C66: キャンプファイヤー | D66: Saltimbanque | E66: Hitzkopf | F66: Prendefuegos | G66: Brandifuoco | H66: 캠프파이어 | I66: 營火專家 | J66: =IFERROR(__xludf.DUMMYFUNCTION("GOOGLETRANSLATE(I66,""zh_HANT"",""zh_HANS"")"),"营火专家")
A67: =CONCATENATE("NAME_TC_", SUBSTITUTE(UPPER(B67), " ", "")) | B67: Lady | C67: おじょうさま | D67: Mademoiselle | E67: =B67 | F67: Damisela | G67: =B67 | H67: 아기씨 | I67: 千金小姐 | J67: =I67
A68: =CONCATENATE("NAME_TC_", SUBSTITUTE(UPPER(B68), " ", "")) | B68: Ninja Boy | C68: ニンジャごっこ | D68: Ninja Amateur | E68: Ninjajunge | F68: Chico ninja | G68: =B68 | H68: 닌자놀이 | I68: 忍者小子 | J68: =I68
A69: =CONCATENATE("NAME_TC_", SUBSTITUTE(UPPER(B69), " ", "")) | B69: Old Couple | C69: きんこんしき | D69: Vieux Couple | E69: Altes Paar | F69: Pareja mayor | G69: Coppiarzilla | H69: 금혼식부부 | I69: 金婚夫妻 | J69: =I69
A70: =CONCATENATE("NAME_TC_", SUBSTITUTE(UPPER(B70), " ", "")) | B70: Parasol Lady | C70: パラソルおねえさん | D70: Sœur Parasol | E70: Schirmdame | F70: Dama parasol | G70: Ombrellina | H70: 파라솔아가씨 | I70: 陽傘姐姐 | J70: =IFERROR(__xludf.DUMMYFUNCTION("GOOGLETRANSLATE(I70,""zh_HANT"",""zh_HANS"")"),"阳伞姐姐")
A71: NAME_TC_PkMnBREEDER-M | B71: Pokémon Breeder | C71: ポケモンブリーダー | D71: Éleveur | E71: Pokémon-Züchter | F71: Criapokémon | G71: Allevapokémon | H71: 포켓몬 브리더 | I71: 寶可夢培育家 | J71: =IFERROR(__xludf.DUMMYFUNCTION("GOOGLETRANSLATE(I71,""zh_HANT"",""zh_HANS"")"),"宝可梦培育家")
A72: NAME_TC_PkMnBREEDER-F | B72: =B71 | C72: =C71 | D72: Éleveuse | E72: =CONCATENATE(E71,"in") | F72: Criapokémon | G72: =G71 | H72: =H71 | I72: =I71 | J72: =J71
A73: NAME_TC_PkMnRANGER | B73: Pokémon Ranger | C73: ポケモンレンジャー | D73: =B73 | E73: Pokémon-Ranger | F73: Pokémon Ranger | G73: =B73 | H73: 포켓몬 레인저 | I73: 寶可夢巡護員 | J73: =IFERROR(__xludf.DUMMYFUNCTION("GOOGLETRANSLATE(I73,""zh_HANT"",""zh_HANS"")"),"宝可梦巡护员")
A74: =CONCATENATE("NAME_TC_", SUBSTITUTE(UPPER(B74), " ", "")) | B74: Rich Boy | C74: おぼっちゃま | D74: Richard | E74: Schnösel | F74: Niño bien | G74: Elegantone | H74: 도련님 | I74: 富家少爺 | J74: =IFERROR(__xludf.DUMMYFUNCTION("GOOGLETRANSLATE(I74,""zh_HANT"",""zh_HANS"")"),"富家少爷")
A75: =CONCATENATE("NAME_TC_", SUBSTITUTE(UPPER(B75), " ", "")) | B75: Ruin Maniac | C75: いせきマニア | D75: Ruinemaniac | E75: Ruinenmaniac | F75: Ruinamaníaco | G75: Scoprirovine | H75: 유적마니아 | I75: 遺跡迷 | J75: =IFERROR(__xludf.DUMMYFUNCTION("GOOGLETRANSLATE(I75,""zh_HANT"",""zh_HANS"")"),"遗迹迷")
A76: =CONCATENATE("NAME_TC_", SUBSTITUTE(UPPER(B76), " ", "")) | B76: Sis & Bro | C76: うみきょうだい | D76: Frère et Sœur | E76: Geschwister | F76: Hermanos | G76: Fratellini | H76: 바다남매 | I76: 海上姐弟 | J76: =I76
A77: =CONCATENATE("NAME_TC_", SUBSTITUTE(UPPER(B77), " ", "")) | B77: Teammates | C77: センパイとコウハイ | D77: Senior et Junior | E77: =G77 | F77: Estudiantes | G77: Senior & Junior | H77: 선배&후배 | I77: 學姊與學妹 | J77: =IFERROR(__xludf.DUMMYFUNCTION("GOOGLETRANSLATE(I77,""zh_HANT"",""zh_HANS"")"),"学姊与学妹")
A78: =CONCATENATE("NAME_TC_", SUBSTITUTE(UPPER(B78), " ", "")) | B78: Triathlete | C78: トライアスリート | D78: Triathlète | E78: Triathlet | F78: Triatleta | G78: =F78 | H78: 트라이애슬리트 | I78: 鐵人三項運動員 | J78: =I78
A79: NAME_TC_TUBER-M | B79: Tuber | C79: うきわボーイ | D79: Garçon à la Bouée | E79: Planscher | F79: Playero | G79: Ciambellino | H79: 튜브보이 | I79: 泳圈男孩 | J79: =I79
A80: NAME_TC_TUBER-F | B80: =B79 | C80: うきわガール | D80: Fille à la Bouée | E80: =E79 | F80: Playera | G80: Ciambellina | H80: 튜브걸 | I80: 泳圈女孩 | J80: =I80
A81: NAME_TC_WORKER-M | B81: Worker | C81: さぎょういん | D81: Ouvrier | E81: Arbeiter | F81: Operario | G81: Lavoratore | H81: 작업원 | I81: 工人 | J81: =I81
A82: NAME_TC_WORKER-F | B82: =B81 | C82: =C81 | D82: Ouvrière | E82: Arbeiterin | F82: Operaria | G82: Lavoratrice | H82: =H81 | I82: =I81 | J82: =J81
A83: =CONCATENATE("NAME_TC_", SUBSTITUTE(UPPER(B83), " ", "")) | B83: Young Couple | C83: ラブラブカップル | D83: Jeune Couple | E83: Junges Glück | F83: Pareja joven | G83: Coppietta | H83: 러브러브커플 | I83: 熱戀情侶 | J83: =IFERROR(__xludf.DUMMYFUNCTION("GOOGLETRANSLATE(I83,""zh_HANT"",""zh_HANS"")"),"热恋情侣")
A84: =CONCATENATE("NAME_TC_", SUBSTITUTE(UPPER(B84), " ", "")) | B84: Crush Kin | C84: かくとうきょうだい | D84: Duo Baston | E84: Mühlensippe | F84: Dúo fuerte | G84: Duo Lotta | H84: 격투남매 | I84: =IFERROR(__xludf.DUMMYFUNCTION("GOOGLETRANSLATE(J84,""zh_HANS"",""zh_HANT"")"),"格鬥姐弟") | J84: 格斗姐弟
A85: NAME_TC_FRONTIERBRAIN | B85: Frontier Brain | C85: フロンティアブレーン | D85: Meneur de Zone | E85: Kampfkoryphäen | F85: As del Frente Batalla | G85: Asso Lotta | H85: 프런티어 브레인 | I85: 開拓之腦 | J85: =IFERROR(__xludf.DUMMYFUNCTION("GOOGLETRANSLATE(I85,""zh_HANT"",""zh_HANS"")"),"开拓之脑")
A86: =CONCATENATE("NAME_TC_", SUBSTITUTE(UPPER(B86), " ", "")) | B86: Ace Duo | C86: エリートコンビ | D86: Top Duo | E86: Ass-Duo | F86: Dúo guay | G86: Fantaduo | H86: 엘리트콤비 | I86: 精英組合 | J86: =IFERROR(__xludf.DUMMYFUNCTION("GOOGLETRANSLATE(I86,""zh_HANT"",""zh_HANS"")"),"精英组合")
A87: NAME_TC_ARTIST-M | B87: Artist | C87: げいじゅつか | D87: =CONCATENATE(B87,"e") | E87: Künstler | F87: =CONCATENATE(B87,"a") | G87: =F87 | H87: 예술가 | I87: 藝術家 | J87: =IFERROR(__xludf.DUMMYFUNCTION("GOOGLETRANSLATE(I87,""zh_HANT"",""zh_HANS"")"),"艺术家")
A88: NAME_TC_ARTIST-F | B88: =B87 | C88: =C87 | D88: =D87 | E88: =CONCATENATE(E87,"in") | F88: =F87 | G88: =G87 | H88: =H87 | I88: =I87 | J88: =J87
A89: NAME_TC_BELLEANDPA | B89: Belle & Pa | C89: ぼくじょうおやこ | D89: Fille & Père | E89: Mädel und Papa | F89: Padre e hija | G89: Ranch Family | H89: =H101 | I89: =I101 | J89: =J101
A90: =CONCATENATE("NAME_TC_", SUBSTITUTE(UPPER(B90), " ", "")) | B90: Cameraman | C90: カメラマン | D90: Caméraman | E90: Kameramann | F90: Cámara | G90: =B90 | H90: 카메라맨 | I90: 攝影師 | J90: =IFERROR(__xludf.DUMMYFUNCTION("GOOGLETRANSLATE(I90,""zh_HANT"",""zh_HANS"")"),"摄影师")
A91: =CONCATENATE("NAME_TC_", SUBSTITUTE(UPPER(B91), " ", "")) | B91: Cowgirl | C91: カウガール | D91: =B91 | E91: =B91 | F91: Vaquera | G91: =B91 | H91: 카우걸 | I91: 牛仔女孩 | J91: =I91
A92: NAME_TC_CLOWN | B92: Clown | C92: ピエロ | D92: Arlequin | E92: =B92 | F92: Payaso | G92: =B92 | H92: 피에로 | I92: 小丑 | J92: =I92
A93: NAME_TC_CYCLIST-M | B93: Cyclist | C93: サイクリング | D93: =CONCATENATE(B93,"e") | E93: =B5 | F93: Ciclista | G93: =F93 | H93: 사이클링 | I93: 自行車手 | J93: =IFERROR(__xludf.DUMMYFUNCTION("GOOGLETRANSLATE(I93,""zh_HANT"",""zh_HANS"")"),"自行车手")
A94: NAME_TC_CYCLIST-F | B94: =B93 | C94: =C93 | D94: =D93 | E94: =CONCATENATE(E93,"in") | F94: Ciclista | G94: =G93 | H94: =H93 | I94: =I93 | J94: =J93
A95: =CONCATENATE("NAME_TC_", SUBSTITUTE(UPPER(B95), " ", "")) | B95: Idol | C95: アイドル | D95: Idole | E95: =B95 | F95: Famosa | G95: Pop Star | H95: 아이돌 | I95: 偶像明星 | J95: =I95
